Workbook

Sheet 說明
A1: 澳洲可出租資料中心盤點
A2: 資料日期：2026-10-03 ｜ 收錄門檻：5 MW 以上 ｜ 範圍：澳洲 8 個州與領地的可出租資料中心
A4: 盤點範圍
A5: 收錄條件 | B5: 同時符合：(1) 可由第三方承租（託管、批發型、建置型／powered shell）；(2) 專案或獨立分期容量 5 MW 以上（未公布 MW 但明顯為大型園區者亦收錄，容量欄顯示「未公布」）；(3) 狀態為施工中、已核准尚未動工、已送件審查中，或近期完工／已營運但仍有 5 MW 以上可租容量或擴建。
A6: 不收錄 | B6: 雲端巨頭自建或終端使用者自用（Amazon/AWS、Microsoft、Google、Meta、Oracle 等）、不足 5 MW、已撤案或遭否決者，列於「排除清單」僅供稽核。已預租給特定雲端業者或 AI 公司的第三方專案不屬於自建，仍收錄並在「已知租戶」註明。
A7: 資料日期 | B7: 2026-10-03。狀態與完工時間以此日期可取得的公開資訊為準。
A8: 涵蓋地區 | B8: 新南威爾斯州、維多利亞州、昆士蘭州、西澳州、南澳州、首都領地、塔斯馬尼亞州、北領地；零筆的州仍有獨立工作表，列出查過的來源。
A10: 工作表導覽（點選名稱可跳轉）
A11: 總覽 | B11: 關鍵指標、各州 × 狀態、各州 × 完工時間窗、各州容量（只計主清單），另有觀察名單統計與重點發現；統計皆為引用「專案清單」的即時公式。
A12: 專案清單 | B12: 全部收錄專案的完整欄位，依完工時間窗 → 狀態 → 容量排序；可用表頭箭頭篩選。
A13: 各州工作表 | B13: 每州一張精簡表：NSW 新南威爾斯、VIC 維多利亞、QLD 昆士蘭、WA 西澳、SA 南澳、ACT 首都領地、TAS 塔斯馬尼亞、NT 北領地。零筆的州列出搜尋紀錄、資料缺口與代理備註。
A14: 完工時間窗 | B14: 依可用時間分組，附各組已知 MW 小計。
A15: 差異與待確認 | B15: 跨來源差異、專案層級差異與低可信度專案，決策前請先看。
A16: 排除清單 | B16: 不符收錄條件的項目與原因，僅供稽核。
A17: 來源 | B17: 所有引用網址，分類為政府／營運商／媒體／其他，並列出引用的專案。
A18: 搜尋紀錄 | B18: 各州、各代理的搜尋紀錄、資料缺口與備註。
A20: 狀態定義（狀態欄的顏色）
A21: 施工中 | B21: 已有具日期的動工證據：開工通知、施工環境管理計畫（CEMP）核准、營運商新聞稿、封頂等。
A22: 已核准、尚未動工 | B22: 已取得規劃許可或開發許可，尚無施工證據。
A23: 近期完工（仍有容量） | B23: 2025-07 以後通電或啟用，且仍有 5 MW 以上未出租或擴建容量。
A24: 已營運（有餘裕／擴建） | B24: 已營運的可租設施，有可信公開證據顯示 5 MW 以上未出租容量，或正進行 5 MW 以上擴建。
A25: 已送件、審查中 | B25: 已公開宣布並正式向規劃主管機關送件（SEARs、EIS、DA、許可申請），尚未核准；僅有傳聞而未送件者不收錄。
A27: 完工時間窗
A28: 已可用／營運中 | B28: 已營運或已交付。
A29: 2026 Q4 – 2027 Q2 | B29: 預計 2026 年 10 月至 2027 年 6 月完工或啟用。
A30: 2027 下半年 | B30: 預計 2027 年 7 月至 12 月。
A31: 2028 年以後 | B31: 預計 2028 年或更晚。
A32: 完工日未公布 | B32: 尚無可靠來源公布完工日期。
A33: 判定方式 | B33: 由彙整程式依「預計完工（原文）」與狀態推得；每個專案的判定依據列在「完工時間窗」工作表的「時間窗依據」欄，並附在「專案清單」完工時間窗欄的儲存格註解。FY 為澳洲會計年度（7 月 1 日起算），例如 FY27 = 2026-07 至 2027-06。
A35: 可租判斷
A36: 可租 | B36: 營運商明確以託管或批發方式對第三方出租。
A37: 大概可租 | B37: 開發商或營運商的模式通常對外出租，但尚未公布租戶或出租條件。
A38: 待確認 | B38: 出租模式不明或可能為單一客戶專用，需向營運商確認。
A40: 分級：主清單與觀察名單
A41: 主清單 | B41: 可租判斷為「可租」或「大概可租」的專案。總覽的主要統計、各組小計與各州摘要的主數字只計主清單。
A42: 觀察名單 (出租性待確認) | B42: 可租判斷為「待確認」的專案，例如出售 GPU 算力而非出租機房空間的垂直整合 AI 雲業者、尚未核准且仍在等待主力客戶的專案、首期可用容量不足 5 MW 的場址，或由彙整者另行判定者。不計入主要統計，但保留顯示，讓每州都看得到現有專案；原因見「分級說明」欄。
A44: 可信度（字色）
A45: 高 | B45: 已開啟並閱讀具日期的政府或營運商一手來源。
A46: 中 | B46: 有可信的產業媒體報導，或有一手來源但未開啟原文。
A47: 低 | B47: 僅有聚合網站或搜尋摘要，需再查證才能作為依據。
A49: 容量口徑（MW）
A50: IT 負載 | B50: 可供伺服器使用的 IT 電力，最接近租戶可用容量。
A51: 關鍵負載 | B51: 關鍵負載（critical load），通常接近 IT 負載。
A52: 銘牌容量 | B52: 設計或設施總容量，可能包含冷卻等非 IT 用電。
A53: 變電容量（MVA） | B53: 電網接入或變電站容量，單位為 MVA，不等於 IT MW。
A54: 耗電量 | B54: 申請文件所列的用電量。
A55: 口徑不明 | B55: 來源未說明口徑。
A56: 重要提醒 | B56: 「容量 MW」欄混合了 IT 負載、銘牌容量與變電容量（MVA）等不同口徑，彼此不能直接比較，各處的 MW 加總僅供量級參考；洽談或報價前請向營運商確認口徑。容量未公布者顯示「未公布」，不計入任何加總，另以件數呈現。
A58: 座標精度
A59: 來源提供 | B59: 座標取自可靠來源（規劃文件地圖、官方頁面等）。
A60: 門牌級 | B60: 地理編碼對到門牌號碼。
A61: 街道級 | B61: 只對到街道，位置可能偏離數百公尺。
A62: 郊區級（近似） | B62: 以郊區或州的中心點代替，地圖位置僅供參考。
A63: 儲存格註解 | B63: 「專案清單」座標精度欄的註解記錄地理編碼方式（例如門牌比對或郊區中心點）。
A65: 顏色圖例
A66: 表頭 | B66: 深青色底、白色粗體字。
A67: 區段標題 | B67: 淺青色底，用來分隔同一工作表內的區塊。
A68: 狀態 | B68: 狀態欄以淡色填滿、深色字標示：綠＝施工中、琥珀＝已核准尚未動工、藍＝近期完工、紫＝已營運有餘裕、灰＝已送件審查中。
A69: 可信度 | B69: 字色：綠＝高、琥珀＝中、紅＝低。
A70: 觀察名單列 | B70: 斜體灰字、淺灰底，表示次要資訊；狀態欄仍保留狀態色。
A71: 超連結 | B71: 藍色底線文字可點擊開啟。
A72: 提示 | B72: 需要特別注意的說明（例如零筆州、排除清單）。
A73: 工作表標籤 | B73: 灰＝說明；深青＝總覽與完工時間窗；綠＝專案清單；淺藍＝各州；琥珀＝差異與待確認、排除清單；紫＝來源與搜尋紀錄。
A75: 閱讀建議
A76: 1. | B76: 先看「總覽」的重點與統計，再到「專案清單」用表頭箭頭依州、狀態、完工時間窗、可信度篩選。
A77: 2. | B77: 各州工作表是精簡版；完整欄位與全部來源網址在「專案清單」。
A78: 3. | B78: 「容量 MW」顯示「未公布」者不計入加總；總覽另列「容量未公布」件數。
A79: 4. | B79: 斜體灰底列是觀察名單（出租性待確認），不計入主要統計；用「分級」欄篩選可只看主清單。
A80: 5. | B80: 來源欄每行一個網址，第一個網址可直接點擊；其餘網址可複製開啟，或到「來源」工作表逐一點擊。
A81: 6. | B81: 「Google 地圖」依座標開啟；座標精度為郊區級者僅為近似位置。
A82: 7. | B82: 決策或報價前，請先看「差異與待確認」：跨來源數字不一致與低可信度專案都列在那裡。
A83: 8. | B83: 「排除清單」只用來證明搜索涵蓋範圍，不屬於盤點清單。
A84: 9. | B84: 本檔公式在開啟時自動計算；若從電子郵件或網路開啟而進入「受保護的檢視」，請按「啟用編輯」，統計數字才會顯示。
A86: 資料來源層級（由高至低）
A87: 1. 政府 | B87: 規劃入口與登記冊（NSW Planning Portal、Planning Victoria 部長許可登記冊、各區政府 DA 系統、PlanSA、WA DAP／WAPC、ACT DA 登記冊、昆士蘭 Coordinator-General／SARA、塔州與北領地規劃系統）、部長新聞稿、EPBC 申報。
A88: 2. 營運商 | B88: 營運商與開發商官方網站、ASX 公告。
A89: 3. 產業媒體 | B89: DatacenterDynamics、W.Media、The Urban Developer、AFR、Capital Brief、InnovationAus 等。
A90: 4. 聚合網站 | B90: Baxtel、DatacenterMap、RenewMap 等只作線索，不單獨作為狀態或完工日依據；其 MW 多為銘牌容量或 MVA。
A91: 原則 | B91: 政府 > 營運商 > 產業媒體 > 聚合網站。單一來源說「施工中」不足為憑，需有具日期的具體事件。
A93: 研究方法
A94: 1. | B94: 納入條件：可出租（託管、批發、裸殼、powered shell、build-to-suit）、容量 5 MW 以上（或首期 5 MW 以上）、狀態為施工中、已核准、近期完工仍有容量、營運中且有擴建、或已向規劃機關正式送件。
A95: 2. | B95: 排除條件：雲端巨頭自建（Amazon、AWS、Microsoft、Google、Meta、Oracle 等）、不足 5 MW、已撤案或否決、只有構想而未正式送件。排除項目列在 Excel『排除清單』分頁，供稽核。
A96: 3. | B96: 分級：主清單＝可租或大概可租；觀察名單＝出租性待確認（垂直整合 AI 雲、等待基石客戶、營運商未證實、信心低）。觀察名單不計入標題數字。
A97: 4. | B97: 證據順序：政府（規劃入口、許可登記冊、DA 登記）＞營運商官網與 ASX 公告＞專業媒體＞聚合站（Baxtel、RenewMap、ITK，只當線索）。NSW 的『已動工』判斷來自規劃入口『核准後文件』中的開工通知、施工環管計畫核准信等。
A98: 5. | B98: 工作方式：18 個 Sonnet 搜索代理分州搜索，我（Claude）對關鍵項目回頭讀政府文件與營運商原文獨立驗證，並以人工裁決修正了多處代理之間的矛盾（例如 3 Davis Road 的歸屬、NEXTDC D2／SC2 只有 1–1.5 MW 在建、Keppel Hazelwood 尚未送件）。
A99: 6. | B99: 座標：50 筆取自來源，其餘由 OpenStreetMap Nominatim 補上；精度分為來源提供、門牌級、街道級、郊區級（近似），地圖上近似者以虛線外框標示。
A101: 注意事項
A102: 1. | B102: 搜索期間 WebSearch 額度（200 次）中途用盡，之後改用新聞 RSS 與直接抓取官方頁面，覆蓋面較薄；Wyndham、Latrobe、Monash 等區政府入口需登入、昆州 Coordinator-General／SARA／EDQ、PlanSA、NT 與塔州部分政府網站被擋，這些地方可能有漏網之魚。
A103: 2. | B103: MW 口徑不一：IT 負載、關鍵負載、銘牌容量、MVA、耗電量混用，標題加總只能當數量級參考，不可當交付容量。
A104: 3. | B104: 完工日多數來自營運商自述、顧問文件或聚合站，不是施工合約日期；僅聚合站提供的年份已標為未公布或註明。
A105: 4. | B105: 公開資料看不到任何一棟的『未租區塊』與預租比例，也看不到 CDC 對非政府外國商業租戶是否開放；這些必須直接詢問營運商。
A106: 5. | B106: 一般的託管或租賃合約通常不涉及外資審查，但長期土地租賃、自建或取得土地權益可能觸發；本報告不構成法律意見，請向澳洲律師確認。
A107: 6. | B107: 底圖使用 Esri 灰階圖磚（免金鑰、需標示出處）；對外商業使用前請確認其條款。

Sheet 總覽
A1: 澳洲可出租資料中心盤點：總覽
A2: 資料日期：2026-10-03 ｜ 主要統計只計主清單，觀察名單另列 ｜ 數字皆為引用「專案清單」的即時公式
A4: 可租、5 MW 以上、而且真的在蓋的專案只有 15 筆；落在 2026 Q4 – 2027 Q2 交付的只有 5 筆，且多半已預售或尚待營運商確認。
A5: 本次盤點由 18 個搜索代理分州地毯式搜索（NSW、VIC 各 3 個角度，其餘各州各 2 個），再由我對關鍵項目回頭讀政府文件與營運商原文做獨立驗證。結果共 79 筆：主清單 60 筆（可租或大概可租）、觀察名單 19 筆（出租性待確認）；另有 190 筆經查證後排除，其中雲端巨頭自建 21 筆、不足 5 MW 的 45 筆、已撤案 9 筆。每一筆都附地址與地圖座標：72 筆有完整門牌，其餘 7 筆只到街道、郊區或區域（例如 Minchinbury、Mawson Lakes、Project Ares），地圖上以虛線外框標示為近似。
A6: 主清單 60 筆裡，施工中 15 筆、已核准尚未動工 16 筆、已正式送件審查中 26 筆、已營運或近期完工 3 筆。落在你要的 2026 Q4 – 2027 Q2 時間窗的有 5 筆：GreenSquareDC SYD1 第一期（雪梨 Norwest，約 15 MW）、STACK MEL01C/D（墨爾本 Truganina，各 54 MW）、STACK MEL02（252 MW）、Vantage MEL1（Tullamarine，64 MW）、CDC Maddington 第一棟（Perth，約 34 MW，2027 年 1 月）。另外 Macquarie IC3 Super West 首期 6 MW 和 Cloud Carrier 的 Southern Highlands DB1（28 MW 裸殼）已經可用。
A7: 真正的限制不在『有沒有在蓋』，而在『有沒有剩』。NEXTDC 自己的 FY26 簡報顯示，NSW／ACT 的已簽約容量是已建成容量的 306%、VIC 是 261%；CDC 的容量多為長約預簽，主要服務政府與關鍵基礎設施客戶。公開資料看不到任何一棟的未租區塊，必須直接向營運商詢問。
A8: 各州概況：NSW（主清單 33 筆）與 VIC（21 筆）佔絕大多數；QLD、WA、ACT 各 2 筆；SA、TAS、NT 沒有已確認可租的專案，只有觀察名單（DigiCo 阿德雷德、DCI ADL03、IREN Bundey、Firmus 塔斯馬尼亞三案、Energy North 的 Project Ares），它們不是出租機房空間，或尚無核准與客戶。
A10: 關鍵指標（只計主清單）
B11: 主清單專案（件） | C11: 已知容量合計（MW） | D11: 容量未公布（件） | E11: 可信度「高」（件） | F11: 施工中（件） | G11: 2027 Q2 前可用（件） | H11: 另有觀察名單（件）
B12: =COUNTIFS(專案清單!$R$2:$R$80,"主清單") -> 60 | C12: =SUMIFS(專案清單!$M$2:$M$80,專案清單!$R$2:$R$80,"主清單") -> 14195.6 | D12: =COUNTIFS(專案清單!$M$2:$M$80,"未公布",專案清單!$R$2:$R$80,"主清單") -> 4 | E12: =COUNTIFS(專案清單!$AD$2:$AD$80,"高",專案清單!$R$2:$R$80,"主清單") -> 46 | F12: =COUNTIFS(專案清單!$Q$2:$Q$80,"施工中",專案清單!$R$2:$R$80,"主清單") -> 15 | G12: =COUNTIFS(專案清單!$X$2:$X$80,"已可用／營運中",專案清單!$R$2:$R$80,"主清單")+COUNTIFS(專案清單!$X$2:$X$80,"2026 Q4 – 2027 Q2",專案清單!$R$2:$R$80,"主清單") -> 8 | H12: =COUNTIFS(專案清單!$R$2:$R$80,"觀察名單 (出租性待確認)") -> 19
B13: ="另有排除項目 "&COUNTA(排除清單!$A$5:$A$194)&" 件（僅供稽核，見「排除清單」）" -> 另有排除項目 190 件（僅供稽核，見「排除清單」）
A15: 各州 × 狀態（主清單件數）
A16: 州 | B16: 州名 | C16: 施工中 | D16: 已核准、尚未動工 | E16: 近期完工（仍有容量） | F16: 已營運（有餘裕／擴建） | G16: 已送件、審查中 | H16: 合計
A17: NSW | B17: 新南威爾斯州 | C17: =COUNTIFS(專案清單!$B$2:$B$80,$B17,專案清單!$Q$2:$Q$80,C$16,專案清單!$R$2:$R$80,"主清單") -> 6 | D17: =COUNTIFS(專案清單!$B$2:$B$80,$B17,專案清單!$Q$2:$Q$80,D$16,專案清單!$R$2:$R$80,"主清單") -> 10 | E17: =COUNTIFS(專案清單!$B$2:$B$80,$B17,專案清單!$Q$2:$Q$80,E$16,專案清單!$R$2:$R$80,"主清單") -> 1 | F17: =COUNTIFS(專案清單!$B$2:$B$80,$B17,專案清單!$Q$2:$Q$80,F$16,專案清單!$R$2:$R$80,"主清單") -> 2 | G17: =COUNTIFS(專案清單!$B$2:$B$80,$B17,專案清單!$Q$2:$Q$80,G$16,專案清單!$R$2:$R$80,"主清單") -> 14 | H17: =SUM(C17:G17) -> 33
A18: VIC | B18: 維多利亞州 | C18: =COUNTIFS(專案清單!$B$2:$B$80,$B18,專案清單!$Q$2:$Q$80,C$16,專案清單!$R$2:$R$80,"主清單") -> 7 | D18: =COUNTIFS(專案清單!$B$2:$B$80,$B18,專案清單!$Q$2:$Q$80,D$16,專案清單!$R$2:$R$80,"主清單") -> 4 | E18: =COUNTIFS(專案清單!$B$2:$B$80,$B18,專案清單!$Q$2:$Q$80,E$16,專案清單!$R$2:$R$80,"主清單") -> 0 | F18: =COUNTIFS(專案清單!$B$2:$B$80,$B18,專案清單!$Q$2:$Q$80,F$16,專案清單!$R$2:$R$80,"主清單") -> 0 | G18: =COUNTIFS(專案清單!$B$2:$B$80,$B18,專案清單!$Q$2:$Q$80,G$16,專案清單!$R$2:$R$80,"主清單") -> 10 | H18: =SUM(C18:G18) -> 21
A19: QLD | B19: 昆士蘭州 | C19: =COUNTIFS(專案清單!$B$2:$B$80,$B19,專案清單!$Q$2:$Q$80,C$16,專案清單!$R$2:$R$80,"主清單") -> 0 | D19: =COUNTIFS(專案清單!$B$2:$B$80,$B19,專案清單!$Q$2:$Q$80,D$16,專案清單!$R$2:$R$80,"主清單") -> 1 | E19: =COUNTIFS(專案清單!$B$2:$B$80,$B19,專案清單!$Q$2:$Q$80,E$16,專案清單!$R$2:$R$80,"主清單") -> 0 | F19: =COUNTIFS(專案清單!$B$2:$B$80,$B19,專案清單!$Q$2:$Q$80,F$16,專案清單!$R$2:$R$80,"主清單") -> 0 | G19: =COUNTIFS(專案清單!$B$2:$B$80,$B19,專案清單!$Q$2:$Q$80,G$16,專案清單!$R$2:$R$80,"主清單") -> 1 | H19: =SUM(C19:G19) -> 2
A20: WA | B20: 西澳州 | C20: =COUNTIFS(專案清單!$B$2:$B$80,$B20,專案清單!$Q$2:$Q$80,C$16,專案清單!$R$2:$R$80,"主清單") -> 1 | D20: =COUNTIFS(專案清單!$B$2:$B$80,$B20,專案清單!$Q$2:$Q$80,D$16,專案清單!$R$2:$R$80,"主清單") -> 0 | E20: =COUNTIFS(專案清單!$B$2:$B$80,$B20,專案清單!$Q$2:$Q$80,E$16,專案清單!$R$2:$R$80,"主清單") -> 0 | F20: =COUNTIFS(專案清單!$B$2:$B$80,$B20,專案清單!$Q$2:$Q$80,F$16,專案清單!$R$2:$R$80,"主清單") -> 0 | G20: =COUNTIFS(專案清單!$B$2:$B$80,$B20,專案清單!$Q$2:$Q$80,G$16,專案清單!$R$2:$R$80,"主清單") -> 1 | H20: =SUM(C20:G20) -> 2
A21: SA | B21: 南澳州 | C21: =COUNTIFS(專案清單!$B$2:$B$80,$B21,專案清單!$Q$2:$Q$80,C$16,專案清單!$R$2:$R$80,"主清單") -> 0 | D21: =COUNTIFS(專案清單!$B$2:$B$80,$B21,專案清單!$Q$2:$Q$80,D$16,專案清單!$R$2:$R$80,"主清單") -> 0 | E21: =COUNTIFS(專案清單!$B$2:$B$80,$B21,專案清單!$Q$2:$Q$80,E$16,專案清單!$R$2:$R$80,"主清單") -> 0 | F21: =COUNTIFS(專案清單!$B$2:$B$80,$B21,專案清單!$Q$2:$Q$80,F$16,專案清單!$R$2:$R$80,"主清單") -> 0 | G21: =COUNTIFS(專案清單!$B$2:$B$80,$B21,專案清單!$Q$2:$Q$80,G$16,專案清單!$R$2:$R$80,"主清單") -> 0 | H21: =SUM(C21:G21) -> 0
A22: ACT | B22: 首都領地 | C22: =COUNTIFS(專案清單!$B$2:$B$80,$B22,專案清單!$Q$2:$Q$80,C$16,專案清單!$R$2:$R$80,"主清單") -> 1 | D22: =COUNTIFS(專案清單!$B$2:$B$80,$B22,專案清單!$Q$2:$Q$80,D$16,專案清單!$R$2:$R$80,"主清單") -> 1 | E22: =COUNTIFS(專案清單!$B$2:$B$80,$B22,專案清單!$Q$2:$Q$80,E$16,專案清單!$R$2:$R$80,"主清單") -> 0 | F22: =COUNTIFS(專案清單!$B$2:$B$80,$B22,專案清單!$Q$2:$Q$80,F$16,專案清單!$R$2:$R$80,"主清單") -> 0 | G22: =COUNTIFS(專案清單!$B$2:$B$80,$B22,專案清單!$Q$2:$Q$80,G$16,專案清單!$R$2:$R$80,"主清單") -> 0 | H22: =SUM(C22:G22) -> 2
A23: TAS | B23: 塔斯馬尼亞州 | C23: =COUNTIFS(專案清單!$B$2:$B$80,$B23,專案清單!$Q$2:$Q$80,C$16,專案清單!$R$2:$R$80,"主清單") -> 0 | D23: =COUNTIFS(專案清單!$B$2:$B$80,$B23,專案清單!$Q$2:$Q$80,D$16,專案清單!$R$2:$R$80,"主清單") -> 0 | E23: =COUNTIFS(專案清單!$B$2:$B$80,$B23,專案清單!$Q$2:$Q$80,E$16,專案清單!$R$2:$R$80,"主清單") -> 0 | F23: =COUNTIFS(專案清單!$B$2:$B$80,$B23,專案清單!$Q$2:$Q$80,F$16,專案清單!$R$2:$R$80,"主清單") -> 0 | G23: =COUNTIFS(專案清單!$B$2:$B$80,$B23,專案清單!$Q$2:$Q$80,G$16,專案清單!$R$2:$R$80,"主清單") -> 0 | H23: =SUM(C23:G23) -> 0
A24: NT | B24: 北領地 | C24: =COUNTIFS(專案清單!$B$2:$B$80,$B24,專案清單!$Q$2:$Q$80,C$16,專案清單!$R$2:$R$80,"主清單") -> 0 | D24: =COUNTIFS(專案清單!$B$2:$B$80,$B24,專案清單!$Q$2:$Q$80,D$16,專案清單!$R$2:$R$80,"主清單") -> 0 | E24: =COUNTIFS(專案清單!$B$2:$B$80,$B24,專案清單!$Q$2:$Q$80,E$16,專案清單!$R$2:$R$80,"主清單") -> 0 | F24: =COUNTIFS(專案清單!$B$2:$B$80,$B24,專案清單!$Q$2:$Q$80,F$16,專案清單!$R$2:$R$80,"主清單") -> 0 | G24: =COUNTIFS(專案清單!$B$2:$B$80,$B24,專案清單!$Q$2:$Q$80,G$16,專案清單!$R$2:$R$80,"主清單") -> 0 | H24: =SUM(C24:G24) -> 0
A25: 合計 | C25: =SUM(C17:C24) -> 15 | D25: =SUM(D17:D24) -> 16 | E25: =SUM(E17:E24) -> 1 | F25: =SUM(F17:F24) -> 2 | G25: =SUM(G17:G24) -> 26 | H25: =SUM(H17:H24) -> 60
A27: 各州 × 完工時間窗（主清單件數）
A28: 州 | B28: 州名 | C28: 已可用／營運中 | D28: 2026 Q4 – 2027 Q2 | E28: 2027 下半年 | F28: 2028 年以後 | G28: 完工日未公布 | H28: 合計
A29: NSW | B29: 新南威爾斯州 | C29: =COUNTIFS(專案清單!$B$2:$B$80,$B29,專案清單!$X$2:$X$80,C$28,專案清單!$R$2:$R$80,"主清單") -> 3 | D29: =COUNTIFS(專案清單!$B$2:$B$80,$B29,專案清單!$X$2:$X$80,D$28,專案清單!$R$2:$R$80,"主清單") -> 1 | E29: =COUNTIFS(專案清單!$B$2:$B$80,$B29,專案清單!$X$2:$X$80,E$28,專案清單!$R$2:$R$80,"主清單") -> 2 | F29: =COUNTIFS(專案清單!$B$2:$B$80,$B29,專案清單!$X$2:$X$80,F$28,專案清單!$R$2:$R$80,"主清單") -> 6 | G29: =COUNTIFS(專案清單!$B$2:$B$80,$B29,專案清單!$X$2:$X$80,G$28,專案清單!$R$2:$R$80,"主清單") -> 21 | H29: =SUM(C29:G29) -> 33
A30: VIC | B30: 維多利亞州 | C30: =COUNTIFS(專案清單!$B$2:$B$80,$B30,專案清單!$X$2:$X$80,C$28,專案清單!$R$2:$R$80,"主清單") -> 0 | D30: =COUNTIFS(專案清單!$B$2:$B$80,$B30,專案清單!$X$2:$X$80,D$28,專案清單!$R$2:$R$80,"主清單") -> 3 | E30: =COUNTIFS(專案清單!$B$2:$B$80,$B30,專案清單!$X$2:$X$80,E$28,專案清單!$R$2:$R$80,"主清單") -> 1 | F30: =COUNTIFS(專案清單!$B$2:$B$80,$B30,專案清單!$X$2:$X$80,F$28,專案清單!$R$2:$R$80,"主清單") -> 3 | G30: =COUNTIFS(專案清單!$B$2:$B$80,$B30,專案清單!$X$2:$X$80,G$28,專案清單!$R$2:$R$80,"主清單") -> 14 | H30: =SUM(C30:G30) -> 21
A31: QLD | B31: 昆士蘭州 | C31: =COUNTIFS(專案清單!$B$2:$B$80,$B31,專案清單!$X$2:$X$80,C$28,專案清單!$R$2:$R$80,"主清單") -> 0 | D31: =COUNTIFS(專案清單!$B$2:$B$80,$B31,專案清單!$X$2:$X$80,D$28,專案清單!$R$2:$R$80,"主清單") -> 0 | E31: =COUNTIFS(專案清單!$B$2:$B$80,$B31,專案清單!$X$2:$X$80,E$28,專案清單!$R$2:$R$80,"主清單") -> 0 | F31: =COUNTIFS(專案清單!$B$2:$B$80,$B31,專案清單!$X$2:$X$80,F$28,專案清單!$R$2:$R$80,"主清單") -> 0 | G31: =COUNTIFS(專案清單!$B$2:$B$80,$B31,專案清單!$X$2:$X$80,G$28,專案清單!$R$2:$R$80,"主清單") -> 2 | H31: =SUM(C31:G31) -> 2
A32: WA | B32: 西澳州 | C32: =COUNTIFS(專案清單!$B$2:$B$80,$B32,專案清單!$X$2:$X$80,C$28,專案清單!$R$2:$R$80,"主清單") -> 0 | D32: =COUNTIFS(專案清單!$B$2:$B$80,$B32,專案清單!$X$2:$X$80,D$28,專案清單!$R$2:$R$80,"主清單") -> 1 | E32: =COUNTIFS(專案清單!$B$2:$B$80,$B32,專案清單!$X$2:$X$80,E$28,專案清單!$R$2:$R$80,"主清單") -> 0 | F32: =COUNTIFS(專案清單!$B$2:$B$80,$B32,專案清單!$X$2:$X$80,F$28,專案清單!$R$2:$R$80,"主清單") -> 1 | G32: =COUNTIFS(專案清單!$B$2:$B$80,$B32,專案清單!$X$2:$X$80,G$28,專案清單!$R$2:$R$80,"主清單") -> 0 | H32: =SUM(C32:G32) -> 2
A33: SA | B33: 南澳州 | C33: =COUNTIFS(專案清單!$B$2:$B$80,$B33,專案清單!$X$2:$X$80,C$28,專案清單!$R$2:$R$80,"主清單") -> 0 | D33: =COUNTIFS(專案清單!$B$2:$B$80,$B33,專案清單!$X$2:$X$80,D$28,專案清單!$R$2:$R$80,"主清單") -> 0 | E33: =COUNTIFS(專案清單!$B$2:$B$80,$B33,專案清單!$X$2:$X$80,E$28,專案清單!$R$2:$R$80,"主清單") -> 0 | F33: =COUNTIFS(專案清單!$B$2:$B$80,$B33,專案清單!$X$2:$X$80,F$28,專案清單!$R$2:$R$80,"主清單") -> 0 | G33: =COUNTIFS(專案清單!$B$2:$B$80,$B33,專案清單!$X$2:$X$80,G$28,專案清單!$R$2:$R$80,"主清單") -> 0 | H33: =SUM(C33:G33) -> 0
A34: ACT | B34: 首都領地 | C34: =COUNTIFS(專案清單!$B$2:$B$80,$B34,專案清單!$X$2:$X$80,C$28,專案清單!$R$2:$R$80,"主清單") -> 0 | D34: =COUNTIFS(專案清單!$B$2:$B$80,$B34,專案清單!$X$2:$X$80,D$28,專案清單!$R$2:$R$80,"主清單") -> 0 | E34: =COUNTIFS(專案清單!$B$2:$B$80,$B34,專案清單!$X$2:$X$80,E$28,專案清單!$R$2:$R$80,"主清單") -> 0 | F34: =COUNTIFS(專案清單!$B$2:$B$80,$B34,專案清單!$X$2:$X$80,F$28,專案清單!$R$2:$R$80,"主清單") -> 0 | G34: =COUNTIFS(專案清單!$B$2:$B$80,$B34,專案清單!$X$2:$X$80,G$28,專案清單!$R$2:$R$80,"主清單") -> 2 | H34: =SUM(C34:G34) -> 2
A35: TAS | B35: 塔斯馬尼亞州 | C35: =COUNTIFS(專案清單!$B$2:$B$80,$B35,專案清單!$X$2:$X$80,C$28,專案清單!$R$2:$R$80,"主清單") -> 0 | D35: =COUNTIFS(專案清單!$B$2:$B$80,$B35,專案清單!$X$2:$X$80,D$28,專案清單!$R$2:$R$80,"主清單") -> 0 | E35: =COUNTIFS(專案清單!$B$2:$B$80,$B35,專案清單!$X$2:$X$80,E$28,專案清單!$R$2:$R$80,"主清單") -> 0 | F35: =COUNTIFS(專案清單!$B$2:$B$80,$B35,專案清單!$X$2:$X$80,F$28,專案清單!$R$2:$R$80,"主清單") -> 0 | G35: =COUNTIFS(專案清單!$B$2:$B$80,$B35,專案清單!$X$2:$X$80,G$28,專案清單!$R$2:$R$80,"主清單") -> 0 | H35: =SUM(C35:G35) -> 0
A36: NT | B36: 北領地 | C36: =COUNTIFS(專案清單!$B$2:$B$80,$B36,專案清單!$X$2:$X$80,C$28,專案清單!$R$2:$R$80,"主清單") -> 0 | D36: =COUNTIFS(專案清單!$B$2:$B$80,$B36,專案清單!$X$2:$X$80,D$28,專案清單!$R$2:$R$80,"主清單") -> 0 | E36: =COUNTIFS(專案清單!$B$2:$B$80,$B36,專案清單!$X$2:$X$80,E$28,專案清單!$R$2:$R$80,"主清單") -> 0 | F36: =COUNTIFS(專案清單!$B$2:$B$80,$B36,專案清單!$X$2:$X$80,F$28,專案清單!$R$2:$R$80,"主清單") -> 0 | G36: =COUNTIFS(專案清單!$B$2:$B$80,$B36,專案清單!$X$2:$X$80,G$28,專案清單!$R$2:$R$80,"主清單") -> 0 | H36: =SUM(C36:G36) -> 0
A37: 合計 | C37: =SUM(C29:C36) -> 3 | D37: =SUM(D29:D36) -> 5 | E37: =SUM(E29:E36) -> 3 | F37: =SUM(F29:F36) -> 10 | G37: =SUM(G29:G36) -> 39 | H37: =SUM(H29:H36) -> 60
A39: 各州容量與資料品質（只計主清單）
A40: 州 | B40: 州名 | C40: 專案數（件） | D40: 已知容量（MW） | E40: 容量未公布（件） | F40: 可信度「高」（件） | G40: 占已知總容量
A41: NSW | B41: 新南威爾斯州 | C41: =COUNTIFS(專案清單!$B$2:$B$80,$B41,專案清單!$R$2:$R$80,"主清單") -> 33 | D41: =SUMIFS(專案清單!$M$2:$M$80,專案清單!$B$2:$B$80,$B41,專案清單!$R$2:$R$80,"主清單") -> 7526.6 | E41: =COUNTIFS(專案清單!$B$2:$B$80,$B41,專案清單!$M$2:$M$80,"未公布",專案清單!$R$2:$R$80,"主清單") -> 2 | F41: =COUNTIFS(專案清單!$B$2:$B$80,$B41,專案清單!$AD$2:$AD$80,"高",專案清單!$R$2:$R$80,"主清單") -> 27 | G41: =IF($D$49=0,0,D41/$D$49) -> 0.53020654
A42: VIC | B42: 維多利亞州 | C42: =COUNTIFS(專案清單!$B$2:$B$80,$B42,專案清單!$R$2:$R$80,"主清單") -> 21 | D42: =SUMIFS(專案清單!$M$2:$M$80,專案清單!$B$2:$B$80,$B42,專案清單!$R$2:$R$80,"主清單") -> 4233 | E42: =COUNTIFS(專案清單!$B$2:$B$80,$B42,專案清單!$M$2:$M$80,"未公布",專案清單!$R$2:$R$80,"主清單") -> 2 | F42: =COUNTIFS(專案清單!$B$2:$B$80,$B42,專案清單!$AD$2:$AD$80,"高",專案清單!$R$2:$R$80,"主清單") -> 15 | G42: =IF($D$49=0,0,D42/$D$49) -> 0.29819099
A43: QLD | B43: 昆士蘭州 | C43: =COUNTIFS(專案清單!$B$2:$B$80,$B43,專案清單!$R$2:$R$80,"主清單") -> 2 | D43: =SUMIFS(專案清單!$M$2:$M$80,專案清單!$B$2:$B$80,$B43,專案清單!$R$2:$R$80,"主清單") -> 1940 | E43: =COUNTIFS(專案清單!$B$2:$B$80,$B43,專案清單!$M$2:$M$80,"未公布",專案清單!$R$2:$R$80,"主清單") -> 0 | F43: =COUNTIFS(專案清單!$B$2:$B$80,$B43,專案清單!$AD$2:$AD$80,"高",專案清單!$R$2:$R$80,"主清單") -> 1 | G43: =IF($D$49=0,0,D43/$D$49) -> 0.13666206
A44: WA | B44: 西澳州 | C44: =COUNTIFS(專案清單!$B$2:$B$80,$B44,專案清單!$R$2:$R$80,"主清單") -> 2 | D44: =SUMIFS(專案清單!$M$2:$M$80,專案清單!$B$2:$B$80,$B44,專案清單!$R$2:$R$80,"主清單") -> 392 | E44: =COUNTIFS(專案清單!$B$2:$B$80,$B44,專案清單!$M$2:$M$80,"未公布",專案清單!$R$2:$R$80,"主清單") -> 0 | F44: =COUNTIFS(專案清單!$B$2:$B$80,$B44,專案清單!$AD$2:$AD$80,"高",專案清單!$R$2:$R$80,"主清單") -> 1 | G44: =IF($D$49=0,0,D44/$D$49) -> 0.02761419
A45: SA | B45: 南澳州 | C45: =COUNTIFS(專案清單!$B$2:$B$80,$B45,專案清單!$R$2:$R$80,"主清單") -> 0 | D45: =SUMIFS(專案清單!$M$2:$M$80,專案清單!$B$2:$B$80,$B45,專案清單!$R$2:$R$80,"主清單") -> 0 | E45: =COUNTIFS(專案清單!$B$2:$B$80,$B45,專案清單!$M$2:$M$80,"未公布",專案清單!$R$2:$R$80,"主清單") -> 0 | F45: =COUNTIFS(專案清單!$B$2:$B$80,$B45,專案清單!$AD$2:$AD$80,"高",專案清單!$R$2:$R$80,"主清單") -> 0 | G45: =IF($D$49=0,0,D45/$D$49) -> 0
A46: ACT | B46: 首都領地 | C46: =COUNTIFS(專案清單!$B$2:$B$80,$B46,專案清單!$R$2:$R$80,"主清單") -> 2 | D46: =SUMIFS(專案清單!$M$2:$M$80,專案清單!$B$2:$B$80,$B46,專案清單!$R$2:$R$80,"主清單") -> 104 | E46: =COUNTIFS(專案清單!$B$2:$B$80,$B46,專案清單!$M$2:$M$80,"未公布",專案清單!$R$2:$R$80,"主清單") -> 0 | F46: =COUNTIFS(專案清單!$B$2:$B$80,$B46,專案清單!$AD$2:$AD$80,"高",專案清單!$R$2:$R$80,"主清單") -> 2 | G46: =IF($D$49=0,0,D46/$D$49) -> 0.0073262138
A47: TAS | B47: 塔斯馬尼亞州 | C47: =COUNTIFS(專案清單!$B$2:$B$80,$B47,專案清單!$R$2:$R$80,"主清單") -> 0 | D47: =SUMIFS(專案清單!$M$2:$M$80,專案清單!$B$2:$B$80,$B47,專案清單!$R$2:$R$80,"主清單") -> 0 | E47: =COUNTIFS(專案清單!$B$2:$B$80,$B47,專案清單!$M$2:$M$80,"未公布",專案清單!$R$2:$R$80,"主清單") -> 0 | F47: =COUNTIFS(專案清單!$B$2:$B$80,$B47,專案清單!$AD$2:$AD$80,"高",專案清單!$R$2:$R$80,"主清單") -> 0 | G47: =IF($D$49=0,0,D47/$D$49) -> 0
A48: NT | B48: 北領地 | C48: =COUNTIFS(專案清單!$B$2:$B$80,$B48,專案清單!$R$2:$R$80,"主清單") -> 0 | D48: =SUMIFS(專案清單!$M$2:$M$80,專案清單!$B$2:$B$80,$B48,專案清單!$R$2:$R$80,"主清單") -> 0 | E48: =COUNTIFS(專案清單!$B$2:$B$80,$B48,專案清單!$M$2:$M$80,"未公布",專案清單!$R$2:$R$80,"主清單") -> 0 | F48: =COUNTIFS(專案清單!$B$2:$B$80,$B48,專案清單!$AD$2:$AD$80,"高",專案清單!$R$2:$R$80,"主清單") -> 0 | G48: =IF($D$49=0,0,D48/$D$49) -> 0
A49: 合計 | C49: =SUM(C41:C48) -> 60 | D49: =SUM(D41:D48) -> 14195.6 | E49: =SUM(E41:E48) -> 4 | F49: =SUM(F41:F48) -> 46 | G49: =SUM(G41:G48) -> 1
A51: 觀察名單 (出租性待確認)：不計入以上統計
A52: 州 | B52: 州名 | C52: 觀察名單（件） | D52: 已知容量（MW） | E52: 容量未公布（件）
A53: NSW | B53: 新南威爾斯州 | C53: =COUNTIFS(專案清單!$B$2:$B$80,$B53,專案清單!$R$2:$R$80,"觀察名單 (出租性待確認)") -> 3 | D53: =SUMIFS(專案清單!$M$2:$M$80,專案清單!$B$2:$B$80,$B53,專案清單!$R$2:$R$80,"觀察名單 (出租性待確認)") -> 209.2 | E53: =COUNTIFS(專案清單!$B$2:$B$80,$B53,專案清單!$M$2:$M$80,"未公布",專案清單!$R$2:$R$80,"觀察名單 (出租性待確認)") -> 0
A54: VIC | B54: 維多利亞州 | C54: =COUNTIFS(專案清單!$B$2:$B$80,$B54,專案清單!$R$2:$R$80,"觀察名單 (出租性待確認)") -> 8 | D54: =SUMIFS(專案清單!$M$2:$M$80,專案清單!$B$2:$B$80,$B54,專案清單!$R$2:$R$80,"觀察名單 (出租性待確認)") -> 443 | E54: =COUNTIFS(專案清單!$B$2:$B$80,$B54,專案清單!$M$2:$M$80,"未公布",專案清單!$R$2:$R$80,"觀察名單 (出租性待確認)") -> 5
A55: QLD | B55: 昆士蘭州 | C55: =COUNTIFS(專案清單!$B$2:$B$80,$B55,專案清單!$R$2:$R$80,"觀察名單 (出租性待確認)") -> 1 | D55: =SUMIFS(專案清單!$M$2:$M$80,專案清單!$B$2:$B$80,$B55,專案清單!$R$2:$R$80,"觀察名單 (出租性待確認)") -> 0 | E55: =COUNTIFS(專案清單!$B$2:$B$80,$B55,專案清單!$M$2:$M$80,"未公布",專案清單!$R$2:$R$80,"觀察名單 (出租性待確認)") -> 1
A56: WA | B56: 西澳州 | C56: =COUNTIFS(專案清單!$B$2:$B$80,$B56,專案清單!$R$2:$R$80,"觀察名單 (出租性待確認)") -> 0 | D56: =SUMIFS(專案清單!$M$2:$M$80,專案清單!$B$2:$B$80,$B56,專案清單!$R$2:$R$80,"觀察名單 (出租性待確認)") -> 0 | E56: =COUNTIFS(專案清單!$B$2:$B$80,$B56,專案清單!$M$2:$M$80,"未公布",專案清單!$R$2:$R$80,"觀察名單 (出租性待確認)") -> 0
A57: SA | B57: 南澳州 | C57: =COUNTIFS(專案清單!$B$2:$B$80,$B57,專案清單!$R$2:$R$80,"觀察名單 (出租性待確認)") -> 3 | D57: =SUMIFS(專案清單!$M$2:$M$80,專案清單!$B$2:$B$80,$B57,專案清單!$R$2:$R$80,"觀察名單 (出租性待確認)") -> 823 | E57: =COUNTIFS(專案清單!$B$2:$B$80,$B57,專案清單!$M$2:$M$80,"未公布",專案清單!$R$2:$R$80,"觀察名單 (出租性待確認)") -> 0
A58: ACT | B58: 首都領地 | C58: =COUNTIFS(專案清單!$B$2:$B$80,$B58,專案清單!$R$2:$R$80,"觀察名單 (出租性待確認)") -> 0 | D58: =SUMIFS(專案清單!$M$2:$M$80,專案清單!$B$2:$B$80,$B58,專案清單!$R$2:$R$80,"觀察名單 (出租性待確認)") -> 0 | E58: =COUNTIFS(專案清單!$B$2:$B$80,$B58,專案清單!$M$2:$M$80,"未公布",專案清單!$R$2:$R$80,"觀察名單 (出租性待確認)") -> 0
A59: TAS | B59: 塔斯馬尼亞州 | C59: =COUNTIFS(專案清單!$B$2:$B$80,$B59,專案清單!$R$2:$R$80,"觀察名單 (出租性待確認)") -> 3 | D59: =SUMIFS(專案清單!$M$2:$M$80,專案清單!$B$2:$B$80,$B59,專案清單!$R$2:$R$80,"觀察名單 (出租性待確認)") -> 424 | E59: =COUNTIFS(專案清單!$B$2:$B$80,$B59,專案清單!$M$2:$M$80,"未公布",專案清單!$R$2:$R$80,"觀察名單 (出租性待確認)") -> 0
A60: NT | B60: 北領地 | C60: =COUNTIFS(專案清單!$B$2:$B$80,$B60,專案清單!$R$2:$R$80,"觀察名單 (出租性待確認)") -> 1 | D60: =SUMIFS(專案清單!$M$2:$M$80,專案清單!$B$2:$B$80,$B60,專案清單!$R$2:$R$80,"觀察名單 (出租性待確認)") -> 1000 | E60: =COUNTIFS(專案清單!$B$2:$B$80,$B60,專案清單!$M$2:$M$80,"未公布",專案清單!$R$2:$R$80,"觀察名單 (出租性待確認)") -> 0
A61: 合計 | C61: =SUM(C53:C60) -> 19 | D61: =SUM(D53:D60) -> 2899.2 | E61: =SUM(E53:E60) -> 6
A63: 重點發現
A64: 1. 2026 Q4 – 2027 Q2 內交付的只有五個
A65: GreenSquareDC SYD1 第一期（約 15 MW，Norwest，W.Media 稱 2026 Q4 初始營運）、STACK MEL01C/D（各 54 MW）、STACK MEL02（252 MW）、Vantage MEL1（64 MW）、CDC Maddington MA1（約 34 MW，2027-01）。其中 STACK 的完工日只有聚合站與 STACK 官網的計畫年份，Vantage 官網沒有日期，可信度中等；STACK MEL01C&D 在承建商 Hickory 的網站上已列為『已完成』，可能是土建完成、機電與啟用仍在進行，需向 STACK 確認。
A66: 2. 最接近 5 MW 尺度的是三個中小型案
A67: GreenSquareDC SYD1 第一期（14.9–15 MW，既有建築改造，2026 Q4）、Macquarie IC3 Super West（首期 6 MW，2026-09 啟用，後續 19 MW 設備已融資）、Cloud Carrier Southern Highlands DB1（28 MW 裸殼，已營運，Moss Vale）。其餘動輒 50–500 MW 的批發園區，5 MW 租戶幾乎沒有議價空間。
A68: 3. 在建的大案幾乎都是批發型，而且多半已預售
A69: NEXTDC FY26 簡報（2026-08-27）：已簽約容量 740.1 MW、已建成 287.9 MW。S4 有 250 MW 在建、M3 有 165 MW、M2 有 60 MW、M4 有 10 MW，但 NSW、VIC 的簽約量都遠超已建成容量。CDC 的 Marsden Park（504 MW）、Laverton、Maddington 同樣以長約預簽為主。AirTrunk SYD3 為三階段、每階段約 24 個月的超大規模建設。
A70: 4. 有 21 筆案子其實是雲端巨頭自建，不能租
A71: 已查證並剔除 21 筆自建案，例如 AWS 的 3 Davis Road（開工通知明寫 AWS）、Project Echidna、Glendenning Road（約 194 MW）、墨爾本 Craigieburn／Cobblebank／Truganina 三案；Amazon 的 43-61 Turner Road（53 MW）；Microsoft 的 Honeman Close（96 MW）與 Station Road。這些常被第三方資料庫列為『資料中心在建』，但沒有任何可租空間。
A72: 5. 垂直整合的 AI 雲不出租機房空間
A73: Firmus 在塔斯馬尼亞的三個 AI 工廠（St Leonards 施工中 84 MW、Bell Bay 288 MW 已核准但有 5 件上訴、Wesley Vale 52 MW）與 IREN Bundey（南澳，約 550 MW IT）賣的是 GPU 算力，不是機房空間，所以放在觀察名單。這也是 TAS、SA 沒有主清單專案的原因。
A74: 6. 2028 年以後才有的新供給
... A79: NSW 於 2026-08-17 發布 Data Centre Guidelines（核准附 firmed 再生能源 PPA 條件）；Goodman 於 2026-09-28 撤回 90 MW 的 Project Mars；維州 2026-09-22 發布永續資料中心行動計畫（住宅 150 公尺緩衝、禁止住宅區），Hume、Brimbank、Maribyrnong 曾要求暫停；昆州 2026-10-02 宣布資料中心審批收歸州級；GreenSquareDC WAi1 的舊核准將於 2026-10-17 失效且從未動工。

Sheet 專案清單
A1: 編號 | B1: 州 | C1: 專案名稱 | D1: 營運商 | E1: 開發商／業主 | F1: 街道地址 | G1: 郊區 | H1: 郵遞區號 | I1: 區政府 | J1: 緯度 | K1: 經度 | L1: 座標精度 | M1: 容量 MW | N1: 容量口徑 | O1: 首期 MW | P1: 容量備註 | Q1: 狀態 | R1: 分級 | S1: 分級說明 | T1: 狀態日期 | U1: 施工證據 | V1: 開工時間 | W1: 預計完工（原文） | X1: 完工時間窗 | Y1: 完工日來源 | Z1: 可租判斷 | AA1: 可租備註 | AB1: 已知租戶 | AC1: 核准案號 | AD1: 可信度 | AE1: 差異／備註 | AF1: 政府來源 | AG1: 營運商來源 | AH1: 媒體來源 | AI1: 已讀原文來源 | AJ1: Google 地圖 | AK1: 回報代理
A2: VIC-001 | B2: 維多利亞州 | C2: CDC Brooklyn 園區（BK1／BK2 已營運，第三棟規劃中） | D2: CDC Data Centres | E2: CDC | F2: 598B Geelong Road, Brooklyn VIC 3012 | G2: Brooklyn | H2: 3012 | I2: Brimbank City Council（依 DCM wiki） | J2: -37.81667 | K2: 144.84641 | L2: 門牌級 | M2: 155 | N2: 口徑不明 | P2: DCD 2026-03-03：引述財政部長貼文稱新增 155 MW；CDC 官網稱完工後逾 350 MW；DCM wiki：BK1 逾 150 MW。 | Q2: 近期完工（仍有容量） | R2: 觀察名單 (出租性待確認) | S2: 出租性待確認：營運設施，未見公開剩餘容量；DCM wiki 稱 Firmus（Project Southgate）與 Meta 已佔用部分。 | T2: 2026-02-26 | U2: DJSIR 2026-02-26（已讀）：CDC 正式啟用 Brooklyn 園區，兩棟設施已運轉，第三棟規劃進行中。Brimbank 公開規劃登記冊（資料截至 2025-07-22，已讀並以座標核對）：P569/2023（598B Geelong Rd）『Development of part of the land for a data centre (second stage – north side) within DDO11 …』2023-11-08 受理、2024-02-20 由委派官員核發；P652/2021（598／598A／598B Geelong Rd）資料中心圖面修訂 2022-12-28 核發、紅線與停車變更 2022-06-21 核發。DCM wiki：BK1 於 2022-05 動工、2024-07 完工；BK2 於 2024-10 動工、約 2025 年底完工。第三棟尚無申請編號。 | V2: BK1 2022-05；BK2 2024-10（wiki） | W2: 第三棟未公布 | X2: 已可用／營運中 | Y2: — | Z2: 待確認 | AA2: 營運設施，未見公開剩餘容量；DCM wiki 稱 Firmus（Project Southgate）與 Meta 已佔用部分。 | AB2: Firmus（GB300 叢集）；Firmus 2026-09 稿稱終端客戶為 Meta（皆依 DCM wiki 轉述，未開啟 Firmus 原文） | AC2: Brimbank P569/2023（第二階段北側，2024-02-20 核發）；P652/2021（修訂，2022）；原始許可編號未取得 | AD2: 中 | AE2: CDC 官網（BK1 營運、其餘興建中）vs DJSIR 2026-02-26（兩座運作中）；350 MW 與變電站 99 MVA 數字不一致 地址備註：另含 11A McDonald Road, Brooklyn（DCM wiki）；Jemena 專用區域變電站在 598 Geelong Road（2023-09 完工）。 | AF2: https://djsir.vic.gov.au/news-and-articles/cdcs-data-centres-fueling-jobs-and-growth-in-the-west https://records.brimbank.vic.gov.au/ExternalLinkAPI/api/document/?docKey=UHZYRmNFYWVDaUN0clNmekJwVXhMUExwUGpQcFE0VVFXVnp1NkdSYlZpc0lsS2NCZlVOWUxOVXBncy9DSUhHZg2 | AG2: https://cdc.com/locations/melbourne/ | AH2: https://www.datacenterdynamics.com/en/news/australias-cdc-opens-data-center-campus-in-melbourne/ https://www.invest.vic.gov.au/news-and-events/news/2026/march/cdc-data-centres-officially-opens-its-first-melbourne-campus-expanding-its-ability-to-deliver-secure-and-sustainable-solutions https://datacentremoratorium.net/index.php/Resources:CDC_Brooklyn_Campus | AI2: https://djsir.vic.gov.au/news-and-articles/cdcs-data-centres-fueling-jobs-and-growth-in-the-west https://www.datacenterdynamics.com/en/news/australias-cdc-opens-data-center-campus-in-melbourne/ https://records.brimbank.vic.gov.au/ExternalLinkAPI/api/document/?docKey=UHZYRmNFYWVDaUN0clNmekJwVXhMUExwUGpQcFE0VVFXVnp1NkdSYlZpc0lsS2NCZlVOWUxOVXBncy9DSUhHZg2 https://datacentremoratorium.net/index.php/Resources:CDC_Brooklyn_Campus https://cdc.com/locations/melbourne/ | AJ2: 開啟地圖 | AK2: VIC-B、VIC-A
A3: NSW-001 | B3: 新南威爾斯州 | C3: Macquarie Technology IC3 Super West — Talavera Road Data Centre Campus Expansion（SSD-24299707） | D3: Macquarie Data Centres（Macquarie Technology Group） | E3: Macquarie Data Centres Pty Ltd（申請人） | F3: 17-23 Talavera Road, Macquarie Park NSW 2113 | G3: Macquarie Park | H3: 2113 | I3: City of Ryde | J3: -33.78073 | K3: 151.12733 | L3: 來源提供 | M3: 47 | N3: 耗電量 | O3: 6 | P3: 原核准（IPC，2024-01-19）38 MW；Mod 1（2024-12-19 核准）增至 47 MW，整個園區合計 66→75 MW。八層擴建、GFA 16,142 m2、20×3.3 MW 發電機。公司揭露（先前資料）：首批 6 MW IT 預計 2026-09 啟用、已有 A$50m 債務額度支應 19 MW 長交期設備；FY27 下半年起認列營收。 | Q3: 近期完工（仍有容量） | R3: 主清單 | T3: 2026-07-23 | U3: A15「Notification of Commencement」2024-01-24；Macquarie Telecom 施工通知 2024-05-22 與 2024-06-11；Stage 2 CEMP 核准 2024-06-27；「Commencement of Operations」函（2026-07-22；portal 上傳 2026-07-23）：Stage 2 預期約一個月後開始營運；FDC Construction 為總包（媒體，先前資料）。 | V3: 2024-01/2024-06（通知函） | W3: 評估報告：施工約 21 個月；Stage 2 營運 2026-08/09 起；後續階段（19 MW→47 MW）未公布日期。 | X3: 已可用／營運中 | Y3: DPHI/IPC Assessment Report（2023-11-27）；Macquarie 營運通知（2026-07-22） | Z3: 可租 | AA3: Macquarie Data Centres 為主權級託管營運商，向企業、政府出租；本期容量逐階段釋出，是 5–20 MW 規模的近期可談標的。 | AB3: 未揭露 | AC3: SSD-24299707（IPC 核准 2024-01-19）；Mod 1（2024-12-19） | AD3: 高 | AE3: 地址 17-23 vs 33-39 Talavera Road（Khartoum 報告）；容量 38/47 MW（兩次核准）；先前資料 47 MW 為「total」，實為本次擴建增量，園區合計 75 MW；先前資料寫首期 6 MW 於 2026-09 啟用；ASX 簡報（2026-08-26）仍屬預告，截至 2026-10-03 是否已啟用未取得公司確認 地址備註：Lot 527 DP 752035 與 Part Lot 3 DP 1043041，約 2 公頃；Khartoum Road 評估報告把同一 SSD 寫成「33-39 Talavera Road」。 | AF3: https://www.planningportal.nsw.gov.au/major-projects/projects/talavera-road-data-centre-campus-expansion https://majorprojects.planningportal.nsw.gov.au/prweb/PRRestService/mp/01/getContent?AttachRef=SSD-24299707%2120231127T020928.161+GMT https://majorprojects.planningportal.nsw.gov.au/prweb/PRRestService/mp/01/getContent?AttachRef=SSD-24299707-PA-22%2120260723T112244.245+GMT https://majorprojects.planningportal.nsw.gov.au/prweb/PRRestService/mp/01/getContent?AttachRef=SSD-24299707-MOD-1%2120241219T224421.352+GMT https://www.planningportal.nsw.gov.au/major-projects/projects/talavera-road-data-centre-mod-1-expansion | AG3: https://cdn-api.markitdigital.com/apiman-gateway/ASX/asx-research/1.0/file/2924-03126655-2A1692379 | AH3: https://baxtel.com/data-center/macquarie-ic3-super-west | AI3: https://www.planningportal.nsw.gov.au/major-projects/projects/talavera-road-data-centre-campus-expansion https://majorprojects.planningportal.nsw.gov.au/prweb/PRRestService/mp/01/getContent?AttachRef=SSD-24299707%2120231127T020928.161+GMT https://majorprojects.planningportal.nsw.gov.au/prweb/PRRestService/mp/01/getContent?AttachRef=SSD-24299707-PA-22%2120260723T112244.245+GMT https://majorprojects.planningportal.nsw.gov.au/prweb/PRRestService/mp/01/getContent?AttachRef=SSD-24299707-MOD-1%2120241219T224421.352+GMT https://www.planningportal.nsw.gov.au/major-projects/projects/talavera-road-data-centre-mod-1-expansion https://cdn-api.markitdigital.com/apiman-gateway/ASX/asx-research/1.0/file/2924-03126655-2A1692379 | AJ3: 開啟地圖 | AK3: NSW-B、NSW-A
A4: VIC-002 | B4: 維多利亞州 | C4: AirTrunk MEL1（Derrimut）— 營運中，疑有擴建 | D4: AirTrunk | E4: AirTrunk（Blackstone／CPP Investments 控股） | F4: 176 Swann Drive, Derrimut VIC 3026 | G4: Derrimut | H4: 3026 | I4: Brimbank City Council | J4: -37.801761 | K4: 144.77557 | L4: 街道級 | M4: 276 | N4: 口徑不明 | P4: AirTrunk 官網（已讀）：185+ MW；AirTrunk 2025-12-24 新聞稿：MEL1 276 MW+，兩者差約 91 MW，與 Brimbank 2025-04 核發的『新增兩階段』相符，推測為新增棟別。 | Q4: 已營運（有餘裕／擴建） | R4: 觀察名單 (出租性待確認) | S4: 出租性待確認：AirTrunk 為超大規模批發型；未見可租空置容量的公開數字。 | T4: 2025-12-24 | U4: Brimbank 公開規劃登記冊（資料截至 2025-07-22，已讀並以座標核對）：P490/2016（Pt 3）涵蓋 31 Jilly Ct、156 與 176 Swann Dr，2024-12-23 受理的修訂內容為『將地址擴充、許可內容加入移除原生植被、修訂圖面以詳述建物與工程並新增兩個階段（add two new stages）』，2025-04-09 由委派官員核發修訂許可；另 P82/2019（210 Swann Dr 『use and staged development of the land for a data centre』）2019-08-30 核發。登記冊未具名 AirTrunk，營運商身分取自 DCM wiki 對這些地址的標註。尚無具日期的施工事件。 | V4: 未公布 | W4: 未公布 | X4: 已可用／營運中 | Y4: — | Z4: 待確認 | AA4: AirTrunk 為超大規模批發型；未見可租空置容量的公開數字。 | AB4: 未公布（DCM wiki 列 Datacom 為共同開發方） | AC4: Brimbank P490/2016（Pt 3，新增兩階段，2025-04-09 核發修訂）；P82/2019（210 Swann Dr，2019-08-30） | AD4: 中 | AE4: 185+ MW（官網）vs 276+ MW（新聞稿）；185+ MW（官網頁）vs 276 MW+（2025-12 新聞稿）；DCM wiki 亦列 185 MW。 地址備註：DCM wiki 列 176 Swann Drive、156 Swann Drive、31 Jilly Court（Brimbank 議會申請）；AirTrunk 官網只稱「墨爾本西部」未列街址；realestatesource 稱 MEL1 在 Derrimut、34 個機房。 | AF4: https://records.brimbank.vic.gov.au/ExternalLinkAPI/api/document/?docKey=UHZYRmNFYWVDaUN0clNmekJwVXhMUExwUGpQcFE0VVFXVnp1NkdSYlZpc0lsS2NCZlVOWUxOVXBncy9DSUhHZg2 | AG4: https://airtrunk.com/data-centres/mel1/ https://airtrunk.com/airtrunk-expands-australian-platform-with-a-second-hyperscale-data-centre-campus-in-melbourne/ https://airtrunk.com/location/mel1-melbourne/ | AH4: https://www.realestatesource.com.au/data-centre-giant-buys-350m-melbourne-site/ | AI4: https://airtrunk.com/data-centres/mel1/ https://airtrunk.com/airtrunk-expands-australian-platform-with-a-second-hyperscale-data-centre-campus-in-melbourne/ https://records.brimbank.vic.gov.au/ExternalLinkAPI/api/document/?docKey=UHZYRmNFYWVDaUN0clNmekJwVXhMUExwUGpQcFE0VVFXVnp1NkdSYlZpc0lsS2NCZlVOWUxOVXBncy9DSUhHZg2 https://datacentremoratorium.net/index.php/Resources:AirTrunk_MEL1 https://airtrunk.com/location/mel1-melbourne/ https://www.realestatesource.com.au/data-centre-giant-buys-350m-melbourne-site/ https://datacentremoratorium.net/index.php/Resources:Data_Centres_in_Greater_Melbourne | AJ4: 開啟地圖 | AK4: VIC-B、VIC-A
A5: NSW-002 | B5: 新南威爾斯州 | C5: Southern Highlands Data Campus (SHDC) — Data Building One (DB1) | D5: Cloud Carrier (Cloud Carrier Operations Pty Ltd) | E5: Nakar Property Pty Ltd（地主／開發商，Bella Vista）；Square Energy Pty Ltd（園區燃氣發電） | F5: 30 Douglas Road, Moss Vale NSW 2577 | G5: Moss Vale | H5: 2577 | I5: Wingecarribee Shire | J5: -34.515334 | K5: 150.36982 | L5: 門牌級 | M5: 28 | N5: 耗電量 | P5: Cloud Carrier DB1 頁面列『Total Power 28MW』、Data Hall 1,850 sqm、Deployment: Powered Shell、DLC 140 kW+/rack、PUE <1.15（IT 負載未明示，故標 power_consumption）。2024-09 發表時 DB1 為 15 MW，園區最終可擴至 300 MW（W.Media 2024-09-27）。園區自建燃氣發電（官網稱數百 MW、脫離電網）。 | Q5: 已營運（有餘裕／擴建） | R5: 主清單 | T5: 2025-09 | U5: Nakar Property 範疇界定報告（Western Sydney Planning，2025-09，Planning Portal）：DA 21/1042（Wingecarribee 議會 2021-02-25 核准，已修改兩次）之後『the first data building (DB1) has now been constructed』。未見第三方確認通電日期、營運狀態或租戶；Cloud Carrier 官網以『Powered Shell』方式行銷 DB1。 | V5: DA 21/1042 於 2021-02-25 核准；確切動工日未知 | W5: DB1：2025-09 報告稱已建成；DB2 官網標示 coming soon | X5: 已可用／營運中 | Y5: Nakar Property 範疇界定報告 2025-09（Planning Portal）；Cloud Carrier 官網 | Z5: 可租 | AA5: 官網載明園區提供『Scalable Powered Shell Solutions』、載體中立、服務政府與企業客戶，屬可出租（powered shell／colocation）。尚無公開租戶，是否仍有 >=5 MW 未租出容量為合理推定，非明確證據。 | AB5: 未公開 | AC5: Wingecarribee Council DA 21/1042（DB1，2021-02-25）；DA 24/0055（14 MW 燃氣發電，2024-04-19 核准）；DA 26/0352（燃氣發電，2025-09-11 遞交）；SSD-102795459（673.2 MW 燃氣發電廳，SEARs 2025-12-22） | AD5: 中 | AE5: (1) DB1 容量：W.Media 2024-09-27 為 15 MW；Cloud Carrier 官網現列 Total Power 28 MW。(2) 園區上限：2024 稱 300 MW 地址備註：Cloud Carrier 官網聯絡頁載明 Campus: Southern Highlands Data Campus, 30 Douglas Road, Moss Vale NSW 2577；範疇界定報告：Lot 40 DP 1288692，約 67 ha。DB1、DB2 與後續建築皆在同一地址。 | AF5: https://www.planningportal.nsw.gov.au/major-projects/projects/southern-highlands-data-campus-power-station https://majorprojects.planningportal.nsw.gov.au/prweb/PRRestService/mp/01/getContent?AttachRef=PDA-95012491%2120250926T033914.129+GMT https://majorprojects.planningportal.nsw.gov.au/prweb/PRRestService/mp/01/getContent?AttachRef=SSD-102795459%2120251222T014859.011+GMT | AG5: https://cloudcarrier.com/campus/ https://cloudcarrier.com/db1/ https://cloudcarrier.com/contact-us/ | AH5: https://w.media/cloud-carrier-launches-australias-first-liquid-cooled-data-campus-in-the-southern-highlands/ | AI5: https://www.planningportal.nsw.gov.au/major-projects/projects/southern-highlands-data-campus-power-station https://majorprojects.planningportal.nsw.gov.au/prweb/PRRestService/mp/01/getContent?AttachRef=PDA-95012491%2120250926T033914.129+GMT https://cloudcarrier.com/ https://cloudcarrier.com/campus/ https://cloudcarrier.com/db1/ https://cloudcarrier.com/contact-us/ https://cloudcarrier.com/about-us/ https://w.media/cloud-carrier-launches-australias-first-liquid-cooled-data-campus-in-the-southern-highlands/ https://majorprojects.planningportal.nsw.gov.au/prweb/PRRestService/mp/01/getContent?AttachRef=SSD-102795459%2120251222T014859.011+GMT | AJ5: 開啟地圖 | AK5: NSW-C、NSW-B
A6: VIC-003 | B6: 維多利亞州 | C6: Fujitsu Noble Park 資料中心（Next Capital 收購中） | D6: Fujitsu Australia（現營運）；Next Capital 於 2026-07-20 簽約收購，預計 2026 下半年交割 | E6: Fujitsu 自有土地與建物（DCD：owned and operated by Fujitsu）；買方為 Next Capital 第五期基金（A$3.75 億） | F6: 5 Summit Road (3-5 Summit Road), Noble Park North VIC 3174 | G6: Noble Park North | H6: 3174 | I6: City of Greater Dandenong（推定，未經官方來源確認） | J6: -37.947699 | K6: 145.18577 | L6: 來源提供 | M6: 12 | N6: 口徑不明 | P6: AFR（經 DCD 2026-07-20）稱 Noble Park 為 12MW；五站合計 25MW、約 7MW 已租給約 130 家客戶，即整體約 18MW 未租（推算），並稱可擴至合計 100MW（主要指 Greystanes 最高 60MW）。站點層級的已租或空置量未公布。Fujitsu 規格（Baxtel）：2 x 4MVA 主進線、2 x 1,800kW 柴油旋轉 UPS（N+1）、2,400kW 靜態 UPS、3 x 1,800kW 發電機（N+1），以此推算受保護 IT 容量遠低於 12MW，與 AFR 數字不一致。 | Q6: 已營運（有餘裕／擴建） | R6: 觀察名單 (出租性待確認) | S6: 出租性待確認：既有 Fujitsu 對外出租的主機代管/託管設施，Next Capital 計畫整合為獨立澳洲平台並擴建；但站點層級 5MW 以上的空置容量缺乏公開證據，列入僅為回應 先前 對 Noble Park 的查詢。 | T6: 2026-07-20 | U6: 不適用（既有 1988 年建、2015 年升級的營運中設施）。DCD 與 Fujitsu 聲明：交割前一切照常營運。 | V6: 不適用 | W6: 不適用（交易預計 2026 下半年完成，不含 North Ryde） | X6: 已可用／營運中 | Y6: DCD 2026-07-20（引 AFR 與 Fujitsu LinkedIn 聲明） | Z6: 待確認 | AA6: 既有 Fujitsu 對外出租的主機代管/託管設施，Next Capital 計畫整合為獨立澳洲平台並擴建；但站點層級 5MW 以上的空置容量缺乏公開證據，列入僅為回應 先前 對 Noble Park 的查詢。 | AB6: 約 130 家客戶（五站合計，AFR 經 DCD）；無單一大租戶公布 | AC6: 不適用 | AD6: 低 | AE6: 容量：AFR/DCD 12MW 對 Fujitsu 電氣規格（進線 2 x 4MVA、UPS 與發電機約 1.8-3.6MW 級）不一致；面積：DCD 3,600 平方公尺，Baxtel 引 Fujitsu 稱機房 3,800 平方公尺、建物 6,700 平方公尺。Next Capital 官網新聞稿未提供站點街址或容量（已開啟閱讀） 地址備註：Baxtel 標示 5 Summit Rd；DatacenterMap 標示 3-5 Summit Road（其頁面郵遞區號誤植為 3101）；OSM 建物標籤為 Fujitsu Data Centre, 3-5 Summit Road, Noble Park North 3174。土地 18,400 平方公尺、建物 6,700 平方公尺、機房 3,800 平方公尺（Baxtel 引 Fujitsu 規格）。 | AG6: https://nextcapital.com.au/next-capital-buys-fujitsu-australian-data-centres/ | AH6: https://www.datacenterdynamics.com/en/news/fujitsu-sells-australian-data-center-business-to-next-capital/ https://baxtel.com/data-center/fujitsu-noble-park https://www.datacentermap.com/australia/melbourne/fujitsu-melbourne/ | AI6: https://www.datacenterdynamics.com/en/news/fujitsu-sells-australian-data-center-business-to-next-capital/ https://baxtel.com/data-center/fujitsu-noble-park https://www.datacentermap.com/australia/melbourne/fujitsu-melbourne/ https://nextcapital.com.au/next-capital-buys-fujitsu-australian-data-centres/ https://nominatim.openstreetmap.org/search?q=5+Summit+Road+Noble+Park+VIC | AJ6: 開啟地圖 | AK6: VIC-C、VIC-A
A7: NSW-003 | B7: 新南威爾斯州 | C7: Fujitsu Greystanes Data Centre（出售予 Next Capital） | D7: Fujitsu Australia → Next Capital（簽約 2026-07-20，預計 2026 稍後交割） | E7: Next Capital（買方，透過其第五支基金） | F7: 6 Bellevue Circuit, Pemulwuy (Greystanes) NSW 2145 | G7: Pemulwuy | H7: 2145 | I7: 未確認（Cumberland 或 Parramatta） | J7: -33.8219 | K7: 150.9238 | L7: 來源提供 | M7: 未公布 | N7: 口徑不明 | P7: 媒體稱 Greystanes 場址潛力最高 60 MW，不是現有可用容量；Fujitsu 五站組合合計約 25 MW、約 7 MW 已租、可擴建到 100 MW。各站現況容量與空置量未公布。 | Q7: 已營運（有餘裕／擴建） | R7: 主清單 | T7: 2026-07-20 | U7: 非建設案。Next Capital 表示交割後將投資擴建並逐站評估擴充，但未公布投資額或容量目標；無申請或開工證據。 | V7: — | W7: 交割預計 2026 年稍後；擴建無時程 | X7: 已可用／營運中 | Y7: W.Media／Fujitsu／Next Capital 2026-07-20 | Z7: 可租 | AA7: Fujitsu 資料中心業務為 colocation 與託管服務；買方稱『available capacity and significant growth potential』。 | AB7: 約 130 家客戶（含政府機關）；Fujitsu 交割後仍為客戶 | AD7: 低 | AE7: 『up to 60MW』與整體組合 25 MW 容量矛盾；本場址的未租出容量沒有公開數字，列入是因為買方明確以『available capacity』與擴建作賣點。無街道地址。 地址備註：新聞只稱 Greystanes，未載街道；該場址為承租物業（leased），非 Fujitsu 自有。需查 Fujitsu／Next Capital 官方資料取得地址。 | AH7: https://w.media/next-capital-agrees-to-acquire-fujitsus-australian-data-centre-business/ https://bebeez.eu/2026/07/20/fujitsu-sells-australian-data-center-business-to-next-capital/ | AI7: https://w.media/next-capital-agrees-to-acquire-fujitsus-australian-data-centre-business/ https://bebeez.eu/2026/07/20/fujitsu-sells-australian-data-center-business-to-next-capital/ | AJ7: 開啟地圖 | AK7: NSW-C
A8: VIC-004 | B8: 維多利亞州 | C8: STACK MEL02（Truganina；Baxtel 另列 MEL02A/MEL02B） | D8: STACK Infrastructure | E8: STACK Infrastructure（2022 年接手 Hickory 的開發案）；施工方 Hickory（據 DCM wiki） | F8: 411 Palmers Road, Truganina VIC 3029 | G8: Truganina | H8: 3029 | I8: Wyndham City Council | J8: -37.817386 | K8: 144.7494 | L8: 門牌級 | M8: 252 | N8: 關鍵負載 | P8: STACK 官網 MEL02 頁（已讀）：標題「250MW of critical capacity」，內文 252 MW、單一建築、227,000 sq ft（21,000 m²）技術面積、14 英畝、自有 132 kV 變電站（總容量 300+ MW）。Baxtel 把 MEL02 拆成 MEL02A（2026 建成）與 MEL02B（2027 規劃），與 STACK 官網的「1 building」不一致。 | Q8: 施工中 | R8: 主清單 | T8: 2026-05-12 | U8: Wyndham 規劃許可 WYP14917/24（2024-12-20 提出、2025-07-04 核發）；S72 修改 WYP14917/24.05 於 2026-05-12 核發（PlanningAlerts 已讀）。建築許可序列（依 DCM wiki 整理 Wyndham 紀錄；wiki 標註部分核發日早於提出日，日期僅供參考）：拆除 2025-07-30；樁基與地下管線前置工程 2025-09；主體結構（地面及 L1 樓板、地面至 L5 垂直構件）2025-12；變電站與 6 座變壓器防火牆 2026-02；新變電站與室內裝修 2026-03。 | V8: 2025-07（拆除許可 2025-07-30） | W8: MEL02A：2026（Baxtel）；MEL02B：2027（Baxtel） | X8: 2026 Q4 – 2027 Q2 | Y8: Baxtel（聚合器）；STACK 未公布日期 | Z8: 可租 | AA8: STACK 為批發/超大規模出租業者，MEL02 未公布租戶；是否能分租 5 MW 須直接詢問。 | AB8: 未公布 | AC8: Wyndham WYP14917/24（.05 修改）；MPA26/0049（TfV 轉介，2026-04-27） | AD8: 中 | AE8: STACK 官網 1 棟 252 MW vs Baxtel MEL02A + MEL02B 兩階段；Baxtel 另列 MEL02A／MEL02B 分棟；STACK 官網僅列單棟 252 MW。 地址備註：取自 Wyndham 申請 WYP14917/24.05（PlanningAlerts 頁面「411 Palmers Road Truganina」）；STACK MEL01 在同路 369-399 Palmers Road。 | AF8: https://planningalerts.org.au/applications/3442743 https://www.planningalerts.org.au/applications/3442743 | AG8: https://www.stackinfra.com/locations/asia-pacific/melbourne/mel02/ | AH8: https://baxtel.com/data-center/stack-melbourne-mel02 https://baxtel.com/data-center/stack-mel02b https://datacentremoratorium.net/index.php/Resources:STACK_MEL02_Campus https://www.datacenterdynamics.com/en/news/stack-tops-out-swiss-data-center-completes-construction-in-melbourne/ | AI8: https://planningalerts.org.au/applications/3442743 https://www.stackinfra.com/locations/asia-pacific/melbourne/mel02/ https://baxtel.com/data-center/stack-melbourne-mel02 https://baxtel.com/data-center/stack-mel02b https://datacentremoratorium.net/index.php/Resources:STACK_MEL02_Campus https://www.planningalerts.org.au/applications/3442743 https://www.datacenterdynamics.com/en/news/stack-tops-out-swiss-data-center-completes-construction-in-melbourne/ | AJ8: 開啟地圖 | AK8: VIC-A、VIC-B
A9: WA-001 | B9: 西澳州 | C9: CDC Maddington Campus (MA1-MA4), Perth | D9: CDC Data Centres (CDC) | E9: CDC Data Centres（股東：Infratil 49.72%，Infratil ASX 2026-07-06；澳洲 Future Fund 約 34.6%，The West Australian 2025-08-11） | F9: 307, 323 and 329 Kenwick Road and 582 Bickley Road, Maddington WA 6109 | G9: Maddington | H9: 6109 | I9: City of Gosnells | J9: -32.030017 | K9: 115.99953 | L9: 街道級 | M9: 200 | N9: 口徑不明 | O9: 34 | P9: (1) 園區總量：CDC 新聞稿（2025-08-11/12）稱完成後 up to 200 megawatts of high-density capacity；The West Australian 2025-09-10 稱獲批設施需約 200 MW 電力；Gosnells 市長 Terresa Lynes 於 ABC（2026-08-13）稱 eventually a 200-megawatt data centre。CDC 未說明是 IT 還是電力口徑。(2) 第一階段：Infratil/CDC 的 ASX 簡報（2026-05-05 公告第 4 頁；FY26 業績 2026-05-26 簡報第 11 頁，即 PDF 第 16 頁）標示 Perth 在建 34 MW（built MW，截至 2026-03-31），應為第一棟 MA1；同一簡報另列 Perth future build 至 FY34 為 101 MW，兩者合計 135 MW，低於 200 MW 標稱（口徑或範圍差異，未釐清）。(3) 2026-09-16 Infratil Investor Day 起改以 leasable capacity（ICT MW）披露，Perth 未另列 MW。(4) 首期投資 A$415m（CDC，2025-08）。(5) 全園區四棟二層樓，最高 24 m（CDC 官網）。 | Q9: 施工中 | R9: 主清單 | T9: 2026-09-16 | U9: (1) CDC 官網時間軸：DA 2025-09 核准、2025-10 場地整備與早期工程開始、2025-12 主體工程開始、2026-10 開始機房 fit-out、2027-01 開始營運。(2) CDC Maddington Project update September 2026（PDF，已讀）：第一棟（四棟之首）外殼幾乎完成、第一台塔吊已拆除、第二台本月拆除、永久電力已接通、污水管接駁即將開工、今年稍後開始系統測試。(3) Infratil Investor Day 簡報（ASX 2026-09-16；CDC 部分頁碼 6、9，即 PDF 第 105、108 頁）：第 6 頁 MA1 標示為在建、MA2 標示為 future development - land secured（以圖例顏色目視判讀）；第 9 頁附 Maddington 施工照片，稱 structure of CDC's inaugural Perth data centre nearing completion。(4) 政府：Metro Outer DAP 於 2025-09-10 核准（The West Australian、Business News 2025-09-10；Gosnells 市長 ABC 2026-08-13 證實 2025 年 9 月核准）。(5) CDC COO Glenn Uidam 於 2026-09-18 對 The West Australian 稱 Maddington 已施工數月，預計三四個月內開始營運。 | V9: 2025-10（場地整備與早期工程）；2025-12（主體工程） | W9: MA1：2027-01 開始營運（CDC 官網）；early 2027（CDC Project update 2026-09）。MA2-MA4：無官方日期（Baxtel 稱 Building 3 計畫 2029，屬聚合站，僅供參考）。 | X9: 2026 Q4 – 2027 Q2 | Y9: 營運商 CDC 官網及 Project update September 2026（一手，2026-10-03 讀取）；Infratil Investor Day（ASX 2026-09-16）稱在建資料中心將於 FY27-29 交付。 | Z9: 大概可租 | AA9: CDC 是批發型出租營運商，但對台灣租戶有三項保留：(a) Infratil 2026-09-16 稱 CDC 在已簽約容量的地點全面施工，MA1（34 MW）很可能已被預租（推論，原文未明說）；(b) CDC COO 於 2026-09-18 對 The West Australian 稱 CDC 主要服務政府機構與水電等關鍵基礎設施營運商，並表示對不在核心範圍的客戶會說不；(c) 目前只有 MA1 在建，MA2 為土地已取得的未來開發，MA3-MA4 無資訊。 | AB9: Maddington 尚無公開具名租戶。CDC 全國客戶包括 RBA、CSIRO、Western Sydney Airport（The West Australian 2025-08-11）；CDC 稱 Maddington 針對政府、研究、國防、關鍵基礎設施客戶。 | AC9: Metro Outer DAP 2025-09-10 核准（City of Gosnells 建議核准）；DAP 申請編號未取得。The West Australian 2025-08-11 稱 CDC 於 2025-06 提出 DA。 | AD9: 高 | AE9: (1) 容量：CDC 稱最高 200 MW，Infratil 披露 Perth 在建 34 MW + 未來 101 MW = 135 MW（built MW，2026-03-31）。(2) 營運時間：2025-08 的 DCD/W.Media/Baxtel 稱 2026 年營運，CDC 官網與 2026-09 update 為 2027-01 / early 2027，以後者為準。(3) 地址：DatacenterMap 稱 307 Kenwick Rd，CDC 稱 Bickley Road 旁，無法調和。(4) 已知事實清單所稱 first building operational Jan 2027 與 CDC 官網一致，確認無誤。(5) 付費牆：The West Australian 與 Business News 僅讀到前段；(1) 金額：媒體（W.Media／Baxtel 2025-08）稱 A$415m 為第一階段投資，但 DAP 報告 Form 1 的 Value of Development 為 A$415m 且涵蓋全部四棟，口徑不同。(2) 營運時間：2025-08 媒體稱 2026 年營運，CDC 2026-09 官方更新改為 2027 年初，以後者為準。(3) 棟數／面積：Baxtel 稱 3 棟、19 英畝；DAP 文件為 4 棟、基地 76,037 sqm（約 18.8 英畝）。(4) 容量：CDC 稱完成後 200 MW，而 Infratil 圖表只顯示 Perth 在建 34 MW（WA-A 另引 future build 101 MW，合計 135 MW，與 200 MW 有差距，口徑未釐清） 地址備註：DAP/25/02926 地址為 Lots 1, 10, 1 (No. 307, 323, 329) Kenwick Road 與 Lot 500 (No. 582) Bickley Road，核准條件要求合併為單一地契；基地約 76,037 sqm（7.6 ha），位於 Kelvin Road 與 Kenwick Road 轉角，緊鄰 Tonkin Highway；CDC 對外只稱『the industrial area off Bickley Road』。屬 Maddington Kenwick Strategic Employment Area（MKSEA）Precinct 1。變電站在圖上標示 By Others，不含在本次核准內，需另案提出 DA。先前資料 所引 DatacenterMap 的 307 Kenwick Rd 即上述 Lot 1，已由 DAP 文件證實。 | AF9: https://announcements.asx.com.au/asxpdf/20260916/pdf/074490wlf78g7n.pdf https://announcements.asx.com.au/asxpdf/20260526/pdf/06zymgqsx9p9y5.pdf https://announcements.asx.com.au/asxpdf/20260505/pdf/06z8f5lpdqcb57.pdf https://www.planning.wa.gov.au/docs/default-source/daps/minutes---no-102---city-of-gosnells.pdf?sfvrsn=9164d69f_1 https://www.planning.wa.gov.au/docs/default-source/daps/agenda---no-102---city-of-gosnells.pdf?sfvrsn=36d5cb68_1 https://www.planning.wa.gov.au/docs/default-source/daps/related-information---no-102---part-b---city-of-gosnells.pdf?sfvrsn=f47a3ead_1 https://www.planning.wa.gov.au/development-assessment-panels/daps-agendas-and-minutes/metro-outer-agenda-and-minutes | AG9: https://cdc.com/locations/perth/maddington/ https://cdc.com/media/4y2fcog4/maddington-project-update-september-2026.pdf https://cdc.com/locations/perth/ https://cdc.com/resources/news/cdc-announces-landmark-plan-to-drive-ai-and-advanced-technology-deployments-in-western-australia/ https://www.cdc.com/maddington | AH9: https://thewest.com.au/business/construction/maddington-data-centre-development-green-light-for-415m-project-and-construction-tipped-to-start-soon-c-19977544 https://thewest.com.au/business/infrastructure/cdc-data-centres-unveils-plans-for-415m-maddington-data-centre-c-19636890 https://www.businessnews.com.au/article/Maddington-s-415m-data-centre-approved https://www.abc.net.au/news/2026-08-13/councils-grapple-with-data-centre-applications/107029724 https://www.yourlocalexaminer.com.au/have-your-say-on-data-centre/ https://w.media/cdc-data-centres-plans-was-largest-ai-and-advanced-technology-campus/ https://www.datacenterdynamics.com/en/news/australias-cdc-plans-200mw-data-center-campus-outside-perth/ https://baxtel.com/data-center/cdc-maddington-perth https://baxtel.com/news/cdc-plans-200mw-data-center-campus-outside-perth https://www.projectory.com.au/article/415m-data-centre-development-approved-in-wa-to-support-digital-infrastructure-and-advanced-tech-capabilities https://renewmap.com.au/resources/projects/wa/datacentre/ | AI9: https://cdc.com/locations/perth/maddington/ https://cdc.com/media/4y2fcog4/maddington-project-update-september-2026.pdf https://cdc.com/locations/perth/ https://cdc.com/resources/news/cdc-announces-landmark-plan-to-drive-ai-and-advanced-technology-deployments-in-western-australia/ https://announcements.asx.com.au/asxpdf/20260916/pdf/074490wlf78g7n.pdf https://announcements.asx.com.au/asxpdf/20260526/pdf/06zymgqsx9p9y5.pdf https://announcements.asx.com.au/asxpdf/20260505/pdf/06z8f5lpdqcb57.pdf https://www.abc.net.au/news/2026-08-13/councils-grapple-with-data-centre-applications/107029724 https://www.yourlocalexaminer.com.au/have-your-say-on-data-centre/ https://thewest.com.au/business/construction/maddington-data-centre-development-green-light-for-415m-project-and-construction-tipped-to-start-soon-c-19977544 https://thewest.com.au/business/infrastructure/cdc-data-centres-unveils-plans-for-415m-maddington-data-centre-c-19636890 https://w.media/cdc-data-centres-plans-was-largest-ai-and-advanced-technology-campus/ https://www.datacenterdynamics.com/en/news/australias-cdc-plans-200mw-data-center-campus-outside-perth/ https://www.projectmanagementplanet.com.au/post/cdcs-maddington-data-centre https://baxtel.com/data-center/cdc-maddington-perth https://www.planning.wa.gov.au/docs/default-source/daps/minutes---no-102---city-of-gosnells.pdf?sfvrsn=9164d69f_1 https://www.planning.wa.gov.au/docs/default-source/daps/agenda---no-102---city-of-gosnells.pdf?sfvrsn=36d5cb68_1 https://www.cdc.com/maddington https://baxtel.com/news/cdc-plans-200mw-data-center-campus-outside-perth https://renewmap.com.au/resources/projects/wa/datacentre/ | AJ9: 開啟地圖 | AK9: WA-A、WA-B
A10: VIC-005 | B10: 維多利亞州 | C10: STACK MEL01C + MEL01D（Truganina；MEL01 園區第三、四棟） | D10: STACK Infrastructure | E10: STACK Infrastructure；施工方 Hickory | F10: 399 Palmers Road, Truganina VIC 3029 | G10: Truganina | H10: 3029 | I10: Wyndham City Council | J10: -37.819933 | K10: 144.74764 | L10: 門牌級 | M10: 108 | N10: 口徑不明 | O10: 54 | P10: STACK 官網 MEL01 頁（已讀）：園區 180 MW、4 棟；MEL01A、B 各 36 MW（已營運）；MEL01C、D 各 54 MW（各 506,000 sq ft）；園區變電站 66kV/11kV、總容量 135 MW。108 MW = 2×54。 | Q10: 施工中 | R10: 主清單 | T10: 2025-11-26 | U10: STACK 官網 MEL01 頁：園區 180 MW、四棟（A、B 各 36 MW 已營運；C、D 各 54 MW），未載各棟狀態。DCD 2025-11-26：MEL01B 竣工，C/D 各 54 MW。承建商 Hickory 專案頁把『MEL01C&D』列在『Completed』類別（該頁稱位於 Laverton、單一三層建築，與 STACK 官網的 Truganina、兩棟不符），可能是土建完成、機電與啟用仍在進行。Baxtel：MEL01C 2026 年建成。缺少政府開工文件，需向 STACK 確認。 | V10: 未確認（2025-07 之後） | W10: MEL01C：2026-Q4；MEL01D：2027-Q2 | X10: 2026 Q4 – 2027 Q2 | Y10: Baxtel（聚合器；先前資料列 MEL01C 2026-Q4、MEL01D 2027-Q2；本次僅親見 MEL01C「Year Built 2026」）。STACK 未公布 | Z10: 可租 | AA10: STACK 批發/超大規模出租；MEL01 租戶未公布。MEL01A（2023-08）與 MEL01B（2025-11 竣工）各 36 MW 已營運，未見公開的剩餘容量證據，故不另列。 | AB10: 未公布 | AC10: Wyndham 規劃許可（編號未取得） | AD10: 中 | AE10: Hickory 專案頁稱 MEL01C&D 位於「Laverton」且為單一三層建築；STACK 稱位於 Truganina、為兩棟各 54 MW；Hickory 專案頁稱 C&D 為單一三層建築且位於 Laverton，STACK 官網為兩棟各 54 MW、位於 Truganina。 地址備註：DCM wiki 登記園區為 369-399 Palmers Road；Baxtel 與 DatacenterHawk 用 399 Palmers Road。 | AG10: https://www.stackinfra.com/locations/asia-pacific/melbourne/mel01/ https://www.stackinfra.com/about/news-press/press-releases/stack-infrastructure-secures-aud-1-3-billion-in-green-financing-to-accelerate-expansion-of-mel01-hyperscale-campus-in-melbourne/ https://www.hickory.com.au/project/mel01cd-2/ | AH10: https://www.datacenterdynamics.com/en/news/stack-tops-out-swiss-data-center-completes-construction-in-melbourne/ https://baxtel.com/data-center/stack-mel01c https://datacentremoratorium.net/index.php/Resources:STACK_MEL01_Campus | AI10: https://www.stackinfra.com/locations/asia-pacific/melbourne/mel01/ https://www.stackinfra.com/about/news-press/press-releases/stack-infrastructure-secures-aud-1-3-billion-in-green-financing-to-accelerate-expansion-of-mel01-hyperscale-campus-in-melbourne/ https://www.hickory.com.au/project/mel01cd-2/ https://www.datacenterdynamics.com/en/news/stack-tops-out-swiss-data-center-completes-construction-in-melbourne/ https://baxtel.com/data-center/stack-mel01c https://baxtel.com/data-center/stack-mel01b https://datacentremoratorium.net/index.php/Resources:STACK_MEL01_Campus | AJ10: 開啟地圖 | AK10: VIC-A、VIC-B
A11: TAS-001 | B11: 塔斯馬尼亞州 | C11: Firmus Project Southgate — Launceston (St Leonards) AI Factory 園區 | D11: Firmus Technologies（自營 AI 雲／AI factory 業者） | E11: Firmus Technologies（澳洲註冊；官方稱自行設計、建造、擁有並營運；規劃申請代理 Pitt&Sherry）；投資人含 NVIDIA、Ellerston Capital（W.Media 2025-09-26） | F11: 23 Killafaddy Road, St Leonards TAS 7250 | G11: St Leonards | H11: 7250 | I11: City of Launceston | J11: -41.441718 | K11: 147.17672 | L11: 來源提供 | M11: 84 | N11: 關鍵負載 | O11: 44 | P11: Firmus Southgate 官網（firmus.co/infrastructure/southgate，2026-10-03 讀取）寫 84 MW Critical IT Load、PUE 小於 1.10。Stage 1a 44 MW、Stage 1b 合計約 90 MW（Firmus 2025-07 發布；DCD 2025-09-02）；Stage 2 另有 300 MW 計畫但『須取得核准』，未見任何申請文件，故不列入本筆。Aurora Energy 與 Firmus 簽 3 年零售協議（2026-03-25）：自 2026-08 起爬升，2026-11 起最高 104 MW。DatacenterMap 標 400 MW 為聚合器數字，疑為塔州三站合計（Firmus 對國會稱三站合約容量約 444 MW），不採用。 | Q11: 施工中 | R11: 觀察名單 (出租性待確認) | S11: 出租性待確認：Firmus 自述『design, build, own and operate』（國會調查意見書 #120，2026-09），運算硬體為自有；對外銷售的是專屬 AI 運算容量（dedicated AI infrastructure capacity）與 GPU 雲（NVIDIA DGX Cloud Lepton，2025-06-12），未見出租機房空間（colocation／powered shell／wholesale）的公開要約。已公布的大客戶合約在墨爾本（Firmus 與 CDC Data Centres 合作，約 18,400 GB300）與東南亞（OpenAI、Meta），並非 Tasmania。對需要 ≥5 MW『可租機房容量』的台灣客戶，只能走與 Firmus 洽談專屬容量合約這條路，故標 uncertain，是否保留請 先前 決定。 | T11: 2026-09-08 | U11: (1) Firmus 官網 Tasmania Community Hub（2026-10-03 讀取）稱 Launceston 是『our anchor site — under construction now』；(2) Firmus 新聞稿 2026-03-02（firmus.co/newsroom，另見 ITWire 同日轉載）稱 Tasmania 綠地 AI Factory 園區施工中、預計 2026 年底完工；(3) ABC 2026-06-15 報導現場已有施工機具、預計『early next year』啟用；(4) 塔州政府 2026-09-08 提交國會的文件（Pulse Tasmania 2026-09-09 報導）將 St Leonards 列為 under construction；(5) Minister Felix Ellis 2026-08-31 函確認 St Leonards AI factory 已完成規劃核准程序（該函措辭仍稱 proposed to operate）；(6) Aurora 新聞稿 2026-03-25 稱供電自 2026-08 起爬升。未取得動工通知書、CEMP 等官方動工文件（塔州制度下無公開對應文件）。 | V11: 未知（2025-09 媒體稱『即將動工』；2026-03-02 公司稱已在施工） | W11: 公司：2026 年底（2026-03-02）；ABC 2026-06-15：2027 年初；Aurora 供電爬升 2026-08～2026-11（最高 104 MW） | X11: 2026 Q4 – 2027 Q2 | Y11: operator（Firmus 新聞稿 2026-03-02）／press（ABC 2026-06-15）／Aurora Energy 新聞稿 2026-03-25 | Z11: 待確認 | AA11: Firmus 自述『design, build, own and operate』（國會調查意見書 #120，2026-09），運算硬體為自有；對外銷售的是專屬 AI 運算容量（dedicated AI infrastructure capacity）與 GPU 雲（NVIDIA DGX Cloud Lepton，2025-06-12），未見出租機房空間（colocation／powered shell／wholesale）的公開要約。已公布的大客戶合約在墨爾本（Firmus 與 CDC Data Centres 合作，約 18,400 GB300）與東南亞（OpenAI、Meta），並非 Tasmania。對需要 ≥5 MW『可租機房容量』的台灣客戶，只能走與 Firmus 洽談專屬容量合約這條路，故標 uncertain，是否保留請 先前 決定。 | AB11: Tasmania 場址無公開客戶／租戶。Firmus 全公司客戶：未具名『先前ing global technology company』（墨爾本，2026-03-02）、OpenAI 與 Meta（東南亞場址，2026-09）、Fireworks AI（Firmus AI Cloud，2026-08）；NVIDIA 為投資人與夥伴。 | AC11: City of Launceston 規劃許可（特別議會會議 2025-09-01 背書，Pulse Tasmania／DCD 2025-09-02；W.Media 2025-09-26 另稱『7 月核准』）；DA 編號未取得 | AD11: 中 | AE11: (1) 容量：Stage 1a 44 MW／1b 合計約 90 MW（Firmus 2025；DCD 2025-09-02）vs 官網 84 MW critical IT vs Aurora 協議上限 104 MW vs 國會問答『100 MW』（tasgreensmps 頁）vs DatacenterMap 400 MW（聚合器，疑為三站合計）。(2) GPU 數：36,800 GB300（Firmus 2026-03-02）vs 36,000（W.Media 2025-09-26，兩階段合計）vs AFR 2026-06-08 標題『26,000 Nvidia chips』（僅見標題，未開啟全文）。(3) 投資額：Stage 1a A$2.1bn（2025）vs Aurora 新聞稿 A$5bn（2026-03-25）。(4) 完工時間：2026 年中（2025-09 說法）→2026 年底（2026-03）→2027 初（ABC 2026-06-15）。(5) 核准日：特別議會會議 2025-09-01（Pulse、DCD 2025-09-02）vs W.Media 2025-09-26 稱『7 月核准』。(6) Baxtel 清單頁把 Launceston Campus 標成 Operational 20 MW（聚合器，無佐證）；Oxford Economics 函稱 Launceston 是 Firmus『first operating Australian site』，應指 2019 年研發站。 地址備註：門牌取自 DatacenterMap／Baxtel 頁面與 Pulse Tasmania 報導；用地約 5 公頃。City of Launceston 的 DA 原件與地號未取得（該議會網站對自動抓取回 403），建議 先前 向議會規劃登記冊核對。另有 Firmus 自 2019 年起的 Launceston 研發小站（容量未公布，推定小於 5 MW，不列入）。 | AF11: https://parliament.tas.gov.au/__data/assets/pdf_file/0012/110730/2026-08-13-ProfRazay.pdf https://www.parliament.tas.gov.au/__data/assets/pdf_file/0012/110064/Aurora-Energy-Media-Release-Firmus-Technologies-25-March-2026_Redacted.pdf https://www.parliament.tas.gov.au/__data/assets/pdf_file/0010/112231/120.-Firmus-combined.pdf https://www.parliament.tas.gov.au/__data/assets/pdf_file/0012/112260/152.-Hydro-Tasmania-Submission.pdf | AG11: https://firmus.co/infrastructure/southgate https://firmus.co/ourcommitments/tasmaniancommunity https://firmus.co/newsroom/firmus-signs-multi-year-agreement-with-global-hyperscale-customer-at-project-southgate https://firmus.co/newsroom/tasmanian-world-first-ai-factory-zone-clears-path-for-firmus-project-southgate https://firmus.co/newsroom/firmus-technologies-expands-regional-ai-access-through-nvidia-dgx-cloud-lepton | AH11: https://www.abc.net.au/news/2026-06-15/firmus-ai-company-tasmania-biggest-power-user-three-sites/106783142 https://www.abc.net.au/news/2026-07-03/firmus-ai-data-centres-is-tasmania-ready/106869862 https://www.abc.net.au/news/2026-09-09/six-new-confidential-data-centre-proposals-tasmania-revealed/107131974 https://pulsetasmania.com.au/news/document-reveals-six-secret-ai-data-centre-proposals-for-tasmania/ https://pulsetasmania.com.au/news/launceston-council-approves-major-2-1-billion-ai-data-centre/ https://www.datacenterdynamics.com/en/news/firmus-gets-go-ahead-for-ai-data-center-project-in-launceston-tasmania/ https://w.media/firmus-wins-approval-to-build-2-1bn-ai-factory-in-launceston/ https://w.media/firmus-raises-aud-330-million-for-tasmania-ai-factory/ https://itwire.com/it-industry-news/deals/firmus-signs-multi-year-agreement-with-global-hyperscale-customer-202603020801.html https://tasgreensmps.org/parliament/questions/firmus-technologies-launceston-ai-data-centre/ https://www.datacentermap.com/australia/launceston/project-southgate/ https://baxtel.com/data-center/firmus-launceston-campus | AI11: https://parliament.tas.gov.au/__data/assets/pdf_file/0012/110730/2026-08-13-ProfRazay.pdf https://www.parliament.tas.gov.au/__data/assets/pdf_file/0012/110064/Aurora-Energy-Media-Release-Firmus-Technologies-25-March-2026_Redacted.pdf https://www.parliament.tas.gov.au/__data/assets/pdf_file/0010/112231/120.-Firmus-combined.pdf https://www.parliament.tas.gov.au/__data/assets/pdf_file/0012/112260/152.-Hydro-Tasmania-Submission.pdf https://firmus.co/infrastructure/southgate https://firmus.co/ourcommitments/tasmaniancommunity https://firmus.co/newsroom/firmus-signs-multi-year-agreement-with-global-hyperscale-customer-at-project-southgate https://firmus.co/newsroom/tasmanian-world-first-ai-factory-zone-clears-path-for-firmus-project-southgate https://firmus.co/newsroom/firmus-technologies-expands-regional-ai-access-through-nvidia-dgx-cloud-lepton https://www.abc.net.au/news/2026-06-15/firmus-ai-company-tasmania-biggest-power-user-three-sites/106783142 https://www.abc.net.au/news/2026-07-03/firmus-ai-data-centres-is-tasmania-ready/106869862 https://www.abc.net.au/news/2026-09-09/six-new-confidential-data-centre-proposals-tasmania-revealed/107131974 https://pulsetasmania.com.au/news/document-reveals-six-secret-ai-data-centre-proposals-for-tasmania/ https://pulsetasmania.com.au/news/launceston-council-approves-major-2-1-billion-ai-data-centre/ https://www.datacenterdynamics.com/en/news/firmus-gets-go-ahead-for-ai-data-center-project-in-launceston-tasmania/ https://w.media/firmus-wins-approval-to-build-2-1bn-ai-factory-in-launceston/ https://w.media/firmus-raises-aud-330-million-for-tasmania-ai-factory/ https://itwire.com/it-industry-news/deals/firmus-signs-multi-year-agreement-with-global-hyperscale-customer-202603020801.html https://tasgreensmps.org/parliament/questions/firmus-technologies-launceston-ai-data-centre/ https://www.datacentermap.com/australia/launceston/project-southgate/ https://baxtel.com/data-center/firmus-launceston-campus | AJ11: 開啟地圖 | AK11: TAS-A
A12: VIC-006 | B12: 維多利亞州 | C12: Vantage MEL1（Tullamarine） | D12: Vantage Data Centers（APAC 業務屬 DigitalBridge 的 Skyline JV，Aware Super 持少數股權） | E12: Vantage Data Centers | F12: 43-45 Tullamarine Park Road, Tullamarine VIC 3043 | G12: Tullamarine | H12: 3043 | I12: Brimbank City Council（DCM wiki 列；未查證，Tullamarine 亦涉 Hume） | J12: -37.70818 | K12: 144.8719 | L12: 門牌級 | M12: 64 | N12: 關鍵負載 | P12: Vantage 官網（已讀）：單一資料中心、7 英畝（3 ha）、64 MW critical IT、25,000 m²、場內 66 kV 變電站、Jemena 供電；Baxtel 的 48 MW／三棟為舊版文案。 | Q12: 施工中 | R12: 主清單 | T12: 2026-10 | U12: Brimbank 公開規劃登記冊（資料截至 2025-07-22，已讀）：P435/2021『Use and development of the land for a data centre and removal of easements』（1/7、2/7、5 Allied Dr 與 43-45 Tullamarine Park Rd）2021-10-29 核發；Pt 3 修訂『alter the height and layout of the data centre』2024-12-05 受理、2025-03-18 核發。Vantage 官網文案為將來式（will provide）；Baxtel 標 Under Construction、2026 年建成；DCM wiki 列 Operating。沒有具日期的施工事件，狀態待查。登記冊未具名 Vantage，營運商取自 DCM wiki 對這些地址的標註。 | V12: 未公布 | W12: 2026（Baxtel，聚合器） | X12: 2026 Q4 – 2027 Q2 | Y12: 聚合器 | Z12: 大概可租 | AA12: Vantage 為批發型，官網稱專為 AI 工作負載設計。 | AB12: 未公布 | AC12: Brimbank P435/2021（Pt 3 修訂 2025-03-18 核發） | AD12: 中 | AE12: 狀態：施工中（Baxtel）vs 營運中（DCM wiki）vs 官網將來式；MW 64（官網）vs 48（Baxtel）；MW：64（官網/RenewMap/DCM wiki）vs 48（Baxtel）；狀態：Under construction（Baxtel）vs Operating（DCM wiki）；棟數：1 棟（官網）vs 3 棟（Baxtel）。Vantage 官網 APAC 地點只列 Melbourne（MEL1），沒有 MEL-C。 地址備註：Baxtel 與 DCM wiki：43-45 Tullamarine Park Rd；wiki 另列 5 Allied Drive, Tullamarine。Vantage 官網稱距墨爾本機場約 6 公里、鄰 NEXTDC M2 與 AirTrunk MEL2。 | AF12: https://records.brimbank.vic.gov.au/ExternalLinkAPI/api/document/?docKey=UHZYRmNFYWVDaUN0clNmekJwVXhMUExwUGpQcFE0VVFXVnp1NkdSYlZpc0lsS2NCZlVOWUxOVXBncy9DSUhHZg2 | AG12: https://vantage-dc.com/data-centers/melbourne/ https://vantage-dc.com/data-center-locations/apac/melbourne-australia/ | AH12: https://baxtel.com/data-center/vantage-melbourne-mel1 https://datacentremoratorium.net/index.php/Resources:Vantage_MEL1 | AI12: https://vantage-dc.com/data-centers/melbourne/ https://records.brimbank.vic.gov.au/ExternalLinkAPI/api/document/?docKey=UHZYRmNFYWVDaUN0clNmekJwVXhMUExwUGpQcFE0VVFXVnp1NkdSYlZpc0lsS2NCZlVOWUxOVXBncy9DSUhHZg2 https://datacentremoratorium.net/index.php/Resources:Vantage_MEL1 https://vantage-dc.com/data-center-locations/apac/melbourne-australia/ https://baxtel.com/data-center/vantage-melbourne-mel1 https://datacentremoratorium.net/index.php/Resources:Data_Centres_in_Greater_Melbourne | AJ12: 開啟地圖 | AK12: VIC-B、VIC-A
A13: NSW-004 | B13: 新南威爾斯州 | C13: GreenSquare DC SYD1 — Stage 1（既有資料中心建築改造，Norwest） | D13: GreenSquare DC (GSDC) | E13: GreenSquare DC | F13: 3 Brookhollow Avenue, Norwest NSW 2153 | G13: Norwest | H13: 2153 | I13: The Hills Shire | J13: -33.732527 | K13: 150.96802 | L13: 來源提供 | M13: 15 | N13: 口徑不明 | O13: 15 | P13: 15 MW 引自 先前資料（Stage 1 15 MW），我方未能獨立驗證；W.Media 2026-09-21 僅稱 SYD1 為『100MW-plus campus』；範疇界定函說明現址原有 4 MW 資料中心（D93/318，1993 年核准）。 | Q13: 施工中 | R13: 主清單 | T13: 2026-09-21 | U13: W.Media 2026-09-21：Stage 1 為既有資料中心建築的 adaptive reuse，建築正升級以支援高密度運算；首批客戶 Sharon AI 預計部署約 8,200 片 NVIDIA Blackwell Ultra GPU，初始營運目標 2026 Q4。先前資料 另稱總承包商為 Erilyan。因屬既有建築改造，Planning Portal 無對應 SSD 開工文件。 | V13: 未知（改造工程進行中） | W13: 2026-Q4（初始營運，W.Media 2026-09-21） | X13: 2026 Q4 – 2027 Q2 | Y13: W.Media 2026-09-21 引述 GreenSquare | Z13: 可租 | AA13: GreenSquare 為批發型出租業者；但 Stage 1 首批容量已由 Sharon AI 長期合約錨定（合約容量未公開），剩餘可租量不明。 | AB13: Sharon AI（Nasdaq 上市、NVIDIA Cloud Partner；首階段錨定客戶，2026-09 簽約） | AC13: 既有建築改造（D93/318，1993 年核准）；未見 SSD。Stage 2 見 SSD-81928961 | AD13: 中 | AE13: 完工時間：先前資料稱 Q3 2026，W.Media 稱初始營運 2026 Q4。首批客戶已簽，對 5 MW 新租戶而言 Stage 1 剩餘量可能很小；是否已完工：先前資料 2026-Q3 完工，Baxtel 稱已營運，無營運商確認；總量：先前資料 110 MW、官網 100MW+ IT、SSD EIS 的第二期 IT 96 MW；先前資料「Stage 1 15 MW」——與規劃小組 EDC/Stage 1 敘述的 14.9 MW 一致。 地址備註：Lot 2021 DP 831173，約 51,867 m2；位於 Norwest Business Park，Norwest 地鐵站以東約 500 m。Stage 1 與 Stage 2（）同一地址。 | AF13: https://www.planningportal.nsw.gov.au/major-projects/projects/brookhollow-avenue-data-centre-expansion-norwest https://www.planningportal.nsw.gov.au/planning-panel/alterations-and-additions-existing-data-centre | AG13: https://www.greensquaredc.com/locations https://greensquaredc.com/locations/ | AH13: https://w.media/greensquare-signs-sharon-ai-as-first-customer-for-syd1-data-centre-campus/ https://baxtel.com/data-center/greensquaredc-sydney-syd1 | AI13: https://www.planningportal.nsw.gov.au/major-projects/projects/brookhollow-avenue-data-centre-expansion-norwest https://majorprojects.planningportal.nsw.gov.au/prweb/PRRestService/mp/01/getContent?AttachRef=PDA-81670721%2120250328T083256.004+GMT https://w.media/greensquare-signs-sharon-ai-as-first-customer-for-syd1-data-centre-campus/ https://www.planningportal.nsw.gov.au/planning-panel/alterations-and-additions-existing-data-centre https://www.greensquaredc.com/locations https://api.apps1.nsw.gov.au/eplanning/data/v0/OnlineDA https://greensquaredc.com/locations/ | AJ13: 開啟地圖 | AK13: NSW-C、NSW-A、NSW-B
A14: NSW-005 | B14: 新南威爾斯州 | C14: CDC Marsden Park Data Centre Campus（Hollinsworth Road） | D14: CDC Data Centres（Canberra Data Centres） | E14: CDC Data Centres Pty Ltd（SSD 申請人，核准通知書所載）；股東含 Infratil（CDC 官網新聞標題） | F14: 105 and 113 Hollinsworth Road, Marsden Park NSW 2765 | G14: Marsden Park | H14: 2765 | I14: Blacktown | J14: -33.722607 | K14: 150.83633 | L14: 來源提供 | M14: 504 | N14: 耗電量 | P14: 入口網站/核准文件口徑為耗電 504 MW，六棟四層樓、720 MVA 變電站（先前資料讀取）；CDC 2024-10-25 新聞稿稱 504 MW 為 ICT capacity（口徑不同，IT 負載可能較低）；CDC 官網 Marsden Park 頁寫五棟四層加一棟兩層。前置議會 DA-24-00542（2024-11-14 核准，CIV A$53.94m）僅為 5 MW 設施。Baxtel 另列 79 MW、Q2 2026，屬聚合站估計。 | Q14: 施工中 | R14: 主清單 | T14: 2026-07-27 | U14: 入口網站 SSD-70889211 後續文件（於 2026-10-03 逐筆列出並從檔案識別碼解出上傳日）：Letter for SSDA Works Commencement（檔名 260714，上傳 2026-07-22）、CEMP Approval Letter（2026-05-12）、Approval of Staging Request（2026-04-24）、Approval of Updated Staging Request（2026-06-12）、ESCP 核准（2026-07-27）。CDC 官網新聞（2024-10-25）已稱 minor earthworks underway。 | V14: 2024-10（CDC 稱輕微土方，新聞稿 2024-10-25）；SSD 工程開工函 2026-07-14；CDC 官網排程的 early/civil works 自 2025-11 起 | W14: 分期交付 2027-09 至 2029-12（staggered handover through 2029） | X14: 2027 下半年 | Y14: CDC 官網 Marsden Park 頁排程（未標日期，2026-10-03 讀取）：early/civil 2025-11 至 2027-06、structural 2026-07 至 2027-11、services/fit-out 2027-02 至 2028-11、commissioning/handover 2027-09 至 2029-12 | Z14: 大概可租 | AA14: CDC 為批發型主機代管；2025 年簽下 555 MW、30 年的美國客戶合約（CDC 官網新聞標題，是否落在本園區未證實），Marsden Park 容量可能大多已預訂，需向 CDC 確認未預訂部分。 | AB14: 未公布；CDC 與一家美國客戶簽有 555 MW 合約（與本園區關係未證實） | AC14: SSD-70889211（2025-11-27 核准）；前置 DA-24-00542 / PPSSCC-562（2024-11-14 核准） | AD14: 高 | AE14: MW 口徑不一：入口網站 504 MW 為耗電、CDC 新聞稿 504 MW 為 ICT capacity；Baxtel 79 MW 且 Q2 2026 啟用，與 CDC 官網的 2027-09 起分期交付不符，以 CDC 官網為準；Portal 標題「504 MW power consumption」vs 評估報告「720 MW 最大電力 / 504 MW IT」；先前資料採 504 MW power consumption——應改註為 IT load 地址備註：SSD-70889211 與前置議會 DA-24-00542（PPSSCC-562）皆列 105 與 113 Hollinsworth Road；專用變電站亦在 Hollinsworth Road（CDC 官網）。 | AF14: https://www.planningportal.nsw.gov.au/major-projects/projects/marsden-park-data-centre https://www.planningportal.nsw.gov.au/planning-panel/canberra-data-centre https://majorprojects.planningportal.nsw.gov.au/prweb/PRRestService/mp/01/getContent?AttachRef=SSD-70889211%2120251128T050853.709+GMT https://majorprojects.planningportal.nsw.gov.au/prweb/PRRestService/mp/01/getContent?AttachRef=SSD-70889211-PA-23%2120260722T061549.935+GMT https://majorprojects.planningportal.nsw.gov.au/prweb/PRRestService/mp/01/getContent?AttachRef=SSD-70889211-PA-21%2120260612T050533.584+GMT | AG14: https://www.cdc.com.au/locations/sydney-and-regional-nsw/marsden-park/ https://www.cdc.com.au/resources/news/cdc-data-centres-breaks-ground-on-new-state-of-the-art-data-centre-development-in-marsden-park-industrial-precinct/ | AH14: https://baxtel.com/data-center/cdc-marsden-park-campus | AI14: https://www.planningportal.nsw.gov.au/major-projects/projects/marsden-park-data-centre https://www.planningportal.nsw.gov.au/planning-panel/canberra-data-centre https://www.cdc.com.au/locations/sydney-and-regional-nsw/marsden-park/ https://www.cdc.com.au/resources/news/cdc-data-centres-breaks-ground-on-new-state-of-the-art-data-centre-development-in-marsden-park-industrial-precinct/ https://baxtel.com/data-center/sydney https://majorprojects.planningportal.nsw.gov.au/prweb/PRRestService/mp/01/getContent?AttachRef=SSD-70889211%2120251128T050853.709+GMT https://majorprojects.planningportal.nsw.gov.au/prweb/PRRestService/mp/01/getContent?AttachRef=SSD-70889211-PA-23%2120260722T061549.935+GMT https://majorprojects.planningportal.nsw.gov.au/prweb/PRRestService/mp/01/getContent?AttachRef=SSD-70889211-PA-21%2120260612T050533.584+GMT | AJ14: 開啟地圖 | AK14: NSW-A、NSW-B
A15: NSW-006 | B15: 新南威爾斯州 | C15: NEXTDC S4 Horsley Park（SSD-63741210） | D15: NEXTDC Limited | E15: NEXTDC Limited（申請人）；總包 Multiplex（lead 資料） | F15: 16 Johnston Crescent, Horsley Park NSW 2175 | G15: Horsley Park | H15: 2175 | I15: Fairfield City（部分工程在 Blacktown） | J15: -33.82784 | K15: 150.82457 | L15: 來源提供 | M15: 365 | N15: IT 負載 | O15: 250 | P15: NEXTDC FY26 簡報（2026-08-27）：S4 升級至 365 MW IT，其中 250 MW 在建、115 MW 規劃；NSW 核准書載 294 MW；Multiplex 新聞稿稱 350 MW；RenewMap 記 232 MW，口徑各不相同。 | Q15: 施工中 | R15: 主清單 | T15: 2026-09-23 | U15: SSD 核准 2025-12-24；CEMP Rev 3 與核准函 2026-02-23；HV 輸電線分階段核准 2026-05-28；「NXT S4 – TG Works – DPHI Condition A13」2026-05-20；Mod 1（設計修改）核准 2026-08-07、Mod 2（隔音牆增高）核准 2026-09-23。Multiplex 2026-03 宣布開工（先前資料，未重新開啟）。portal 上無「Notification of Commencement」文件。 | V15: 2026-03（Multiplex，lead 資料）；CEMP 2026-02-23 核准。 | W15: 評估報告：全案約 5 年／54 個月、四階段——Stage 1 Building C + HV 開關站/330 kV 變電站/輸電線/入口/水塔；Stage 2 Building D；Stage 3 Building A；Stage 4 Building B。第一期約 2027 年中（Multiplex，先前資料）。 | X15: 2027 下半年 | Y15: DPHI SSD Assessment Report（2025-12-24）；Multiplex（透過 先前） | Z15: 可租 | AA15: NEXTDC 以租賃方式出租；但 先前 引用 FY26 數據：已簽約使用量 740 MW、前置訂單 565 MW、已建成 287.9 MW，容量幾乎已被預訂，新租戶需談後續階段。 | AB15: 政府文件未揭露 | AC15: SSD-63741210；Mod 1、Mod 2；後續 Phase 2 = SSD-108864209 | AD15: 高 | AE15: 容量來源互相矛盾：DPHI 評估報告 294 MW（修訂後）；Portal 列表 250 MW；Multiplex 350 MW；RenewMap 232 MW（=原 EIS）。建議以 294 MW（power consumption）為官方數字；MW：核准文件 294 MW（耗電）、Multiplex 350 MW、RenewMap 232 MW；先前資料未載明 294 MW，此為更正。 地址備註：資料中心基地 8.206 公頃（IN1）；另含 Johnston Crescent / Old Wallgrove Road 道路預留地 1.16 公頃的 2.6 km、2×330 kV 輸電線，及 TransGrid Sydney West 變電站 43.09 公頃擴建。 | AF15: https://www.planningportal.nsw.gov.au/major-projects/projects/nextdc-s4-data-centre-horsley-park https://majorprojects.planningportal.nsw.gov.au/prweb/PRRestService/mp/01/getContent?AttachRef=SSD-63741210%2120251224T003217.140+GMT https://www.planningportal.nsw.gov.au/major-projects/projects/nextdc-s4-modification-1-design-modifications https://www.planningportal.nsw.gov.au/major-projects/projects/nextdc-s4-horsley-park-mod-2-acoustic-barrier-amendments | AI15: https://www.planningportal.nsw.gov.au/major-projects/projects/nextdc-s4-data-centre-horsley-park https://majorprojects.planningportal.nsw.gov.au/prweb/PRRestService/mp/01/getContent?AttachRef=SSD-63741210%2120251224T003217.140+GMT https://www.planningportal.nsw.gov.au/major-projects/projects/nextdc-s4-modification-1-design-modifications https://www.planningportal.nsw.gov.au/major-projects/projects/nextdc-s4-horsley-park-mod-2-acoustic-barrier-amendments | AJ15: 開啟地圖 | AK15: NSW-B、NSW-A
A16: VIC-007 | B16: 維多利亞州 | C16: AirTrunk MEL2（Tullamarine，前 Honda 廠址；DFP 許可 PA2403452） | D16: AirTrunk（修訂／更正申請人為 Airtrunk Mel2 Pty Ltd；Blackstone／CPP Investments 控股） | E16: AirTrunk。原 DFP 申請人 EMKC3 Pty Ltd（經 Urbis）；AirTrunk 於 2025-12-24 公告收購該址；土地先由 Hines 自 Honda 購入（2022）及 A$187m 價格皆僅見 DCM wiki，未獨立查證 | F16: 85 Sharps Road, Tullamarine VIC 3043 | G16: Tullamarine | H16: 3043 | I16: Brimbank City Council（DTP 官員報告：Brimbank Planning Scheme） | J16: -37.706813 | K16: 144.86181 | L16: 門牌級 | M16: 354 | N16: 口徑不明 | P16: AirTrunk 官網與 2025-12-24 新聞稿：354+ MW（官網另載 8.070 ha、GFA 45,578 m²、最多 32 間技術資料廳 42,240 m²、66 kV 雙回路供電）。DTP 官員報告：單棟、高 32.5 m（含設備 38.15 m）、GFA 45,578 m²。DCM wiki 稱 2026-06 修訂將資料廳由 8 間減為 5 間並調整屋頂設備，MW 是否受影響未知。AirTrunk 未說明 354 MW 口徑（IT／關鍵／耗電）。W.Media 標題寫 345 MW 為筆誤。 | Q16: 已核准、尚未動工 | R16: 主清單 | T16: 2026-08-14 | U16: DFP 許可 PA2403452：2024-12-20 受理、2025-02-04 公告、2025-03-28 核發（The Age：約 44 天、A$973m）；PA2403452-1 修訂 2026-06-26 核准；另有 S71 更正 2026-08-14 核准（2026-07-27 受理，申請人欄 Airtrunk Mel2 Pty Ltd，頁面已讀）。Brimbank 公開規劃登記冊（資料截至 2025-07-22，已讀）：VicSmart P47/2025（85 Sharps Rd，『carry out works (clearing, excavation and trenching)』，2025-02-14 受理、2025-02-27 核發，屬前業主階段的早期工程）。至 2026-10-03 未找到 AirTrunk 開工通知、動土新聞或建築許可，因此判定主體施工尚無硬證據。 | V16: 未公布（主體工程）；早期工程許可見 2025-02-27 | W16: 2027-H2（首期開放，多期建設） | X16: 2027 下半年 | Y16: AirTrunk 新聞稿 2025-12-24；CRN 2026-01-06（預定 2027 下半年啟用） | Z16: 大概可租 | AA16: AirTrunk 為超大規模批發型業者，客群為全球雲端與 AI 客戶；官網稱 carrier neutral。5 MW 級租戶是否可行須直接洽詢，容量可能以大型整租為主。 | AB16: 未公布 | AC16: DFP PA2403452（permit 2025-03-28；PA2403452-1 修訂 2026-06-26；更正 2026-08-14）；Brimbank VicSmart P47/2025（早期工程，2025-02-27 核發） | AD16: 高 | AE16: 先前資料稱 PA2403452 申請人未知：已確認即 AirTrunk MEL2（官網 GFA 45,578 m²、8.070 ha 與官員報告完全一致）。容量 354+ MW（AirTrunk）vs 345 MW（W.Media 標題）；資料廳 8 間（原許可）vs 5 間（2026-06 修訂，wiki）；狀態三說：CRN「2027 下半年營運」（隱含將/已開工）、Baxtel「planned」、RenewMap「construction」。本次查證結論：許可 2025-03-28 已核准、設計於 2026-06-26 剛改（8→5 棟），AirTrunk 2025-12-24 才完成購地，未見主體施工文件——判定 approved_not_started；若要趕上 2027-H2 營運，主體施工應在 2026 下半年啟動，建議向 AirTrunk 或 Brimbank 建築許可確認。先前資料 只列 PA2403452 為「unknown」，現確認為 AirTrunk MEL2。 地址備註：Lot 95 on PS 135452；Sharps Road 與 Keilor Park Drive 轉角，土地 8.07 ha，現有約 16,742 m² 兩層倉庫（前 Honda）。官員報告檔名曾誤寫 Sharps Street，指同址。DCM wiki 座標（-37.70658, 144.86374）屬社群來源，未採用。 | AF16: https://www.planning.vic.gov.au/planning-approvals/ministerial-permits-register/ministerial-permits/1ea17bd8-75be-ef11-b8e8-002248938a9c https://www.planning.vic.gov.au/planning-approvals/ministerial-permits-register/ministerial-permits/739c637a-54d6-42c8-a673-5c590bae387a https://sftpbspomppprod01.blob.core.windows.net/applicationfiles/1ea17bd8-75be-ef11-b8e8-002248938a9c_PA2403452%20-%2085%20Sharps%20Road,%20Tullamarine%20-%20Officer%20Report%20-%20REDACTED.pdf https://records.brimbank.vic.gov.au/ExternalLinkAPI/api/document/?docKey=UHZYRmNFYWVDaUN0clNmekJwVXhMUExwUGpQcFE0VVFXVnp1NkdSYlZpc0lsS2NCZlVOWUxOVXBncy9DSUhHZg2 https://www.planning.vic.gov.au/planning-approvals/ministerial-permits-register/ministerial-permits/975c57aa-6b34-f111-88b4-7c1e5262e513 | AG16: https://airtrunk.com/data-centres/mel2/ https://airtrunk.com/airtrunk-expands-australian-platform-with-a-second-hyperscale-data-centre-campus-in-melbourne/ https://airtrunk.com/location/mel2-melbourne/ | AH16: https://www.crn.com.au/news/2026/data-centre/airtrunk-new-melbourne-location-mel2 https://www.datacenterdynamics.com/en/news/airtrunk-acquires-site-in-melbourne-australia-for-354mw-data-center/ https://www.theage.com.au/national/victoria/1b-data-centre-given-planning-tick-in-just-75-days-as-state-gets-cosy-with-big-tech-20260219-p5o3sl.html https://w.media/airtrunk-to-add-345-mw-facility-in-aud-5bn-melbourne-investment/ https://datacenterdynamics.com/en/news/airtrunk-acquires-site-in-melbourne-australia-for-354mw-data-center https://datacentremoratorium.net/index.php/Resources:AirTrunk_MEL2 | AI16: https://www.planning.vic.gov.au/planning-approvals/ministerial-permits-register/ministerial-permits/1ea17bd8-75be-ef11-b8e8-002248938a9c https://sftpbspomppprod01.blob.core.windows.net/applicationfiles/1ea17bd8-75be-ef11-b8e8-002248938a9c_PA2403452%20-%2085%20Sharps%20Road,%20Tullamarine%20-%20Officer%20Report%20-%20REDACTED.pdf https://records.brimbank.vic.gov.au/ExternalLinkAPI/api/document/?docKey=UHZYRmNFYWVDaUN0clNmekJwVXhMUExwUGpQcFE0VVFXVnp1NkdSYlZpc0lsS2NCZlVOWUxOVXBncy9DSUhHZg2 https://airtrunk.com/data-centres/mel2/ https://airtrunk.com/airtrunk-expands-australian-platform-with-a-second-hyperscale-data-centre-campus-in-melbourne/ https://www.crn.com.au/news/2026/data-centre/airtrunk-new-melbourne-location-mel2 https://www.datacenterdynamics.com/en/news/airtrunk-acquires-site-in-melbourne-australia-for-354mw-data-center/ https://www.theage.com.au/national/victoria/1b-data-centre-given-planning-tick-in-just-75-days-as-state-gets-cosy-with-big-tech-20260219-p5o3sl.html https://datacentremoratorium.net/index.php/Resources:AirTrunk_MEL2 https://www.planning.vic.gov.au/planning-approvals/ministerial-permits-register/ministerial-permits/975c57aa-6b34-f111-88b4-7c1e5262e513 https://airtrunk.com/location/mel2-melbourne/ https://w.media/airtrunk-to-add-345-mw-facility-in-aud-5bn-melbourne-investment/ | AJ16: 開啟地圖 | AK16: VIC-B、VIC-A
A17: NSW-007 | B17: 新南威爾斯州 | C17: Goodman SYD01 — Lanceley Place Data Centre, Artarmon（SSD-66777221） | D17: Goodman（Goodman Property Services (Aust) Pty Ltd） | E17: Goodman Property Services (Aust) Pty Ltd（申請人） | F17: 2-8 Lanceley Place and 14 Campbell Street, Artarmon NSW 2064 | G17: Artarmon | H17: 2064 | I17: Willoughby City | J17: -33.81844 | K17: 151.19004 | L17: 來源提供 | M17: 80 | N17: 變電容量（MVA） | O17: 12.2 | P17: 核准時為「80MVA」（Portal 與 Mod 2 報告皆如此稱）；評估報告表 1 把同一數字寫成「IT power consumption 80 MW」。Mod 2（2026-04-14 核准）將饋線容量提高到 90 MVA、發電機由 30×2.8 MW 增為 42×2.82 MW。CIV A$845,852,021、施工 669 人、營運 30 人。 | Q17: 施工中 | R17: 主清單 | T17: 2026-08-11 | U17: Goodman「A10 Notice of Commencement of Construction Works」（2026-05-27 日期，portal 上傳 2025-05-29）：預定 2025-07-17 開工；CEMP Rev 3 與核准函 2025-08-27；CEMP Rev 7 / CTMP v4 / ESCP v1 核准 2026-05-14；Mod 1（2025-12-11）、Mod 2（2026-04-14）、Mod 3（2026-08-11）皆已核准；外牆覆層通知 2026-04-01；夜間施工申請 2026-04-30 核准。 | V17: 2025-07-17（預定日，Goodman 通知函） | W17: 評估報告：施工約 24 個月（→ 約 2027 年中）。Goodman SYD01 頁面（先前 的搜尋摘要，未重新開啟）：第一期 12.2 MW 排定 2028 Q2。 | X17: 2028 年以後 | Y17: DPHI SSD Assessment Report（2025-04-11）；Goodman（透過 先前） | Z17: 大概可租 | AA17: Goodman 開發並出租給超大規模客戶；政府文件未揭露租戶。第一期僅 12.2 MW，且排程已因電力移到 2028。 | AB17: 未揭露 | AC17: SSD-66777221（核准 2025-04-11）；Mod 1/2/3 | AD17: 高 | AE17: 營運商（Goodman 官網摘要）稱首期 12.2 MW 於 2028-Q2；NSW 評估報告估施工約 24 個月（自 2025-05 開工起算約 2027 年中）。以營運商說法為準。 地址備註：基地 14,024 m2（E4 工業區），位於 Gore Hill 科技園東側、皇家北岸醫院南約 200 m。 | AF17: https://www.planningportal.nsw.gov.au/major-projects/projects/lanceley-place-data-centre-artarmon https://majorprojects.planningportal.nsw.gov.au/prweb/PRRestService/mp/01/getContent?AttachRef=SSD-66777221%2120250411T063539.397+GMT https://majorprojects.planningportal.nsw.gov.au/prweb/PRRestService/mp/01/getContent?AttachRef=SSD-66777221-PA-5%2120250529T050113.400+GMT https://majorprojects.planningportal.nsw.gov.au/prweb/PRRestService/mp/01/getContent?AttachRef=SSD-66777221-MOD-2%2120260414T055621.028+GMT | AH17: https://baxtel.com/data-center/goodman-artarmon | AI17: https://www.planningportal.nsw.gov.au/major-projects/projects/lanceley-place-data-centre-artarmon https://majorprojects.planningportal.nsw.gov.au/prweb/PRRestService/mp/01/getContent?AttachRef=SSD-66777221%2120250411T063539.397+GMT https://majorprojects.planningportal.nsw.gov.au/prweb/PRRestService/mp/01/getContent?AttachRef=SSD-66777221-PA-5%2120250529T050113.400+GMT https://majorprojects.planningportal.nsw.gov.au/prweb/PRRestService/mp/01/getContent?AttachRef=SSD-66777221-MOD-2%2120260414T055621.028+GMT | AJ17: 開啟地圖 | AK17: NSW-B、NSW-A
A18: NSW-008 | B18: 新南威爾斯州 | C18: DCI Data Centers Eastern Creek Expansion（SYD02；SSD-21342738） | D18: DCI Data Centers（申請人 NineZero DC Sub TC I Pty Ltd trading as DCI Data Centers） | E18: NineZero DC Sub TC I Pty Ltd（DCI；印尼資本） | F18: 90 Peter Brock Drive, Eastern Creek NSW 2766 | G18: Eastern Creek | H18: 2766 | I18: Blacktown | J18: -33.80496 | K18: 150.88607 | L18: 來源提供 | M18: 63 | N18: 耗電量 | P18: 原核准（2023-09-01）32 MW、GFA 13,210 m2、高 35.7 m、27×2.65 MW 發電機。Mod 2（2026-08-12 核准）以更高機架密度把總用電由 32 MW 提高到 63 MW，並放大變電站、取消四層辦公樓。先前 所稱「SYD02 = 64 MW」與此吻合；SYD01 現有約 11 MW、最終 65 MW（先前資料）。 | Q18: 施工中 | R18: 主清單 | T18: 2026-08-12 | U18: Notice of Commencement（CC1）2025-06-19、CEMP（CC1）2025-06；Stage 2 開工通知 2025-10-10（CC2 2025-10-03）；CC3 通知 2026-05-20；CEMP Rev 04 核准函 2026-07-21。但 Mod 2 評估報告（2026-08）寫明：「已大致完成現場拆除，準備開始核准開發的施工」——故主體施工在 2026-08 尚在啟動期。 | V18: 拆除/早期工程 2025-06 起；主體工程 2026 中（Linesight，lead 資料） | W18: 評估報告：施工 24 個月 + 試運轉 6 個月；四階段（資料儲存棟與變電站→內裝→辦公棟→人行橋）。Linesight：2028 初完工（先前資料）。 | X18: 2028 年以後 | Y18: DPHI SSD Assessment Report（2023-09-01）；Linesight（透過 先前） | Z18: 可租 | AA18: DCI 為託管/批發營運商，向外出租；是 2028 前可談的西雪梨中型容量（約 63 MW 新增）。租戶未揭露。 | AB18: 未揭露 | AC18: SSD-21342738（核准 2023-09-01）；Mod 1（2025-09-18）、Mod 2（2026-08-12） | AD18: 高 | AE18: 先前資料「SYD02 = 64 MW、5 層、30,000 m2（Linesight）」與 DPHI：原 32 MW/GFA 13,210 m2，Mod 2 後 63 MW；差異為舊版媒體數字；更正 先前資料：最早的開工通知為 2025-06-19（非 2025-10-03）；SYD02 由 32 MW 提高到 63 MW（Mod 2，2026-08-05）。Portal 把本案歸類為『Warehouse or distribution centres』，不在 Data Storage 篩選清單。核准報告把既有場址稱 SYD01／SYD03 不一，建議以 SYD01（既有）、SYD02（本擴建）理解；規模：2022 新聞 36 MW 對 Linesight 現行 64 MW（曾 51 MW）；Baxtel 稱 Huntingwood 對政府資料 Eastern Creek 地址備註：Lot 34 DP 1131779、Lots 32/33 DP 1140168、Lot 25 DP 1122038；基地約 4.1 公頃，Raceway Precinct，鄰 Prospect Nature Reserve；現有 SYD01（原 Woolworths，Part 3A MP08_0108）。補足 先前 缺漏的街道地址。 | AF18: https://www.planningportal.nsw.gov.au/major-projects/projects/eastern-creek-data-centre-expansion-project https://majorprojects.planningportal.nsw.gov.au/prweb/PRRestService/mp/01/getContent?AttachRef=SSD-21342738%2120230901T061348.447+GMT https://majorprojects.planningportal.nsw.gov.au/prweb/PRRestService/mp/01/getContent?AttachRef=SSD-21342738-MOD-2%2120260812T003248.610+GMT https://www.planningportal.nsw.gov.au/major-projects/projects/eastern-creek-data-centre-mod-2-power-consumption-increase | AG18: https://www.linesight.com/projects/supporting-delivery-of-dcis-64mw-syd02-hyperscale-data-centre-in-sydney/ | AH18: https://baxtel.com/data-center/dci-syd02 https://cfotech.com.au/story/dci-data-centers-to-build-400m-facility-in-sydney | AI18: https://www.planningportal.nsw.gov.au/major-projects/projects/eastern-creek-data-centre-expansion-project https://majorprojects.planningportal.nsw.gov.au/prweb/PRRestService/mp/01/getContent?AttachRef=SSD-21342738%2120230901T061348.447+GMT https://majorprojects.planningportal.nsw.gov.au/prweb/PRRestService/mp/01/getContent?AttachRef=SSD-21342738-MOD-2%2120260812T003248.610+GMT https://www.planningportal.nsw.gov.au/major-projects/projects/eastern-creek-data-centre-mod-2-power-consumption-increase https://www.linesight.com/projects/supporting-delivery-of-dcis-64mw-syd02-hyperscale-data-centre-in-sydney/ | AJ18: 開啟地圖 | AK18: NSW-B、NSW-C、NSW-A
A19: VIC-008 | B19: 維多利亞州 | C19: DoverDC SM1A（South Morang；DFP 許可 PA2402997） | D19: DoverDC（Dover1 SM1A；許可持有人 PVAC Development Pty Ltd c/- Planning & Property Partners）；營運／招租模式未公布 | E19: PVAC Development Pty Ltd（DoverDC 體系）；DCD 稱一家 ASX 上市房地產投資集團持有兩案股權（未具名） | F19: 525 and 535 McDonalds Road and 765 Plenty Road, South Morang VIC 3752 | G19: South Morang | H19: 3752 | I19: City of Whittlesea | J19: -37.650911 | K19: 145.08236 | L19: 來源提供 | M19: 120 | N19: 口徑不明 | P19: DoverDC 官網（經 DCD 2026-08-26、W.Media）：三層、120 MW；DTP 官員報告：四層資料中心（含地下室燃料與水槽）GFA 28,465 m²＋兩層辦公 1,480 m²，高約 21–22.3 m，現場最多 285 人。2025-10-30 修訂（PA2402997-2）擴大建築面積並增加資料儲存容量。 | Q19: 已核准、尚未動工 | R19: 主清單 | T19: 2026-08-26 | U19: DFP PA2402997：2024-06-20 受理、2024-09-12 核發；PA2402997-1（2025-06-02，原生植被許可）與 -2（2025-10-30，增加建築面積與資料容量）。DCD／W.Media（2026-08）：預計 2026 年底或 2027 年初動工。Whittlesea 議會與居民（4,600+ 連署）反對。尚未動工。 | V19: 預計 2026 年底至 2027 年初（DoverDC，經 DCD） | W19: 2028–2029（首期；DoverDC，經 DCD 2026-08-26） | X19: 2028 年以後 | Y19: DCD 2026-08-26 引述 DoverDC；W.Media 2026-08 | Z19: 大概可租 | AA19: DoverDC 為開發商，W.Media 描述為超大規模園區；未公布租戶與出租模式。 | AB19: 未公布 | AC19: DFP PA2402997（permit 2024-09-12；-1 2025-06-02；-2 2025-10-30） | AD19: 高 | AE19: 層數：DCD（引官網）三層 vs DTP 官員報告四層（2025-10 另有擴大面積的修訂）；realestatesource 2026-07-22 推測 Stockland 為幕後，與許可申請人 PVAC／DoverDC 不符，視為錯誤；地方反對：維州議會請願已逾 4,600 簽名（由綠黨議員發起），綠黨提出暫停新資料中心的法案已在議會被否決（DCD 2026-08-26）。DatacenterMap 對本案郵遞區號寫成 3082，South Morang 應為 3752。許可資料由 先前 提供，我方未能自行開啟登記冊；55 MW（PVAC 原核准，搜尋摘要）vs 120 MW（Dover 2026-08）。PVAC 與 Dover 的關係（購入/合作）本次未取得一手說明 地址備註：三宗地（Lot 1 PS 712881T、Lot 1 TP 840734D、PC 367571U）；計畫單元 6.21 ha，DoverDC 稱建物約占 1 ha／3.5 ha 地塊；鄰 South Morang Terminal Station。 | AF19: https://www.planning.vic.gov.au/planning-approvals/ministerial-permits-register/ministerial-permits/1b31ed89-8d2e-ef11-840a-000d3acb3ea1 https://sftpbspomppprod01.blob.core.windows.net/applicationfiles/1b31ed89-8d2e-ef11-840a-000d3acb3ea1_PA2402997-525%20MCDONALDS%20ROAD%20SOUTH%20MORANG%20-%20Officer%20Report%20-%20FINAL.pdf https://www.planning.vic.gov.au/planning-approvals/ministerial-permits-register https://planning.vic.gov.au/planning-approvals/ministerial-permits-register/ministerial-permits/1b31ed89-8d2e-ef11-840a-000d3acb3ea1 | AH19: https://www.datacenterdynamics.com/en/news/application-filed-for-200mw-data-center-in-melbourne-australia/ https://w.media/whittlesea-seeks-greater-oversight-as-dover-plans-200mw-victorian-facility/ https://www.realestatesource.com.au/green-light-for-data-centre-half-the-size-of-the-rialto/ https://www.datacentermap.com/australia/melbourne/dover-sm1a/ https://datacentremoratorium.net/index.php/Resources:Dover_SM1A | AI19: https://www.planning.vic.gov.au/planning-approvals/ministerial-permits-register/ministerial-permits/1b31ed89-8d2e-ef11-840a-000d3acb3ea1 https://sftpbspomppprod01.blob.core.windows.net/applicationfiles/1b31ed89-8d2e-ef11-840a-000d3acb3ea1_PA2402997-525%20MCDONALDS%20ROAD%20SOUTH%20MORANG%20-%20Officer%20Report%20-%20FINAL.pdf https://www.datacenterdynamics.com/en/news/application-filed-for-200mw-data-center-in-melbourne-australia/ https://w.media/whittlesea-seeks-greater-oversight-as-dover-plans-200mw-victorian-facility/ https://www.realestatesource.com.au/green-light-for-data-centre-half-the-size-of-the-rialto/ https://datacentremoratorium.net/index.php/Resources:Dover_SM1A https://www.datacentermap.com/australia/melbourne/dover-sm1a/ https://nominatim.openstreetmap.org/search?q=765+Plenty+Road+South+Morang+VIC https://planning.vic.gov.au/planning-approvals/ministerial-permits-register/ministerial-permits/1b31ed89-8d2e-ef11-840a-000d3acb3ea1 | AJ19: 開啟地圖 | AK19: VIC-B、VIC-C、VIC-A
A20: NSW-009 | B20: 新南威爾斯州 | C20: Starwood / Doma / Telstra InfraCo — Minchinbury Data Centre | D20: Starwood Capital Group 與 Doma Infrastructure Group（開發、建設、營運） | E20: Telstra InfraCo 提供土地與連網；Starwood（受控關係企業）與 Doma 負責融資、開發、建設與管理 | F20: Minchinbury, Western Sydney NSW 2770（街道地址未公開） | G20: Minchinbury | H20: 2770 | I20: Blacktown | J20: -33.786673 | K20: 150.82722 | L20: 郊區級（近似） | M20: 62 | N20: IT 負載 | P20: 聯合新聞稿：62 MW IT 負載、90 MVA 電力包絡；Tier III+；支援液冷與 AI 級機櫃密度；可選 core & shell、powered shell 或 build-to-suit。 | Q20: 已核准、尚未動工 | R20: 主清單 | T20: 2025-11-12 | U20: 無硬證據。新聞稿（AAP/Cision 2025-11-12）稱 2026 年初開工、2028-Q1 初可交付；截至 2026-10-03 我找不到任何開工通知或承包商公告。Baxtel（聚合站）標為 Under Construction、2028，不能單獨採信。 | V20: 計畫 2026 年初（新聞稿）；未證實 | W20: 2028-Q1 初（Ready for Service） | X20: 2028 年以後 | Y20: Starwood / Doma / Telstra InfraCo 聯合新聞稿（AAP 發布，2025-11-12；Mingtiandi 2025-11-15 報導） | Z20: 可租 | AA20: 明確針對資料中心營運商、超大規模業者、AI 平台與 GPU 運算業者提供 core & shell、powered shell、build-to-suit，屬租戶導向，與台灣客戶最相容。 | AB20: 無 | AC20: 未公布（新聞稿稱已取得 DA） | AD20: 中 | AE20: 狀態：新聞稿只說將於 2026 年初開工，Baxtel 稱已在建；地址未公開；42 Sargents Road 的 2020 年 DA 是否相關未證實。 地址備註：未能解決街道地址。新聞稿僅稱位於 Minchinbury、緊鄰 Eastern Creek 資料中心群，土地來自 Telstra InfraCo，並稱 Development Approval 已取得，但未給地址或 DA 編號。我已查：NSW Planning Portal 主要專案清單（50 筆 Data Storage 另加其他類型掃描）、Planning Panels 登錄（Blacktown 335 筆）、NSW ePlanning DA 資料庫（成本 A$10m 以上、2021-06 起），皆無對應項目。唯一相近：Sydney Central City Planning Panel 於 2020-02-28 核准 DA SPP-18-01554（PPS-2019CCI002），地點 42 Sargents Road, Minchinbury，兩層資料中心，CIV A$86.8m，當時土地所有者 Aldi Foods Pty Ltd、申請人 Urbis；是否為同一場址未證實，且 CIV 遠低於 62 MW 規模，可能是另一方案，僅供線索。 | AF20: https://www.planningportal.nsw.gov.au/planning-panel/data-centre | AG20: https://www.aap.com.au/aapreleases/cision20251112ae20247 | AH20: https://www.mingtiandi.com/real-estate/data-centres/starwood-teams-with-doma-telstra-to-develop-62mw-sydney-data-centre/ https://www.datacenterdynamics.com/en/news/starwood-doma-and-telstra-plan-62mw-data-center-in-sydney/ https://baxtel.com/data-center/starwood-doma-minchinbury | AI20: https://www.aap.com.au/aapreleases/cision20251112ae20247 https://www.mingtiandi.com/real-estate/data-centres/starwood-teams-with-doma-telstra-to-develop-62mw-sydney-data-centre/ https://www.planningportal.nsw.gov.au/planning-panel/data-centre https://baxtel.com/data-center/starwood-doma-minchinbury | AJ20: 開啟地圖 | AK20: NSW-A
A21: NSW-010 | B21: 新南威爾斯州 | C21: Stockland / EdgeConneX SYD1（MPark）— 1-5 Khartoum Road Data Centre（Talavera Road DC；SSD-63235720） | D21: Stockland–EdgeConneX 50:50 合資（EdgeConneX 營運） | E21: Stockland Development Pty Ltd（SSD 申請人） | F21: 1-5 Khartoum Road, Macquarie Park NSW 2113 | G21: Macquarie Park | H21: 2113 | I21: City of Ryde | J21: -33.77923 | K21: 151.1249 | L21: 來源提供 | M21: 51.4 | N21: IT 負載 | P21: DPHI 評估報告（2026 年）：最大電力 76.4 MW（IT load 51.4 MW）；24 個 data halls 在六層（Portal 稱五層）；GFA 19,434 m2；高 45 m；28×3 MW 發電機；EDC A$718,259,656；施工 250 人、營運 50 人。Portal 標題的「35 MW、五層」是 SEARs 階段的舊描述。 | Q21: 已核准、尚未動工 | R21: 主清單 | T21: 2026-06-11 | U21: 核准 2026-03-11（評估報告 2026-06-11 上傳）；Portal 無後審文件。W.Media（2026-03-11）：「施工時間尚未確認」；Stockland CEO（2026-03）稱真正花錢的建造「還有一段時間」。 | V21: 未定 | W21: 評估報告：施工 33 個月（拆除 3 + 土方 3 + 施工與試運轉 27 個月）。Baxtel（聚合站）寫 2029。 | X21: 2028 年以後 | Y21: DPHI SSD Assessment Report；Baxtel（僅線索） | Z21: 大概可租 | AA21: 合資明言目標客戶為超大規模雲端與 AI；尚無租戶。風險：Baxtel 稱鄰近 MPark Stage 1 租給 AWS，且 Stockland 的雪梨據點可能優先服務 AWS（見 Davis Road 更正）。 | AB21: 未揭露 | AC21: SSD-63235720（核准 2026-03-11）；Council concept DA LDA2022/0176（已退回議會） | AD21: 高 | AE21: 先前資料寫 35 MW、五層、推測為 EdgeConneX MPark Stage 2；核准文件為 76.4 MW（IT 51.4 MW）、24 data halls，更正。申請人確為 Stockland，與 EdgeConneX 的關聯依 Baxtel（聚合站） 地址備註：基地 10,015 m2（原多層停車場），臨 Talavera Road 與 Murrell Street；Stockland MPark Stage 2；南側緊鄰同申請人的 Building H。土地原屬 Johnson & Johnson（Urban Developer）。 | AF21: https://www.planningportal.nsw.gov.au/major-projects/projects/1-5-khartoum-road-data-centre https://majorprojects.planningportal.nsw.gov.au/prweb/PRRestService/mp/01/getContent?AttachRef=SSD-63235720%2120260611T061649.742+GMT https://www.planningportal.nsw.gov.au/planning-panel/1-5-khartoum-road-concept-da | AH21: https://w.media/?p=38408 https://theurbandeveloper.com/articles/stockland-data-centre-macquarie-park-mpark https://baxtel.com/data-center/edgeconnex-syd1-mpark https://w.media/stockland-finalises-edgeconnex-data-centre-jv-as-ceo-plots-more-investment/ | AI21: https://www.planningportal.nsw.gov.au/major-projects/projects/1-5-khartoum-road-data-centre https://majorprojects.planningportal.nsw.gov.au/prweb/PRRestService/mp/01/getContent?AttachRef=SSD-63235720%2120260611T061649.742+GMT https://w.media/?p=38408 https://theurbandeveloper.com/articles/stockland-data-centre-macquarie-park-mpark https://baxtel.com/data-center/edgeconnex-syd1-mpark https://w.media/stockland-finalises-edgeconnex-data-centre-jv-as-ceo-plots-more-investment/ | AJ21: 開啟地圖 | AK21: NSW-B、NSW-A
A22: NSW-011 | B22: 新南威爾斯州 | C22: DigiCo SYD1 Data Centre Expansion, Ultimo（SSD-69637456） | D22: DigiCo（DigiCo REIT / HDI SYD1 Property Holdings Limited） | E22: HDI SYD1 Property Holdings Limited（申請人） | F22: 390-422 Harris Street and 273 Pyrmont Street, Ultimo NSW 2007 | G22: Ultimo | H22: 2007 | I22: City of Sydney | J22: -33.875 | K22: 151.197 | L22: 來源提供 | M22: 47.5 | N22: 耗電量 | O22: 20 | P22: 本 SSD 為增量：總用電由原有提高 47.5 MW 至 120 MW（IT load 88 MW）；加蓋兩層、高度增至 54.4 m、GFA 41,785 m2。EDC A$605.6m；施工 80 人、營運 45 人。DigiCo FY26（先前資料）：首批 20 MW 升級已完成（15 MW 至 2026-05），再有 LOI 52 MW，至 FY28 底 88 MW；未揭露可租/已租比例。 | Q22: 已核准、尚未動工 | R22: 主清單 | T22: 2026-09-08 | U22: NSW 規劃入口 2026-09-08 上傳「Condition A9a - Notice to Commence」，通知預定 2026-10-07 開工；截至 2026-10-03 尚未動工。先前已完成的 20 MW 屬較早階段。 | V22: 2026-10-07（預定） | W22: 評估報告：施工期 21 個月（含 6 個月招標、3 個月進場、委任調試 7 個月）→ 約 2028-07；DigiCo：88 MW 於 FY28 底（2028-06）。 | X22: 2028 年以後 | Y22: DPHI SSD Assessment Report（2025-12-23）；DigiCo FY26 業績（透過 先前） | Z22: 大概可租 | AA22: DigiCo 為上市的託管營運商，新增容量對外出租；但 LOI 已覆蓋 52 MW，且這是現有營運館的擴建，需向 DigiCo 確認剩餘未簽約容量。 | AB22: 未揭露（LOI 52 MW，對象未公布） | AC22: SSD-69637456（核准 2025-12-23）；Mod 1 審查中（Prepare Mod Report） | AD22: 高 | AE22: 先前 以「Notice to Commence 已上傳」視為施工證據；原文實為「預定 2026-10-07 開工」的事前通知，故非已開工。W.Media（2026-05-06）：首 15 MW 已完成、餘 5 MW 2026 年中、再 10 MW 2027；無重大衝突；入口網站座標僅三位小數。 地址備註：評估報告寫「390-422 Harris Street」，Portal 地址欄寫「392-422 Harris Street」；現有 DigiCo SYD1（前 Global Switch Sydney），基地 1.1 公頃，位於 Darling Harbour 區。 | AF22: https://www.planningportal.nsw.gov.au/major-projects/projects/digico-syd1-data-centre-expansion https://majorprojects.planningportal.nsw.gov.au/prweb/PRRestService/mp/01/getContent?AttachRef=SSD-69637456%2120251223T231353.781+GMT https://majorprojects.planningportal.nsw.gov.au/prweb/PRRestService/mp/01/getContent?AttachRef=SSD-69637456-PA-4%2120260908T051808.581+GMT https://www.planningportal.nsw.gov.au/major-projects/projects/digico-syd1-dc-mod-1-minor-design-refinements | AH22: https://w.media/digico-to-sell-us-assets-as-it-pivots-capital-to-sydney-growth/ https://baxtel.com/data-center/digico-sydney-syd1-west | AI22: https://www.planningportal.nsw.gov.au/major-projects/projects/digico-syd1-data-centre-expansion https://majorprojects.planningportal.nsw.gov.au/prweb/PRRestService/mp/01/getContent?AttachRef=SSD-69637456%2120251223T231353.781+GMT https://majorprojects.planningportal.nsw.gov.au/prweb/PRRestService/mp/01/getContent?AttachRef=SSD-69637456-PA-4%2120260908T051808.581+GMT https://w.media/digico-to-sell-us-assets-as-it-pivots-capital-to-sydney-growth/ | AJ22: 開啟地圖 | AK22: NSW-B、NSW-A
A23: SA-001 | B23: 南澳州 | C23: DigiCo ADL1（Edinburgh Parks）棕地擴建 15 MW — 即 DigiCo FY26 所稱的 Adelaide brownfield project | D23: DigiCo Infrastructure REIT（ASX: DGT）；前身 iseek / YourDC | E23: DigiCo Infrastructure REIT（HMC Capital 管理；2024-12-17 以約 A$400m 完成收購 iseek） | F23: 23-27 Woomera Avenue, Edinburgh SA 5111 | G23: Edinburgh | H23: 5111 | I23: City of Salisbury | J23: -34.740409 | K23: 138.64402 | L23: 來源提供 | M23: 15 | N23: IT 負載 | P23: 15 MW 是新增 IT 容量，不是場址總量。證據鏈：2024-11-11 DigiCo Platform Update 列 ADL1 擴建 8 MW；2025-08-18 FY25 簡報仍為 additional 8MW；2026-02-20 HY26 簡報上調為 15MW（目標 10-12% yield on cost）；2026-08-21 FY26 簡報字面寫 additional 15MW of IT Capacity (up from 8MW)，其澳洲計費容量橋接圖為 41 + 52（SYD1 LOI）+ 15（ADL1）= 108 MW，可證 15 MW 為增量。ADL1 現有裝機容量未揭露；iseek 全集團（7 座，QLD/SA/NSW）在 2024-11 為 installed IT 6 MW、contracted 3 MW（52%），所以 ADL1 現有可租餘量不大。設計等級：既有 Tier III、擴建 Tier IV。 | Q23: 已營運（有餘裕／擴建） | R23: 觀察名單 (出租性待確認) | S23: 新增 15 MW IT 尚待基石客戶簽約，沒有核准或動工證據；目標 FY28 底前開始計費。 | T23: 2026-08-21 | U23: 尚無動工證據，status 為最接近的分類（實際是已公告、待基石客戶簽約的擴建）。時間線：2024-11-11 Platform Update 列為 Design planning underway；2026-02-20 HY26 簡報稱 Commencements of ADL1 and BNE3 developments subject to cornerstone customer and capital partnering；2026-08-21 FY26 簡報稱專案處於 advanced customer discussions，簡報同頁預估 FY27-FY28 資本支出約 A$1.2bn（橋接圖涵蓋 SYD1 新增 52 MW 與 ADL1 15 MW，未單獨列出 ADL1 金額）。FY26 財報附註：2026-06-30 已簽約資本支出 A$121.1m（上年同期 A$5.7m），包含 SYD1 與 iseek 資產的工程，未指明是否含 ADL1。未找到 DA、建築許可或開工公告（PlanSA 被 Cloudflare 擋下，無法查詢）。 | V23: 未開工（至 2026-08-21 仍待基石客戶與資本夥伴）；DigiCo 規劃 FY27-FY28（2026-07 至 2028-06）分階段交付 | W23: 2028-06（FY28 年底前上線並計費；分階段，未公布各期 MW） | X23: 2028 年以後 | Y23: 營運商：DigiCo FY26 Results Presentation（2026-08-21；橋接圖標註 Targeted to be online and billing by the end of FY28，依圖面位置推定涵蓋 SYD1 新增與 ADL1）；媒體：Tech Partner（2026-08，稱 ADL1 15MW 擴建 delivered in phases across FY27 and FY28） | Z23: 可租 | AA23: DigiCo（前 iseek / YourDC）經營第三方 colocation；HY26 簡報稱專案 to support Government, Hyperscale and Co-location workloads，空間可滿足 a wide range of densities and security requirements。DigiCo 明示專案取決於 cornerstone customer，對需要 5 MW 以上的台灣租戶是可直接洽談的切入點，但 advanced customer discussions 代表窗口可能很短。 | AB23: 擴建部分未揭露（正與基石客戶洽談）。ADL1/iseek 既有客戶涵蓋政府、hyperscale 與企業（iseek 全集團超過 500 家客戶，2024-11）；ADL1 原規劃 FY26 Q2 取得 HCF Certified Strategic（FY25 簡報），是否達成未查證。 | AD23: 中 | AE23: (1) 街號：OSM 23-27、DatacenterMap 23、Baxtel 27 Woomera。(2) 容量：Baxtel 與 RenewMap（DC1 Edinburgh Parks Data Centre）把 ADL1 列為 8 MW 營運中，但 DigiCo 文件顯示 8 MW 是 2024-11 至 2025-08 的擴建規模（現已上調為 15 MW），現有裝機未揭露，推測聚合網站誤植。(3) FY26 簡報字面 additional 15MW (up from 8MW) 容易被誤讀為場址總量，橋接圖 41+52+15=108 證明 15 MW 為增量。(4) 無核准或動工證據，與 status 欄位的 operating_with_spare 並不完全相符，請主管決定是否降級為 watch-list；(1) 門牌 23 與 27 Woomera Avenue 不一。(2) 8 MW 的意義不一：RenewMap 與 Baxtel 把 DC1 Edinburgh Parks / ADL1 列為 8 MW 營運中，SA-A 認為是把擴建規模誤植為現有容量；DatacenterMap 標題寫 15 MW。(3) 沒有任何規劃許可資料可證明擴建已核准。 地址備註：ADL1 位於 Edinburgh Parks 工業區（Adelaide 北部）。街號各源不同：OSM 建物標註 23-27 Woomera Avenue；DatacenterMap（僅搜尋摘要）23 Woomera Avenue | AF23: https://www.defencesa.com/industry/industry-directory/yourdc-pty-ltd | AG23: https://investorpa.com/announcement-pdf/20260821/330767.pdf https://www.hmccapital.com.au/investment-strategies/digital-infrastructure/digico-infrastructure-reit/financial-reports-presentations/dgt-fy26-results-presentation/ https://www.hmccapital.com.au/investment-strategies/digital-infrastructure/digico-infrastructure-reit/financial-reports-presentations/hy26-results-presentation/ https://www.hmccapital.com.au/investment-strategies/digital-infrastructure/digico-infrastructure-reit/financial-reports-presentations/dgt-fy25-results-presentation/ https://www.hmccapital.com.au/investment-strategies/digital-infrastructure/digico-infrastructure-reit/financial-reports-presentations/digico-platform-update/ https://www.hmccapital.com.au/investment-strategies/digital-infrastructure/digico-infrastructure-reit/financial-reports-presentations/dgt-appendix-4e-and-fy26-financial-report/ https://www.digi-co.com.au/location/adelaide-adl1/ https://announcements.asx.com.au/asxpdf/20260821/pdf/07313trvmvdpsb.pdf https://announcements.asx.com.au/asxpdf/20260821/pdf/07313ph24n944h.pdf | AH23: https://www.techpartner.news/news/digico-posts-positive-fy26-results-shakes-up-leadership-team-628362 https://www.fool.com.au/2026/08/21/digico-infrastructure-reit-posts-fy26-earnings-beat-outlines-expansion-plans/ https://w.media/hmcs-acquisition-of-iseek-to-seed-its-global-digico-platform-strategy/ https://baxtel.com/data-center/digico-adelaide-adl1 https://www.datacentermap.com/australia/adelaide/yourdc-edinburgh/specs https://baxtel.com/sites/digico-adelaide-adl1 https://www.datacentermap.com/australia/adelaide/yourdc-edinburgh/ https://www.datacenters.com/locations/australia/south-australia/adelaide | AI23: https://investorpa.com/announcement-pdf/20260821/330767.pdf https://www.hmccapital.com.au/investment-strategies/digital-infrastructure/digico-infrastructure-reit/financial-reports-presentations/ https://www.hmccapital.com.au/investment-strategies/digital-infrastructure/digico-infrastructure-reit/financial-reports-presentations/hy26-results-presentation/ https://www.hmccapital.com.au/investment-strategies/digital-infrastructure/digico-infrastructure-reit/financial-reports-presentations/dgt-fy25-results-presentation/ https://www.hmccapital.com.au/investment-strategies/digital-infrastructure/digico-infrastructure-reit/financial-reports-presentations/digico-platform-update/ https://www.hmccapital.com.au/investment-strategies/digital-infrastructure/digico-infrastructure-reit/financial-reports-presentations/dgt-appendix-4e-and-fy26-financial-report/ https://www.hmccapital.com.au/investment-strategies/digital-infrastructure/digico-infrastructure-reit/financial-reports-presentations/dgt-annual-report-2025/ https://announcements.asx.com.au/asxpdf/20260220/pdf/06wj5yyhn754y6.pdf https://www.techpartner.news/news/digico-posts-positive-fy26-results-shakes-up-leadership-team-628362 https://www.fool.com.au/2026/08/21/digico-infrastructure-reit-posts-fy26-earnings-beat-outlines-expansion-plans/ https://baxtel.com/data-center/digico-adelaide-adl1 https://baxtel.com/data-centers/digico-infrastructure-reit https://w.media/hmcs-acquisition-of-iseek-to-seed-its-global-digico-platform-strategy/ https://nominatim.openstreetmap.org/reverse?lat=-34.7404086&lon=138.6440232&format=json https://geo.abs.gov.au/arcgis/rest/services/ASGS2021/LGA/MapServer/0/query https://asx.api.markitdigital.com/asx-research/1.0/companies/dgt/announcements https://itbrief.com.au/story/digico-posts-strong-fy25-results-with-aud-99m-ebitda-gains-key-certification https://baxtel.com/news/digico-infrastructure-reit-signs-14mw-of-data-center-deals https://w.media/iseek-acquires-yourdc-expands-australian-footprint/ https://announcements.asx.com.au/asxpdf/20260821/pdf/07313trvmvdpsb.pdf https://announcements.asx.com.au/asxpdf/20260821/pdf/07313ph24n944h.pdf https://announcements.asx.com.au/asxpdf/20260821/pdf/073136jvdkgcx0.pdf https://baxtel.com/sites/digico-adelaide-adl1 https://baxtel.com/data-center/adelaide https://www.datacentermap.com/australia/adelaide/yourdc-edinburgh/ https://www.datacenters.com/locations/australia/south-australia/adelaide | AJ23: 開啟地圖 | AK23: SA-A、SA-B
A24: NT-001 | B24: 北領地 | C24: Project Ares（Energy North，Murranji Station 離網 1 GW 超大規模 AI 資料中心園區） | D24: Energy North Pty Ltd（總部新加坡） | E24: Energy North 由 Raggiana Global 持有（CEO／創辦人 Scott Criddle，前 Decmil CEO）；土地為 Murranji Station（約 447,500 ha 畜牧場，永久牧場租約；DCD 稱 2025-11 由 Viv Oldfield 以約 A$44m 購入）；同址另規劃 Project Sol（綠氫／綠氨，另行環評） | F24: Murranji Station（Elliott 西北約 52 公里），Elliott NT 0862；NT EPA 轉介表名義地址 18698A Stuart Highway, Daly Waters NT 0852 | G24: Elliott | H24: 0862 | I24: Barkly Region（轄區議會未核實） | J24: -17.561217 | K24: 133.55719 | L24: 街道級 | M24: 1000 | N24: IT 負載 | O24: 500 | P24: EPBC 2026/10560 轉介書：總 IT 容量 1 GW，分兩期，Phase 1 約 500 MW IT、Phase 2 補足餘量；配套太陽能約 3,000 MWp、BESS 約 16 GWh、燃氣約 1,038 MW（可轉氫），完全離網、Tier III。DCD（2026-07-01）：首期投資約 A$11.9bn（資金來源不明）；Energy North 稱長期可擴至 5 GW 以上。 | Q24: 已送件、審查中 | R24: 觀察名單 (出租性待確認) | S24: 離網燃氣、位置偏遠（達爾文以南約 683 公里）、尚無租戶與融資；2028 年前不應視為可租。 | T24: 2026-10-03 | U24: 尚未動工。提交證據：(1) EPBC 轉介 2026/10560（RenewEconomy 2026-07-01 稱 2026-06 提交；公眾意見期至 2026-07-13；EPBC 入口網站 2026-10-03 讀取時狀態為 Awaiting additional information）；(2) 轉介書載明同時依 NT《Environment Protection Act 2019》以『proponent-initiated EIS』提出，NT EPA 受理意見至 2026-08-20，NT EPA 網站已有『Notice of Decision EP2026/052 Project Ares』與 draft SOR 的 PDF（被 Cloudflare 擋住，未能開啟，決定內容不明）；(3) 已獲聯邦 Major Project Status（Energy North 說明這不是批准）。Energy North 稱 FEL-2／Pre-FEED 完成、邁向 FEED，FID 待最終批准。 | V24: 未開工（FID 未決；Baxtel 推測 2027 年中，聚合資料） | W24: 首期供電目標 2028 年中（Energy North FAQ，視批准與 FID）；專案頁稱 FID 後 12-18 個月；施工約 3 年分階段至全面完工 | X24: 2028 年以後 | Y24: Energy North 官網 FAQ／專案頁（營運商自述，未標日期）；Baxtel（聚合，低權重） | Z24: 大概可租 | AA24: Energy North 是開發商而非終端使用者；官網稱專案為滿足『global hyperscale customers』而設計，EPBC 轉介書的營運人力含『data centre tenant operations』，表示規劃由承租客戶進駐。目前沒有任何簽約客戶（RenewEconomy：客戶處於早期洽談），租賃模式（colocation／wholesale／build-to-suit）營運商文件未明說；第三方 ecosistemastartup 稱採 colocation，未被營運商文件證實。風險：距城市極遠（達爾文以南約 683 km）、離網且以燃氣為主要早期電源（燃氣供應的商業安排尚未敲定）、無公布融資、環評與聯邦資料中心再生能源政策未定、環保團體強烈反對。 | AB24: 無（未公開） | AC24: EPBC 2026/10560；NT EPA EP2026/052 | AD24: 高 | AE24: (1) 距離：DCD 與 Baxtel 稱 Elliott 西北約 50 km，RenewEconomy 稱約 52 km；(2) 燃氣容量：EPBC 約 1,038 MW，DCD 稱 900 MW 至 1.1 GW；(3) 時程：FAQ 稱首電 2028 年中，專案頁與 RenewEconomy 稱 FID 後 12-18 個月，Baxtel 稱 2027 年中動工、2028 年啟用、2031 年前擴建；(4) 面積：DCD 稱牧場 447,500 ha，EPBC 專案範圍 186,000 ha，擾動範圍 19,150 ha；(5) 職位：EPBC 稱營運人力 200-300 FTE（Phase 1）至 350-500 FTE（全規模），Climate Council 引述 200-500，皆為營運商自述；（1）轉介表摘要稱『單一整合建置、交付完整 1 GW IT』，但規格表又拆為 Phase 1 500 MW IT + Phase 2 500 MW IT；摘要另寫 'Phase 1 delivers 500 megawatts (MW) of firm power alongside the full 1 GW IT campus'，措辭不一致，故 first_phase_mw 取規格表的 500。（2）官網寫首次供電在 FID 後 12–18 個月，轉介報告寫 FID 2027-07-31 後約 11 個月（2028-06-28）首次供電。（3）官網寫 '5 GW+' 長期潛力，政府文件僅 1 GW 地址備註：專案區約 186,000 公頃，位於 Murranji Station 內，NT EPA 通知書稱在 Elliott 西北約 52 公里、Daly Waters 西南約 100 公里（達爾文以南約 683 公里）。沒有街道地址，也沒有可靠座標；地圖上的點釘在 Elliott 鎮，僅供方向參考，實際位置差約 50 公里。 | AF24: https://epbcpublicportal.environment.gov.au/all-referrals/project-referral-summary/?id=f4f8aae0-956b-f111-ab0b-000d3aca9bcb https://ntepa.nt.gov.au/__data/assets/pdf_file/0003/1622280/notice-of-decision-ep2026-052-project-ares.pdf https://ntepa.nt.gov.au/__data/assets/pdf_file/0019/1622107/project-ares-draft-sor.pdf https://ntepa.nt.gov.au/your-business/public-registers/environmental-impact-assessments-register/assessments-in-progress-register/project-ares https://ntepa.nt.gov.au/__data/assets/pdf_file/0014/1622102/referral-form.pdf https://ntepa.nt.gov.au/__data/assets/pdf_file/0015/1622103/referral-report.pdf https://ntepa.nt.gov.au/news/2026/public-comment-is-sought-on-new-referral-project-ares https://ntepa.nt.gov.au/your-business/public-registers/environmental-impact-assessments-register https://territorycoordinator.nt.gov.au/news-and-insights/beetaloo-digital-advances-plans-for-weddell-data-centre | AG24: https://energy-north.com/projects/project-ares/ https://energy-north.com/project-ares-your-questions-answered/ https://energy-north.com/ https://www.energynorth.com.au | AH24: https://www.datacenterdynamics.com/en/news/gigawatt-scale-behind-the-meter-data-center-campus-proposed-in-australias-northern-territories/ https://reneweconomy.com.au/plan-to-power-off-grid-data-centre-with-solar-gas-and-a-16-gigawatt-hour-battery-seek-federal-green-tick/ https://www.climatecouncil.org.au/resources/six-reasons-proposed-project-ares-data-centre-big-alarm-bells/ https://ntindependent.com.au/opinion-behind-the-meter-the-unanswered-questions-behind-the-barklys-ai-data-centre/ https://altenergy.com.au/newsandviews/show/168/rocky-path-ahead-for-data-centre-regulation https://www.energy-storage.news/energy-north-submits-1gw-off-grid-hyperscale-data-centre-with-16gwh-of-battery-storage-to-australias-epbc-act/ https://baxtel.com/data-center/energy-north-project-ares https://esdnews.com.au/northern-territory-commits-land-to-gas-backed-data-centre/ https://ntindependent.com.au/nt-government-backs-proposed-2gw-data-centre-at-weddell/ | AI24: https://epbcpublicportal.environment.gov.au/all-referrals/project-referral-summary/?id=f4f8aae0-956b-f111-ab0b-000d3aca9bcb https://energy-north.com/ https://energy-north.com/projects/project-ares/ https://energy-north.com/project-ares-your-questions-answered/ https://www.datacenterdynamics.com/en/news/gigawatt-scale-behind-the-meter-data-center-campus-proposed-in-australias-northern-territories/ https://reneweconomy.com.au/plan-to-power-off-grid-data-centre-with-solar-gas-and-a-16-gigawatt-hour-battery-seek-federal-green-tick/ https://www.climatecouncil.org.au/resources/six-reasons-proposed-project-ares-data-centre-big-alarm-bells/ https://ntindependent.com.au/opinion-behind-the-meter-the-unanswered-questions-behind-the-barklys-ai-data-centre/ https://altenergy.com.au/newsandviews/show/168/rocky-path-ahead-for-data-centre-regulation https://ecosistemastartup.com/?p=93254 https://baxtel.com/data-center/energy-north-project-ares https://nominatim.openstreetmap.org/search（OSM 地理編碼：Murranji、Elliott） https://ntepa.nt.gov.au/your-business/public-registers/environmental-impact-assessments-register/assessments-in-progress-register/project-ares https://ntepa.nt.gov.au/__data/assets/pdf_file/0003/1622280/notice-of-decision-ep2026-052-project-ares.pdf https://ntepa.nt.gov.au/__data/assets/pdf_file/0014/1622102/referral-form.pdf https://ntepa.nt.gov.au/__data/assets/pdf_file/0015/1622103/referral-report.pdf https://ntepa.nt.gov.au/news/2026/public-comment-is-sought-on-new-referral-project-ares https://ntepa.nt.gov.au/your-business/public-registers/environmental-impact-assessments-register https://territorycoordinator.nt.gov.au/news-and-insights/beetaloo-digital-advances-plans-for-weddell-data-centre https://www.energynorth.com.au https://esdnews.com.au/northern-territory-commits-land-to-gas-backed-data-centre/ https://ntindependent.com.au/nt-government-backs-proposed-2gw-data-centre-at-weddell/ | AJ24: 開啟地圖 | AK24: NT-B、NT-A
A25: SA-002 | B25: 南澳州 | C25: IREN Bundey Data Centre Campus（Bundey 資料中心園區，南澳 Mid North） | D25: IREN Limited（申請實體 TAS 1 Holdings Pty Ltd，ABN 23 652 889 579） | E25: IREN Limited（Nasdaq: IREN）100% 持有 TAS 1；土地由地主持有，TAS 1 持有購買選擇權（CT 5915/155）；ElectraNet 持有 Bundey 變電站（CT 6270/132）；EPBC 轉介書由顧問 JBS&G 代為提交 | F25: Lot 69 Bundey Church Road, Bundey SA 5320 | G25: Bundey | H25: 5320 | I25: Regional Council of Goyder | J25: -33.894037 | K25: 139.23304 | L25: 街道級 | M25: 800 | N25: 耗電量 | P25: EPBC 轉介書：800 MW 資料中心，三個資料大廳各最高 200 MW IT，三座一次變電站（132/33 kV）加一座 330/132 kV 大宗變電站。RenewEconomy（2026-08-24）換算為 800 MW 併網負載、約 550 MW IT。IREN 與 ElectraNet 的輸電連接協議含 4 個 330 kV 饋線出口，稱可支撐最高 800 MW 且不需電網升級（IREN 新聞稿 2026-06-03/04）。800 MW 是併網或總負載口徑，不是可出租 IT MW；各期 MW 未公布。 | Q25: 已送件、審查中 | R25: 觀察名單 (出租性待確認) | S25: 出租性待確認：IREN 在 EPBC 轉介書自述為 vertically integrated AI cloud provider，官網解決方案目前只列 AI Cloud（GPU 雲），未見對外批發或託管（colocation）招租說明；新聞稿稱服務全球與區域 AI 需求及南澳自身算力需求。因此對要租 5 MW 以上機房電力的客戶，較可能只能購買 GPU 雲容量而非租用機房，需直接向 IREN 確認是否提供批發大廳或專用容量。SA-A 將此案列為 excluded（captive）；我保留為 planned_filed 並標 uncertain，因為這是南澳唯一正式送件的 5 MW 以上案件，由主管裁決。 | T25: 2026-07-30 | U25: 尚無施工證據。已有的正式文件：(1) 2026-03 向 SA Department of State Development 提出 s131 Crown sponsorship 正式申請並補件，EPBC 轉介書稱 TAS 1 已取得 DSD 的 sponsorship，可走 Crown development 與 essential infrastructure 路徑（PDI Act s131）；(2) 2026-07-30 向聯邦提出 EPBC 轉介（表單 Application Number 03559，估計 2026-11-01 開工）；(3) 2026-06 與 ElectraNet 簽署輸電連接協議。Crown 開發申請（DA）本身尚未公開提出，法定公眾諮詢（由 DHUD 辦理）尚未開始；ABC 2026-06-19 也寫尚未提交 DA。IREN 稱 early works 與採購將與監管核准並行。 | V25: 預計 2026-11-01（EPBC 轉介書的估計開工日，待核准，未實際開工） | W25: 首期通電自 2028 起；整體施工約 6 至 8 年（分期並行） | X25: 2028 年以後 | Y25: IREN 新聞稿 2026-06-03/04（2028 起通電）；EPBC 轉介書 2026-07-30（施工 6-8 年） | Z25: 待確認 | AA25: IREN 在 EPBC 轉介書自述為 vertically integrated AI cloud provider，官網解決方案目前只列 AI Cloud（GPU 雲），未見對外批發或託管（colocation）招租說明；新聞稿稱服務全球與區域 AI 需求及南澳自身算力需求。因此對要租 5 MW 以上機房電力的客戶，較可能只能購買 GPU 雲容量而非租用機房，需直接向 IREN 確認是否提供批發大廳或專用容量。SA-A 將此案列為 excluded（captive）；我保留為 planned_filed 並標 uncertain，因為這是南澳唯一正式送件的 5 MW 以上案件，由主管裁決。 | AB25: 未公布。IREN 在美國德州場址已與 Microsoft 簽約（US$9.7bn GPU 雲合約，W.Media 報導），那不是 Bundey。 | AC25: EPBC 轉介（表單 Application Number 03559，commencement 2026-07-30；入口網站檔名為 00-2026-10605 Referral.pdf，故推測編號為 EPBC 2026/10605，尚未在入口網站頁面核實）；DSD s131 Crown sponsorship（2026-03 申請、已獲 sponsorship）；Crown DA 編號尚無 | AD25: 高 | AE25: (1) 申請狀態：ABC 2026-06-19 稱尚未提交 DA， 稱未見州級 s131 紀錄；EPBC 轉介書（政府入口網站文件）明載 s131 Crown sponsorship 申請已於 2026-03 提交且已取得 sponsorship，兩者指不同階段（Crown DA 未提、sponsorship 已獲）。(2) 容量口徑：EPBC 為三廳各最高 200 MW IT（合計可到 600 MW），RenewEconomy 為約 550 MW IT，800 MW 為併網負載。(3) 面積：IREN 官網寫 1,300 英畝（約 526 公頃），EPBC 園區主體 565.2 公頃、全範圍 610.4 公頃。(4) 距 Adelaide：各源 75 km、78 英里、125 km、126 km 不一。(5) 開發階段：IREN 官網標 Planned；Baxtel 曾標 Operational（SA-A 指出有誤）。 地址備註：EPBC 轉介書 2.2.1 的場址地址欄寫「Lot 69 Bundey Church Road Bundey」（Lot 號，非街號）。園區範圍 610.4 公頃：園區主體 565.2 公頃（三筆相連自由地，同一地契 CT 5915/155）加上約 2 km x 250 m、45.3 公頃的輸電線走廊通往 ElectraNet 的 Bundey 變電站（走廊另涉 CT 6300/200、CT 6300/199）。出入口：北側 Bundey Church Road 三處、西側 Sutherlands Road 兩處（均為未鋪面道路）；距 Robertstown 東北約 15 km、距 Adelaide 北北東約 126 km；最近主要道路 Goyder Highway 在北方約 11.5 km；SA Water 供水接點在 Pipeline Road 與 Bower Boundary Road 附近；分區為 Rural Intensive Enterprise Zone。郵遞區號 5320 取自 Wikipedia（引用 Location SA），未以 Australia Post 核對。Bundey 地區中心點約 -33.89, 139.30（Wikipedia），僅供參考，不是場址座標。 | AF25: https://epbcpublicportal.environment.gov.au/_entity/sharepointdocumentlocation/5c72ac54-e89c-f111-b8db-70a8a5564bc0/2ab10dab-d681-4911-b881-cc99413f07b6?file=00-2026-10605+Referral.pdf https://statedevelopment.sa.gov.au/downloads/data-centre-crown-sponsorship-form | AG25: https://iren.com/data-centers/bundey https://www.pv-magazine-australia.com/press-releases/iren-announces-first-australian-data-centre-campus-800-mw-in-south-australia/ https://iren.gcs-web.com/news-releases/news-release-details/iren-announces-first-australian-data-center-campus-800mw-south | AH25: https://reneweconomy.com.au/australias-biggest-data-centre-to-require-4-substations-2-grid-scale-power-lines-and-lots-of-diesel-backup/ https://w.media/iren-targets-bundey-transmission-hub-for-800mw-australian-data-centre-campus/ https://www.abc.net.au/news/2026-06-19/proposed-data-centre-in-south-australia-dividing-locals/106810776 https://www.geoffbrock.com.au/2026/08/iren-community-drop-in-sessions-bundey-data-centre/ https://www.abc.net.au/news/2026-06-23/sa-push-for-ai-data-centres-in-sa-in-new-strategy/106830536 https://www.afr.com/companies/financial-services/iren-plans-10-billion-south-australian-ai-data-centre-20260603-p603o9 | AI25: https://epbcpublicportal.environment.gov.au/_entity/sharepointdocumentlocation/5c72ac54-e89c-f111-b8db-70a8a5564bc0/2ab10dab-d681-4911-b881-cc99413f07b6?file=00-2026-10605+Referral.pdf https://statedevelopment.sa.gov.au/downloads/data-centre-crown-sponsorship-form https://iren.com/data-centers/bundey https://iren.com/ https://www.pv-magazine-australia.com/press-releases/iren-announces-first-australian-data-centre-campus-800-mw-in-south-australia/ https://reneweconomy.com.au/australias-biggest-data-centre-to-require-4-substations-2-grid-scale-power-lines-and-lots-of-diesel-backup/ https://w.media/iren-targets-bundey-transmission-hub-for-800mw-australian-data-centre-campus/ https://www.abc.net.au/news/2026-06-19/proposed-data-centre-in-south-australia-dividing-locals/106810776 https://www.geoffbrock.com.au/2026/08/iren-community-drop-in-sessions-bundey-data-centre/ https://www.abc.net.au/news/2026-06-23/sa-push-for-ai-data-centres-in-sa-in-new-strategy/106830536 https://en.wikipedia.org/wiki/Bundey,_South_Australia | AJ25: 開啟地圖 | AK25: SA-B
A26: VIC-009 | B26: 維多利亞州 | C26: DoverDC SM1B／SM2（South Morang，165 Williamsons Road；DFP 申請 PA2604586） | D26: DoverDC（申請人 Dover1 SM2 Pty Ltd） | E26: Dover1 SM2 Pty Ltd（Level 12, 468 St Kilda Road, Melbourne） | F26: 165 Williamsons Road, South Morang VIC 3752 | G26: South Morang | H26: 3752 | I26: City of Whittlesea | J26: -37.643497 | K26: 145.0813 | L26: 來源提供 | M26: 200 | N26: 口徑不明 | P26: DoverDC 官網（經 DCD、W.Media）：SM1B 為三層、200 MW 單棟，約 1.8 ha；兩案（SM1A＋SM1B）合計最多 320 MW。 | Q26: 已送件、審查中 | R26: 主清單 | T26: 2026-08-13 | U26: DFP PA2604586：2026-08-13 受理（頁面已讀，無決定）；Whittlesea 議會 2026-08-18 提出關切。 | V26: 未核准（W.Media：預計 2026 年底至 2027 年初動工） | W26: 2028 年底至 2029 年初（W.Media，兩案） | X26: 2028 年以後 | Y26: W.Media 2026-08 | Z26: 大概可租 | AA26: 同 。 | AB26: 未公布 | AC26: DFP PA2604586（待決） | AD26: 高 | AE26: 受理日 2026-08-13（DTP 頁）vs 8 月 14 日（DCD 報導）；收件日：先前 記為 2026-08-13，W.Media 記為 2026-08-14。命名：登記冊/申請人用 Dover1 SM2，Dover 官網與 DCD 用 SM1B。DatacenterMap 的郵遞區號誤植為 3752/3082 混用，South Morang 正確為 3752。Whittlesea 市議會 2026-08-18 會議表達對透明度與監管的疑慮（W.Media） 地址備註：毗鄰 South Morang Terminal Station 與 South Morang Substation，約 8.7 ha 地塊。 | AF26: https://www.planning.vic.gov.au/planning-approvals/ministerial-permits-register/ministerial-permits/4b779b5c-ef96-f111-8075-7ced8d33fb5a https://www.planning.vic.gov.au/planning-approvals/ministerial-permits-register | AH26: https://www.datacenterdynamics.com/en/news/application-filed-for-200mw-data-center-in-melbourne-australia/ https://w.media/whittlesea-seeks-greater-oversight-as-dover-plans-200mw-victorian-facility/ https://www.datacentermap.com/australia/melbourne/dover-sm1b/ | AI26: https://www.planning.vic.gov.au/planning-approvals/ministerial-permits-register/ministerial-permits/4b779b5c-ef96-f111-8075-7ced8d33fb5a https://www.datacenterdynamics.com/en/news/application-filed-for-200mw-data-center-in-melbourne-australia/ https://w.media/whittlesea-seeks-greater-oversight-as-dover-plans-200mw-victorian-facility/ https://datacentremoratorium.net/index.php/Resources:Dover_SM2 https://www.datacentermap.com/australia/melbourne/dover-sm1b/ https://nominatim.openstreetmap.org/search?q=165+Williamsons+Road+South+Morang+VIC | AJ26: 開啟地圖 | AK26: VIC-B、VIC-A、VIC-C
A27: WA-002 | B27: 西澳州 | C27: CDC Hazelmere Campus (proposed), Perth | D27: CDC Data Centres (CDC) | E27: CDC Data Centres（The West Australian 2026-09-18 稱 CDC 約自 2022 年起持有 Bushmead Road 土地） | F27: 178-196 Bushmead Road, Hazelmere WA 6055 | G27: Hazelmere | H27: 6055 | I27: City of Swan | J27: -31.901389 | K27: 115.99361 | L27: 街道級 | M27: 192 | N27: 口徑不明 | P27: The West Australian（Ryan Johnson，2026-09-18）：CDC 計畫在 Bushmead Road 興建兩棟各 96 MW、四層樓的資料中心，合計 192 MW，並稱比 GreenSquareDC 已撤案的 120 MW 方案多 60% 電力容量。CDC 官網與 2026-09 社區更新僅稱兩棟四層樓，未列 MW。COO 稱分階段興建，投資額暫無。口徑（IT 或電力）未說明。Perth is OK! 引用反對團體稱高度 38 m。 | Q27: 已送件、審查中 | R27: 主清單 | T27: 2026-10-01 | U27: 尚未施工。Perth is OK!（2026-10-01）：City of Swan CEO Stephen Cain 確認 CDC 的 DA 已提交，但目前暫停、待補充資料後才會公開徵詢意見。CDC 官網與 Hazelmere Community update September 2026（PDF，已讀）時間軸：2026 年提交 DA 並開始場地整備；2027 主體工程與 fit-out；2028 開始營運；2029 全面營運（dates may change）。WA DAP All Current Applications（截至 2026-09-29，已讀）尚無任何資料中心案，與 DA 在議會端暫停的說法相符，無法由政府登記冊獨立證實提交日期。 | V27: 尚未開始（CDC 計畫 2026 年底場地整備、2027 初主體工程） | W27: 2028 開始營運；2029 全面營運 | X27: 2028 年以後 | Y27: 營運商 CDC：Hazelmere Community update September 2026 及 cdc.com/locations/perth/hazelmere（一手，2026-10-03 讀取） | Z27: 大概可租 | AA27: 同 Maddington：CDC 主要服務政府與關鍵基礎設施客戶（COO，The West Australian 2026-09-18），對台灣民間租戶不一定開放。另有高度社區反對風險：前一案 GreenSquareDC 收到約 1,890 份公眾意見（約 1,829 份反對），2026-05 撤案；Trillion Trees Australia 已公開反對 CDC 案（原生植被、黑鳳頭鸚鵡棲地）。City of Swan 已於 2026-09-09 通過制定資料中心地方規劃政策動議。 | AB27: 無公開租戶。 | AC27: City of Swan 收件（編號未公布）；預期由 Metro Outer DAP 決定（GreenSquareDC 前案即走此途徑）。 | AD27: 中 | AE27: (1) 提交時間：CDC 官網與 2026-09 更新寫 2026 年將提交 DA；The West Australian（2026-09-18）稱兩週內提交；Perth is OK!（2026-10-01）稱已提交但暫停；Echo（2026-09-24）仍稱早期溝通階段。未見政府登記冊佐證。(2) 規模：2x96 MW 僅見於 The West Australian（付費牆，僅讀前段）；CDC 官網無 MW。CDC Perth 頁稱 Perth 完成後 over 200 megawatts，未釐清是否含 Hazelmere。(3) 高度：CDC 稱四層，反對團體稱 38 m；(1) 申請時點：CDC 網頁時程把『Submit development application』放在 2026 年（2026-09），並稱『will soon lodge』；DPLH 清單卻顯示 DAP/26/03103 已於 2026-04-07 收件；City of Swan CEO 稱已提交但暫停。可能是 2026-04 先登記、後續補件／CDC 對外措辭落後，或另有申請人，需向 DAP Secretariat／City of Swan 確認。(2) 容量：192 MW（The West Australian，經 WA-A）、200 MW（RenewMap）、CDC 無官方 MW，三者皆未經 WA-B 驗證。(3) 高度：CDC 稱四層，反對團體稱 38 m（Perth is OK!）。(4) DPLH 清單不顯示申請人，與 CDC 的對應為推定 地址備註：CDC Hazelmere 官網、Echo（2026-09-24）、Perth is OK!（2026-10-01）均載 178-196 Bushmead Road，位於 Hazelmere 工業區；距已撤案的 GreenSquareDC 場址（Stirling Crescent lots 14 and 15）約 2 km。地段編號未公布。另：The West Australian（SQM 專欄，2026-09-22）報導 CDC 以 A$15,326,350 購入 50 Hazelmere Circus, Hazelmere（辦公室加高桁架倉庫），並稱 CDC 在 Hazelmere、Wangara、Maddington 皆持有物業；該地用途未說明，是否與 Bushmead Road 案相鄰不明。 | AF27: https://www.planning.wa.gov.au/docs/default-source/daps-docs-other/current-applications.pdf https://www.planning.wa.gov.au/docs/default-source/daps-docs-website/current-applications.pdf?sfvrsn=ebbf7a78_310 https://www.planning.wa.gov.au/development-assessment-panels/current-development-assessment-panels-applications-and-information | AG27: https://cdc.com/locations/perth/hazelmere/ https://cdc.com/media/v2detpiy/cdc-hazelmere-community-update_sep-2026.pdf https://cdc.com/locations/perth/ https://www.cdc.com/locations/perth/hazelmere/ | AH27: https://perthisok.com/news/new-hazelmere-data-centre-plans-cdc/ https://thewest.com.au/business/cdc-courts-hazelmere-residents-with-192mw-data-centre-after-greensquares-11b-plan-collapsed-c-22889611 https://echonewspaper.com.au/news/community-engagement-begins-for-new-hazelmere-data-centre/ https://echonewspaper.com.au/news/swan-backs-data-centre-policy-push/ https://renewmap.com.au/resources/projects/wa/datacentre/ | AI27: https://cdc.com/locations/perth/hazelmere/ https://cdc.com/media/v2detpiy/cdc-hazelmere-community-update_sep-2026.pdf https://perthisok.com/news/new-hazelmere-data-centre-plans-cdc/ https://thewest.com.au/business/cdc-courts-hazelmere-residents-with-192mw-data-centre-after-greensquares-11b-plan-collapsed-c-22889611 https://echonewspaper.com.au/news/community-engagement-begins-for-new-hazelmere-data-centre/ https://echonewspaper.com.au/news/swan-backs-data-centre-policy-push/ https://www.planning.wa.gov.au/docs/default-source/daps-docs-other/current-applications.pdf https://www.planning.wa.gov.au/docs/default-source/daps-docs-website/current-applications.pdf?sfvrsn=ebbf7a78_310 https://www.planning.wa.gov.au/development-assessment-panels/current-development-assessment-panels-applications-and-information https://www.cdc.com/locations/perth/hazelmere/ https://renewmap.com.au/resources/projects/wa/datacentre/ | AJ27: 開啟地圖 | AK27: WA-A、WA-B
A28: NSW-012 | B28: 新南威爾斯州 | C28: Gateway Capital Frederick Street Data Centre, St Leonards / Artarmon（SSD-139545990） | D28: Gateway Capital（與 Lendlease 負責建造/營運，W.Media） | E28: Gateway Capital Holdings Pty Ltd（Scoping 申請人；2023 年以 A$118.5m 自 Dexus 購入，與 Invesco 合資） | F28: 12 Frederick Street, St Leonards NSW 2065 (portal lists Artarmon) | G28: St Leonards | H28: 2065 | I28: Willoughby City | J28: -33.81909 | K28: 151.18958 | L28: 來源提供 | M28: 81 | N28: IT 負載 | P28: Scoping Report（2026-08）：總電力需求 81 MW；五層、11 個 data halls、GFA 16,634 m2、PUE <1.3、44 台發電機、2 座 33 kV 變電站；W.Media：A$1bn。 | Q28: 已送件、審查中 | R28: 主清單 | T28: 2026-09-15 | U28: 尚未核准。Scoping 2026-08-06；SEARs 簽發 2026-09-15；Portal 現狀 Prepare EIS。W.Media 稱仍在「中期考慮」階段。 | V28: Scoping：Stage 1 拆除 2027 Q4 | W28: Scoping：Stage 2 施工 2028 Q3–2030 Q4 | X28: 2028 年以後 | Y28: Scoping Report（Urbis，2026-08） | Z28: 大概可租 | AA28: W.Media：無錨定客戶，屬批發/多租戶模式——是少數仍可談預租的標的，但最早 2030 年底才交付。 | AB28: 無（W.Media 2026-08-26） | AC28: SSD-139545990（Prepare EIS） | AD28: 高 | AE28: 先前 沒有申請人——現證實為 Gateway Capital；先前資料 只列 Frederick Street, Artarmon（SSD-139545990）而未知 proponent；現確認為 Gateway Capital。申請已提出但業主態度保守（中期考慮），實際動工時程不確定；先前資料清單寫 Artarmon；SEARs 寫 St Leonards（Willoughby LGA） 地址備註：基地 1.82 公頃，原兩棟大型倉庫/室內運動設施；鄰皇家北岸醫院與 Gore Hill 科技園。 | AF28: https://www.planningportal.nsw.gov.au/major-projects/projects/frederick-street-data-centre https://majorprojects.planningportal.nsw.gov.au/prweb/PRRestService/mp/01/getContent?AttachRef=PDA-137556738%2120260806T061124.974+GMT | AH28: https://w.media/gateway-considers-81mw-data-centre-at-sydneys-st-leonards/ https://baxtel.com/data-center/gateway-sydney | AI28: https://www.planningportal.nsw.gov.au/major-projects/projects/frederick-street-data-centre https://majorprojects.planningportal.nsw.gov.au/prweb/PRRestService/mp/01/getContent?AttachRef=PDA-137556738%2120260806T061124.974+GMT https://w.media/gateway-considers-81mw-data-centre-at-sydneys-st-leonards/ | AJ28: 開啟地圖 | AK28: NSW-B、NSW-C、NSW-A
A29: VIC-010 | B29: 維多利亞州 | C29: Goodman Truganina 資料中心（433 Mount Atkinson Road；聯邦 AIPP 稱 MEL02 Building A；DFP 申請 PA2604503） | D29: Goodman（開發，未公布營運商） | E29: Goodman Property Services (Aust) Pty Ltd（土地向 ESR 購入，前 Logos） | F29: 433 Mount Atkinson Road, Truganina VIC 3029 | G29: Truganina | H29: 3029 | I29: Melton City Council（依 DCM wiki） | J29: -37.771667 | K29: 144.67552 | L29: 來源提供 | M29: 未公布 | N29: 變電容量（MVA） | P29: 登記冊未載 MW，僅『兩層、三棟資料中心』。聯邦 AIPP 摘要（2026-09-14）：首棟，約 180 MVA，資本支出 A$500m–1bn，園區 36 ha。180 MVA 換算 IT MW 會更低。 | Q29: 已送件、審查中 | R29: 主清單 | T29: 2026-09-14 | U29: DFP PA2604503：2026-06-30 受理，登記冊無決定。AIPP 摘要（已讀）：FID 預計 2026-10、長交期設備採購 2026-11 起、2027-04 開工、Phase 1 與 2 於 2029-06 試運轉、預計完工 2030-12-12。 | V29: 2027-04（計畫，AIPP） | W29: 2029-06（Phase 1 & 2 試運轉）；2030-12-12 全部完工 | X29: 2028 年以後 | Y29: 聯邦 AIPP 摘要 2026-09-14（Goodman 提交） | Z29: 大概可租 | AA29: Goodman 以出租予超大規模客戶為主，租戶未公布；AIPP 稱將聘 Design & Construct Partner。 | AB29: 未公布 | AC29: DFP PA2604503（待決）；AIPP 參考碼 V9Z4B5-C6T4X4 | AD29: 中 | AE29: AIPP 與 433 Mount Atkinson Road 的對應是推定（其他資料 同樣推定）；先前資料稱 433 Mount Atkinson Road「reported Goodman」——申請人欄確認為 Goodman Property Services。AIPP 的「MEL02」與 STACK 的 MEL02 同名但是不同專案；AIPP 與 PA2604503 的對應為推定。au.goodman.com 回 403，Goodman 官網頁未能開啟；申請日：先前 記為 2026-06-30，DCD/W.Media 稱 July 2026 提交。租賃模式為依 Goodman 慣例推定，非本案原文 地址備註：AIPP 只寫『Truganina，36 ha 工業開發區』，與 433 Mount Atkinson Road 的對應為推定。 | AF29: https://www.planning.vic.gov.au/planning-approvals/ministerial-permits-register/ministerial-permits/fdc8d827-6b74-f111-ab0f-7c1e522a8afb https://www.industry.gov.au/sites/default/files/aip/2026-09/mel02-building-a-aipp-summary.pdf https://www.planning.vic.gov.au/planning-approvals/ministerial-permits-register | AG29: https://au.goodman.com/property-lease-site/MEL02 | AH29: https://www.datacenterdynamics.com/en/news/au11-billion-data-center-project-proposed-outside-melbourne-australia/ https://www.realestatesource.com.au/data-centre-giant-buys-350m-melbourne-site/ https://datacentremoratorium.net/index.php/Resources:Goodman_Truganina https://w.media/victorias-data-centre-pipeline-grows-with-four-new-melbourne-proposals/ | AI29: https://www.planning.vic.gov.au/planning-approvals/ministerial-permits-register/ministerial-permits/fdc8d827-6b74-f111-ab0f-7c1e522a8afb https://www.industry.gov.au/sites/default/files/aip/2026-09/mel02-building-a-aipp-summary.pdf https://www.datacenterdynamics.com/en/news/au11-billion-data-center-project-proposed-outside-melbourne-australia/ https://www.realestatesource.com.au/data-centre-giant-buys-350m-melbourne-site/ https://datacentremoratorium.net/index.php/Resources:Goodman_Truganina https://w.media/victorias-data-centre-pipeline-grows-with-four-new-melbourne-proposals/ https://nominatim.openstreetmap.org/search?q=433+Mount+Atkinson+Road+Truganina+VIC | AJ29: 開啟地圖 | AK29: VIC-B、VIC-A、VIC-C
A30: NSW-013 | B30: 新南威爾斯州 | C30: AirTrunk SYD3 — 51 Huntingwood Drive Data Centre（SSD-41589232） | D30: AirTrunk（依申請人 EMKC Cubed Management Pty Ltd 與圖檔代碼 ATSYD3 推定；政府文件未直呼 AirTrunk） | E30: EMKC Cubed Management Pty Ltd（原 SSD 申請人）；Mod 2 由建商 AW Edwards Pty Ltd 代為申請 | F30: 51 Huntingwood Drive, Huntingwood NSW 2148 | G30: Huntingwood | H30: 2148 | I30: Blacktown | J30: -33.79863 | K30: 150.876 | L30: 來源提供 | M30: 400 | N30: 耗電量 | P30: 原核准（2023-09-15）：400 MW、七層、10 個 data shells、GFA 122,546 m2、316 台柴油發電機、CIV A$1,074,990,484、施工 1,333 人。Mod 2（2026-08-28 核准）：10 shells 併為 5 shells（A–E，30 個 data halls），GFA 降至 64,346 m2，但申請理由是「提高整體電力容量」（以更高機架密度；MW 數字未在評估報告列出）——400 MW 同意書未改。 | Q30: 施工中 | R30: 主清單 | T30: 2026-08-28 | U30: CEMP 核准 2023-10-17；分階段核准 2023-10-15；「A10/A11 Notice of Commencement – Stage 2 construction works」（AW Edwards 致規劃部，2024-08-22）：Stage 2 於 2024-10-01 開工；Stage 2 管理計畫核准 2024-11-08；ESCP 更新 2026-04-24；Mod 2 核准 2026-08-28。媒體：Bouygues/AW Edwards 取得約 A$1.3bn 後續階段合約（先前資料）。 | V30: Stage 1：2023-10（CEMP 核准）；Stage 2：2024-10-01（AW Edwards 函）。 | W30: 同意書規定三階段、每階段 24 個月；Stage 2 起於 2024-10-01。未見營運商公布完工日。 | X30: 完工日未公布 | Y30: DPHI SSD Assessment Report（2023-09-15）；AW Edwards 開工通知（2024-08-22） | Z30: 可租 | AA30: AirTrunk 為批發型超大規模營運商，對第三方出租；但此站規模大、多半由超大規模客戶預租，尚無任何政府文件顯示尚未預租的容量。 | AB30: 未揭露 | AC30: SSD-41589232（Mod 1 撤回；Mod 2 核准 2026-08-28） | AD30: 高 | AE30: 先前資料「ATSYD3 檔名＝AirTrunk SYD3」；政府文件只顯示申請人 EMKC Cubed Management Pty Ltd（與 Apollo Place 同一申請人，後者核准函收件人為「Trustee for Airtrunk Lane Cove Trust」），故 AirTrunk 歸屬屬合理推定。Mod 2 報告內部稱該棟為「SYD02 building」，命名與 先前 的 SYD3 不一致；AirTrunk 為申請人屬先前資料依圖檔代號 ATSYD3 推定，入口網站文件未直接顯示公司名；Baxtel 另有 SYD2（營運中）與 Kemps Creek 條目，請勿與 SYD3 混淆 地址備註：Lot 1 DP 857249；位於 Great Western Hwy 與 M4 之間；基地約 9 公頃（原為 Endeavour Energy 辦公室）。 | AF30: https://www.planningportal.nsw.gov.au/major-projects/projects/51-huntingwood-drive-data-centre https://majorprojects.planningportal.nsw.gov.au/prweb/PRRestService/mp/01/getContent?AttachRef=SSD-41589232%2120230915T074128.135+GMT https://majorprojects.planningportal.nsw.gov.au/prweb/PRRestService/mp/01/getContent?AttachRef=SSD-41589232-PA-14%2120240822T035712.620+GMT https://majorprojects.planningportal.nsw.gov.au/prweb/PRRestService/mp/01/getContent?AttachRef=SSD-41589232-MOD-2%2120260828T070329.740+GMT https://www.planningportal.nsw.gov.au/major-projects/projects/51-huntingwood-drive-data-centre-mod-2-design-updates | AH30: https://baxtel.com/data-center/airtrunk-syd3-sydney-west | AI30: https://www.planningportal.nsw.gov.au/major-projects/projects/51-huntingwood-drive-data-centre https://majorprojects.planningportal.nsw.gov.au/prweb/PRRestService/mp/01/getContent?AttachRef=SSD-41589232%2120230915T074128.135+GMT https://majorprojects.planningportal.nsw.gov.au/prweb/PRRestService/mp/01/getContent?AttachRef=SSD-41589232-PA-14%2120240822T035712.620+GMT https://majorprojects.planningportal.nsw.gov.au/prweb/PRRestService/mp/01/getContent?AttachRef=SSD-41589232-MOD-2%2120260828T070329.740+GMT https://www.planningportal.nsw.gov.au/major-projects/projects/51-huntingwood-drive-data-centre-mod-2-design-updates | AJ30: 開啟地圖 | AK30: NSW-B、NSW-A
A31: VIC-011 | B31: 維多利亞州 | C31: CDC Laverton Campus（Laverton North，CDC 墨爾本第二園區） | D31: CDC Data Centres (CDC) | E31: CDC Data Centres（自建自營；股東結構本次未查證） | F31: 20-38 Leakes Road, Laverton North VIC 3026 | G31: Laverton North | H31: 3026 | I31: Wyndham City Council | J31: -37.841092 | K31: 144.76591 | L31: 街道級 | M31: 400 | N31: 口徑不明 | O31: 150 | P31: CDC 官網墨爾本頁（2026-10-03 讀取）：Laverton 完工後將增加「over 400 MW」，Brooklyn 完工後「over 350 MW」，墨爾本合計 780 MW 以上。2025-02-17 動土新聞稿稱「新的 150 MW 園區」，應為第一階段。Baxtel（聚合器）列 Campus One 150 MW、Campus Two 300 MW。CDC 未說明 MW 是 IT 負載、關鍵負載或耗電量（CDC 在雪梨的 MW 多以 power consumption 表述），基準不明。 | Q31: 施工中 | R31: 主清單 | T31: 2026-06-18 | U31: (1) CDC 新聞稿：2025-02-17 動土，稱已在 Laverton 開工興建 150 MW 園區（cdc.com 已讀）。(2) Wyndham 規劃許可 WYP14790/24（2024-10-02 受理）的後續動作：.07「第三棟資料中心大樓」S72 修改約 2026-02-18 受理（PlanningAlerts 已讀）；.06 為「LA1 Data Centre」增設發電機 plenum（2026-01-16 提出、2026-06-15 核發）；WYP15649/26 土方工程許可（2026-05-01 提出、2026-06-18 核發）——後兩項日期取自 DCM wiki 對 Wyndham 紀錄的整理，未直接開啟 Wyndham 入口網站。(3) CDC 官網墨爾本頁（2026-10-03 讀取）稱 Laverton 園區「currently under construction」。 | V31: 2025-02-17 | W31: 2027（首期；CDC 未公布） | X31: 完工日未公布 | Y31: Baxtel（聚合器，Laverton 頁列 Expected Completion 2027，已讀）；CDC 官方未公布完工日期 | Z31: 可租 | AA31: CDC 為出租型（批發/超大規模/政府）業者，Laverton 租戶未公布。CDC 與一家美國客戶簽有 555 MW、30 年合約（Infratil，先前資料；涵蓋哪些園區未證實），Laverton 容量可能大量預售；5 MW 租戶須直接詢問 CDC 是否有小型模組。 | AB31: Laverton 未公布（同公司 Brooklyn 園區有 Firmus，客戶為 Meta） | AC31: Wyndham WYP14790/24（含 .06 / .07 修改）；WYP15649/26 | AD31: 高 | AE31: 容量：150 MW（2025-02 動土稿）vs over 400 MW（CDC 官網 2026-10）vs Baxtel 150+300 MW；建議以 CDC 官網為園區完工規模、150 MW 為第一期。另：Invest Victoria 2026-03 新聞「CDC officially opens its first Melbourne campus」指的是 Brooklyn，不是 Laverton（DJSIR 2026-02-26 稿可佐證）；MW：150（CDC 動土稿）vs 逾 400（CDC 官網，其他代理讀取） 地址備註：街址取自 Wyndham 市議會申請 WYP14790/24（PlanningAlerts 頁面，受理日 2024-10-02，描述為 utility installation (data centre)）與 Baxtel；CDC 新聞稿只稱 Laverton。注意：同區 AusNet 的 Laverton North 輸電工程是服務 114-146 Leakes Road 的另一座資料中心（見 PAC1 紀錄），不要混淆。 | AF31: https://www.planningalerts.org.au/applications/3206534 https://www.planningalerts.org.au/applications/3436259 https://djsir.vic.gov.au/news-and-articles/cdcs-data-centres-fueling-jobs-and-growth-in-the-west | AG31: https://cdc.com/resources/news/cdc-brings-27bn-groundbreaking-opportunity-to-melbournes-south-west/ https://cdc.com/locations/melbourne/ | AH31: https://baxtel.com/data-center/cdc-laverton-campus https://datacentremoratorium.net/index.php/Resources:CDC_Laverton_Campus https://www.datacenterdynamics.com/en/news/australias-cdc-opens-data-center-campus-in-melbourne/ | AI31: https://www.planningalerts.org.au/applications/3206534 https://www.planningalerts.org.au/applications/3436259 https://cdc.com/resources/news/cdc-brings-27bn-groundbreaking-opportunity-to-melbournes-south-west/ https://cdc.com/locations/melbourne/ https://baxtel.com/data-center/cdc-laverton-campus https://datacentremoratorium.net/index.php/Resources:CDC_Laverton_Campus https://djsir.vic.gov.au/news-and-articles/cdcs-data-centres-fueling-jobs-and-growth-in-the-west https://www.datacenterdynamics.com/en/news/australias-cdc-opens-data-center-campus-in-melbourne/ | AJ31: 開啟地圖 | AK31: VIC-A、VIC-B
A32: VIC-012 | B32: 維多利亞州 | C32: NEXTDC M3（West Footscray）— Stage 2／Stage 4 施工中（已核准階段） | D32: NEXTDC Limited | E32: NEXTDC（承建 Kapitol） | F32: 25 Indwe Street, West Footscray VIC 3012 | G32: West Footscray | H32: 3012 | I32: Maribyrnong City Council | J32: -37.803512 | K32: 144.86548 | L32: 門牌級 | M32: 207 | N32: IT 負載 | O32: 165 | P32: NEXTDC FY26 簡報：M3 已交付 42 MW、另有 165 MW 在建（合計 207 MW）；官網稱規劃 225 MW；RenewMap 的 133 MW 是集團訂單簿數字，不可用。 | Q32: 施工中 | R32: 主清單 | T32: 2026-02-25 | U32: Kapitol 專案頁（2025-07）：M3 Stage 2 與 Stage 4 兩個工地六台塔吊，Stage 2 接近封頂；NEXTDC 1H26 ASX 新聞稿：capex A$1,285m 投入 S3、M3、KL1 等；The Age 2026-03-25：M3 自 2021 年起興建、居民抱怨施工粉塵。 | V32: 園區 2021；Stage 2/4 約 2024–2025 | W32: 未公布（擴建 PA2604231 預計 2027 年底，The Age） | X32: 完工日未公布 | Y32: NEXTDC／The Age | Z32: 大概可租 | AA32: NEXTDC 新容量大量預售（1H26 合約利用率 416.6 MW、計費 119.8 MW）；5 MW 租戶需洽 NEXTDC。 | AB32: 未公布 | AC32: Maribyrnong 2021 規劃同意（編號未取得）；擴建見 DFP PA2604231 | AD32: 高 | AE32: 容量口徑：NEXTDC 225 MW（現行總規劃）vs 150 MW（2021 舊稿）vs DCM wiki 320 MW vs RenewMap 133 MW（疑為預售訂單數）；(1) 先前資料 將 PA2403320（63 Sunshine Road, West Footscray；申請人 Contour Consultants）歸為 NEXTDC M3——本次不成立：該許可是 Goldsborough Mort 羊毛倉庫改建，官方文件未提 NEXTDC（見獨立紀錄）；M3 實際 DFP 申請為 PA2604231（NEXTDC Limited）。(2) MW：225（官網）/ 150（舊 masterplan）/ 320（DCM wiki）/ 133（RenewMap=預售訂單） 地址備註：25 Indwe Street 取自 DCM wiki；NEXTDC 擴建申請 PA2604231 列的土地為 1 Paramount Road、39 Indwe Street、11-13 Paramount Road、15 Paramount Road（Tottenham Employment Precinct）。定位時請以 PA2604231 地塊為準交叉比對。 | AF32: https://www.planning.vic.gov.au/planning-approvals/ministerial-permits-register/ministerial-permits/ef7039bf-cd0b-f111-8407-7c1e5262e60a | AG32: https://www.nextdc.com/news/asx-release-1h26-record-results https://www.nextdc.com/news/its-all-systems-go-victoria-nextdc-unveils-plans-150mw-hyperscale-campus-melbournes-west https://www.kapitol.com/insights/project-news/project-update-m3-stage-2-and-4 https://www.nextdc.com/data-centres/m3-melbourne-data-centre | AH32: https://www.theage.com.au/national/victoria/west-footscray-data-centre-bids-to-double-in-size-amid-nightmare-construction-20260324-p5uags.html https://www.kapitol.com/insights/project-news/project-update-m3-stage-2-and-4 https://baxtel.com/data-center/nextdc-m3west-footscray https://datacentremoratorium.net/index.php/Resources:NEXTDC_M3 | AI32: https://www.nextdc.com/news/asx-release-1h26-record-results https://www.nextdc.com/news/its-all-systems-go-victoria-nextdc-unveils-plans-150mw-hyperscale-campus-melbournes-west https://www.kapitol.com/insights/project-news/project-update-m3-stage-2-and-4 https://www.theage.com.au/national/victoria/west-footscray-data-centre-bids-to-double-in-size-amid-nightmare-construction-20260324-p5uags.html https://datacentremoratorium.net/index.php/Resources:NEXTDC_M3 https://www.planning.vic.gov.au/planning-approvals/ministerial-permits-register/ministerial-permits/ef7039bf-cd0b-f111-8407-7c1e5262e60a https://www.nextdc.com/data-centres/m3-melbourne-data-centre https://datacentremoratorium.net/index.php/Resources:Data_Centres_in_Greater_Melbourne | AJ32: 開啟地圖 | AK32: VIC-B、VIC-A
A33: VIC-013 | B33: 維多利亞州 | C33: NEXTDC M4（Fishermans Bend／Port Melbourne，127 Todd Road；DFP 許可 PA2504019） | D33: NEXTDC Limited | E33: NEXTDC Limited（申請人 NEXTDC Limited c/- Urbis） | F33: 127 Todd Road, Port Melbourne VIC 3207 | G33: Port Melbourne | H33: 3207 | I33: City of Melbourne（Fishermans Bend；責任機關為規劃部長） | J33: -37.834266 | K33: 144.91348 | L33: 街道級 | M33: 162 | N33: 口徑不明 | O33: 10 | P33: NEXTDC 2026-01-19 新聞稿：M4 為 162 MW 園區（AI Factory、任務關鍵營運中心、技術卓越中心），直達晶片液冷、機櫃密度逾 1,000 kW；2025-06-12 新聞稿曾稱 up to 150 MW／50,000 m²。總投資 A$2bn，The Age 稱建造成本 A$911m。DTP 官員報告：單棟五層建築、三個主要資料廳組件，GFA 94,987 m²。ABC 引述規劃文件：現場柴油 3.5 ML、鋰電池 900 噸。 | Q33: 施工中 | R33: 主清單 | T33: 2026-08-27 | U33: NEXTDC FY26 簡報（2026-08-27）：M4 early works commenced with 10 MW in progress；DFP 許可 PA2504019 於 2026-01-16 核發。 | V33: 未公布 | W33: 未公布 | X33: 完工日未公布 | Y33: — | Z33: 大概可租 | AA33: NEXTDC 為 colocation／批發型業者，M4 主打主權 AI 與國防客戶。NEXTDC 全公司合約利用率遠高於計費利用率（1H26：合約 416.6 MW、計費 119.8 MW），新容量多半預售，5 MW 租戶需向 NEXTDC 確認可用性。 | AB33: 未公布 | AC33: DFP PA2504019（permit 2026-01-16） | AD33: 高 | AE33: 容量：150 MW（NEXTDC 2025-06）→ 162 MW（2026-01）；成本：A$911m（The Age，建造）vs A$2bn（NEXTDC，整體投資）；150 MW（DCD）vs 162 MW（Mingtiandi、DCM wiki）。 地址備註：前 Westgate Park 印刷廠（News Corp 報廠，2024 年拆除），毗鄰 Westgate Park 濕地與 West Gate Freeway。 | AF33: https://www.planning.vic.gov.au/planning-approvals/ministerial-permits-register/ministerial-permits/76685df6-baaf-f011-bbd2-6045bdc32df2 https://sftpbspomppprod01.blob.core.windows.net/applicationfiles/76685df6-baaf-f011-bbd2-6045bdc32df2_REDACTED_PA2504019%20Officer%20Report%20-%20Signed%2016-01-26.pdf | AG33: https://www.nextdc.com/news/m4-technology-campus-approved https://www.nextdc.com/news/nextdc-announces-2-billion-ai-factory-and-technology-campus-at-fishermans-bend https://www.nextdc.com/news/asx-release-1h26-record-results https://www.nextdc.com/data-centres/m3-melbourne-data-centre | AH33: https://www.theurbandeveloper.com/articles/nextdc-m4-digital-campus-fishermans-bend-approval https://www.theage.com.au/national/victoria/1b-data-centre-given-planning-tick-in-just-75-days-as-state-gets-cosy-with-big-tech-20260219-p5o3sl.html https://www.abc.net.au/news/2026-06-09/firefighter-concern-over-data-centres-in-melbourne-west/106762858 https://www.datacenterdynamics.com/en/news/nextdc-receives-development-approval-for-m4-campus-in-melbourne-australia/ https://www.mingtiandi.com/real-estate/data-centres/stockland-seeks-approval-for-250mw-melbourne-data-centre-campus/ | AI33: https://www.planning.vic.gov.au/planning-approvals/ministerial-permits-register/ministerial-permits/76685df6-baaf-f011-bbd2-6045bdc32df2 https://sftpbspomppprod01.blob.core.windows.net/applicationfiles/76685df6-baaf-f011-bbd2-6045bdc32df2_REDACTED_PA2504019%20Officer%20Report%20-%20Signed%2016-01-26.pdf https://www.nextdc.com/news/m4-technology-campus-approved https://www.nextdc.com/news/nextdc-announces-2-billion-ai-factory-and-technology-campus-at-fishermans-bend https://www.nextdc.com/news/asx-release-1h26-record-results https://www.theurbandeveloper.com/articles/nextdc-m4-digital-campus-fishermans-bend-approval https://www.theage.com.au/national/victoria/1b-data-centre-given-planning-tick-in-just-75-days-as-state-gets-cosy-with-big-tech-20260219-p5o3sl.html https://www.abc.net.au/news/2026-06-09/firefighter-concern-over-data-centres-in-melbourne-west/106762858 https://www.datacenterdynamics.com/en/news/nextdc-receives-development-approval-for-m4-campus-in-melbourne-australia/ https://www.mingtiandi.com/real-estate/data-centres/stockland-seeks-approval-for-250mw-melbourne-data-centre-campus/ https://www.nextdc.com/data-centres/m3-melbourne-data-centre | AJ33: 開啟地圖 | AK33: VIC-B、VIC-A
A34: VIC-014 | B34: 維多利亞州 | C34: NEXTDC M2（Tullamarine）— 擴建階段施工中 | D34: NEXTDC Limited | E34: NEXTDC（承建 Kapitol） | F34: 75 Sharps Road and 9 Barrie Road, Tullamarine VIC 3043 | G34: Tullamarine | H34: 3043 | I34: Brimbank City Council | J34: -37.708865 | K34: 144.87545 | L34: 門牌級 | M34: 72 | N34: IT 負載 | O34: 60 | P34: NEXTDC FY26 簡報：M2 已交付 12 MW、另有 60 MW 在建（合計 72 MW）；官網稱全站 120 MW 以上（長期規劃）。 | Q34: 施工中 | R34: 主清單 | T34: 2026-08-27 | U34: NEXTDC FY26 簡報（2026-08-27）：M2 Melbourne 12 MW delivered with remaining 60 MW in progress。無政府施工文件，施工細節未公開。 | V34: 未公布 | W34: Kapitol 頁面稱 Stage 6 原定 2025 年完工，但 NEXTDC 於 2025-12-31 仍列 30 MW 推進中，實際日期未公布 | X34: 完工日未公布 | Z34: 大概可租 | AA34: NEXTDC 為商業託管營運商，但同簡報顯示維州已簽約容量為已建成容量的 261%，新增容量幾乎全數預售，需直接詢問是否有未簽約區塊。 | AB34: 未公布 | AC34: Brimbank P589/2016（主許可，多次修訂）；P154/2025（修訂，2025-04-23 受理） | AD34: 高 | AE34: M2 規模 60 MW（Kapitol）vs 150 MW（DCM wiki）；進行中 30 MW（NEXTDC）vs 單階段 8 MW（Kapitol）。 地址備註：街址取自 DCM wiki；M2 毗鄰 AirTrunk MEL2（85 Sharps Road）。 | AF34: https://records.brimbank.vic.gov.au/ExternalLinkAPI/api/document/?docKey=UHZYRmNFYWVDaUN0clNmekJwVXhMUExwUGpQcFE0VVFXVnp1NkdSYlZpc0lsS2NCZlVOWUxOVXBncy9DSUhHZg2 | AG34: https://www.nextdc.com/news/asx-release-1h26-record-results https://www.kapitol.com/our-projects/industrial/nextdc-m2-data-centre-portfolio-2 | AI34: https://www.nextdc.com/news/asx-release-1h26-record-results https://www.kapitol.com/our-projects/industrial/nextdc-m2-data-centre-portfolio-2 https://records.brimbank.vic.gov.au/ExternalLinkAPI/api/document/?docKey=UHZYRmNFYWVDaUN0clNmekJwVXhMUExwUGpQcFE0VVFXVnp1NkdSYlZpc0lsS2NCZlVOWUxOVXBncy9DSUhHZg2 https://datacentremoratorium.net/index.php/Resources:NEXTDC_M2 | AJ34: 開啟地圖 | AK34: VIC-B
A35: ACT-001 | B35: 首都領地 | C35: CDC Hume 6 (HU6) - Hume Campus Two 擴建 | D35: CDC Data Centres (Canberra Data Centres Pty Ltd) | E35: CDC Group 自建自營（Infratil 持股約 49.7%，依 Infratil FY2026 年報；其餘主要股東未於已讀資料中列名） | F35: 62 Sawmill Circuit, Hume ACT 2620 (Block 99 Section 7) | G35: Hume | H35: 2620 | I35: Australian Capital Territory（ACT 無地方政府；由 ACT Government / Territory Planning Authority 審批） | J35: -35.39707 | K35: 149.16393 | L35: 來源提供 | M35: 20 | N35: 口徑不明 | P35: 20 MW 來源：Infratil FY2026 年報（2026-05-29）第 18 頁地圖，CDC 坎培拉「興建中」容量 20MW（截至 2026-03-31）；CDC 2026-03-26 投資人簡報（ASX）顯示坎培拉僅 HU6 為興建中，故推定 20MW 即 HU6（推論）。DA 基礎設施報告（SUPP-202443633-INFRASTRUCTURE_REPORT-01）載 Hu6 計算最大需量約 20MVA（Evoenergy 11kV，4 路市電饋線取自 Hume 2 園區既有 2 座 switching station；備援電源由 HU5 的 11kV 發電機提供）。建築：2 層、GFA 8,281 m2、7 個資料機房（1F 4 間、2F 3 間）。CDC 未說明 MW 是 IT 或 critical 口徑，20MW 與 20MVA 也未必同義。 | Q35: 施工中 | R35: 主清單 | T35: 2026-05-29 | U35: （營運商/ASX 層）CDC 投資人簡報（Infratil 於 ASX 公告，2026-03-26）第 4 頁以「Data centre under construction」圖例標示 HU6，並稱全集團 5 座興建中、坎培拉僅 HU6；Infratil FY2026 年報（2026-05-29）第 18 頁：坎培拉興建中 20MW。（政府層）DA202443633 於 2025-06-12 附條件核准（Notice of Decision，delegate Fawzia Majid）；修正案 S205H（2025-11-28，Block 26 地下管線）與 S205E（2026-05-26，冷卻機組平台隔音牆、空橋縮短、增設立管等施工圖層級調整）均獲核准，顯示設計與施工持續推進。ACT 不公開開工通知，故無 notice of commencement。（彙整站層，僅線索）DatacenterMap 亦標示 Under Construction。 | V35: 未公布；DA 核准（2025-06-12）後、最晚 2026-03-26 前已動工 | W35: 未公布 | X35: 完工日未公布 | Y35: 無（CDC 官網 cdc.com/locations/canberra 只列 7 座營運中資料中心，未提 HU6；政府文件亦無完工日） | Z35: 大概可租 | AA35: CDC 是批發/託管業者；其坎培拉園區服務聯邦政府機構、國安單位、研究機構與產業夥伴（CDC 2026-08-26 聲明）。Infratil FY2026 年報：營收九成以上來自投資級對手方、加權平均租期約 27 年；CDC 採 demand-led 建置，容量多半預先簽約。HU6 是否仍有 5MW 以上未簽約容量，公開資料無法判斷，需直接向 CDC 洽詢。 | AB35: 未公開（CDC 未列名坎培拉客戶） | AC35: DA202443633（2025-06-12 附條件核准）；修正 DA202443633-S205H（2025-11-28）、DA202443633-S205E（2026-05-26） | AD35: 高 | AE35: （1）DatacenterMap/Baxtel 把 HU6 歸在 5 Tralee St（Hume Campus Two 園區地址），DA 顯示新建築實際在 Block 99（62 Sawmill Circuit）。（2）CDC 官網仍寫 Hume Campus Two 只有 HU4、HU5，且坎培拉總量「250 MW +」，未提 HU6。（3）20MW（Infratil 圖）與約 20MVA（DA 計算需量）口徑不同，不可直接等同；CDC 官網 Hume Campus Two 只列 HU4、HU5（51 MW 運轉），未列在建的 HU6；Baxtel Canberra 市場頁寫 0 MW 在建（過時）。；容量只有約 20 MVA 的計算需量，IT MW 未公布；兩者不可直接等同。 地址備註：DA202443633 的地址欄寫「62 Sawmill Circuit, 5 Tralee Street, Hume」。新建築位於 Block 99 Section 7（62 Sawmill Circuit，面向 Sawmill Circuit），以空橋連接 Block 103 Section 7（5 Tralee Street）上既有的 HU4/HU5（CDC Hume Campus Two）；兩塊租約將合併。另有 Block 26 Section 7（未租賃領地，約 77 m2）供私有地下電力與通訊管線（DA 修正 S205H，2025-11-28 核准，另需 direct sale）。DatacenterMap 把 HU6 掛在園區地址 5 Tralee St。Block 103 Section 7 的多邊形中心點約為 lat -35.39589 / lon 149.16328。 | AF35: https://www.planning.act.gov.au/applications-and-assessments/development-applications/browse-das/development-application-details?da-number=202443633&amendment-version= https://dafinder.blob.core.windows.net/dadocuments/DOCs/NOTICEOFDECISION-202443633-SIGNED.pdf https://dafinder.blob.core.windows.net/dadocuments/DOCs/NOTICEOFDECISION-202443633-S205D-SIGNED.pdf https://dafinder.blob.core.windows.net/dadocuments/DOCs/NOTICEOFDECISION-202443633-S205E-SIGNED.pdf https://dafinder.blob.core.windows.net/dadocuments/DOCs/SUPP-202443633-INFRASTRUCTURE_REPORT-01.pdf https://dafinder.blob.core.windows.net/dadocuments/DOCs/DEVOUTCOMEREP-202443633-01.pdf https://services1.arcgis.com/E5n4f1VY84i0xSjy/arcgis/rest/services/ACTGOV_DAFINDER_LIST_VIEW/FeatureServer/0/query https://www.planning.act.gov.au/applications-and-assessments/development-applications/browse-das/development-application-details?da-number=202443633 https://dafinder.blob.core.windows.net/dadocuments/DOCs/SUPP-202443633-STATEMENT-01.pdf https://dafinder.blob.core.windows.net/dadocuments/DOCs/DEVOUTCOMEREP-202443633-S205E-01.pdf | AG35: https://announcements.asx.com.au/asxpdf/20260326/pdf/06xtcw1cnqqc5p.pdf https://infratil.com/for-investors/financial-reports/annual-report-2026/ https://cdc.com/locations/canberra https://cdc.com/resources/news/cdc-welcomes-act-governments-data-centre-framework-development/ https://cdc.com/au/canberra | AH35: https://www.datacentermap.com/australia/canberra/cdc-hume-hu6/ https://baxtel.com/data-center/cdc-hume-5 https://region.com.au/new-200-million-data-centre-proposed-for-beard-fits-territory-standards-on-power-and-water/996833/ | AI35: https://www.planning.act.gov.au/applications-and-assessments/development-applications/browse-das/development-application-details?da-number=202443633&amendment-version= https://dafinder.blob.core.windows.net/dadocuments/DOCs/NOTICEOFDECISION-202443633-SIGNED.pdf https://dafinder.blob.core.windows.net/dadocuments/DOCs/NOTICEOFDECISION-202443633-S205D-SIGNED.pdf https://dafinder.blob.core.windows.net/dadocuments/DOCs/NOTICEOFDECISION-202443633-S205E-SIGNED.pdf https://dafinder.blob.core.windows.net/dadocuments/DOCs/APP-202443633-02.pdf https://dafinder.blob.core.windows.net/dadocuments/DOCs/SUPP-202443633-INFRASTRUCTURE_REPORT-01.pdf https://dafinder.blob.core.windows.net/dadocuments/DOCs/SUPP-202443633-S205D-LETTER-01.pdf https://dafinder.blob.core.windows.net/dadocuments/DOCs/DEVOUTCOMEREP-202443633-01.pdf https://services1.arcgis.com/E5n4f1VY84i0xSjy/arcgis/rest/services/ACTGOV_DAFINDER_LIST_VIEW/FeatureServer/0/query https://services1.arcgis.com/E5n4f1VY84i0xSjy/arcgis/rest/services/ACTGOV_BLOCKS/FeatureServer/0/query https://announcements.asx.com.au/asxpdf/20260326/pdf/06xtcw1cnqqc5p.pdf https://infratil.com/for-investors/financial-reports/annual-report-2026/ https://cdc.com/locations/canberra https://cdc.com/resources/news/cdc-welcomes-act-governments-data-centre-framework-development/ https://www.datacentermap.com/australia/canberra/cdc-hume-hu6/ https://www.planning.act.gov.au/applications-and-assessments/development-applications/browse-das/development-application-details?da-number=202443633 https://dafinder.blob.core.windows.net/dadocuments/DOCs/SUPP-202443633-STATEMENT-01.pdf https://dafinder.blob.core.windows.net/dadocuments/DOCs/DEVOUTCOMEREP-202443633-S205E-01.pdf https://cdc.com/au/canberra https://baxtel.com/data-center/cdc-hume-5 https://region.com.au/new-200-million-data-centre-proposed-for-beard-fits-territory-standards-on-power-and-water/996833/ | AJ35: 開啟地圖 | AK35: ACT-B、ACT-A
A36: QLD-001 | B36: 昆士蘭州 | C36: Supernode Brendale 資料中心園區（Quinbrook） | D36: Supernode（Quinbrook Infrastructure Partners 旗下投資組合公司） | E36: Quinbrook Infrastructure Partners | F36: 83 Kremzow Road, Brendale QLD 4500 | G36: Brendale | H36: 4500 | I36: Moreton Bay Regional Council（City of Moreton Bay） | J36: -27.318286 | K36: 152.99256 | L36: 街道級 | M36: 500 | N36: IT 負載 | P36: Quinbrook 官網：資料中心 potential 500 MW-IT（潛在量，不是已核准／已建量）。獲核准範圍為最多四座 hyperscale 資料中心（Qld 政府 2022-07-08 新聞稿、Quinbrook），核准的 MW 與各棟規模未在可開啟來源揭露。BESS 另計，不是資料中心：Stage 1-3 合計約 780 MW／3,073 MWh。較舊報導（搜尋摘要）曾稱 230 MW-IT 與 800 MW，口徑混亂。 | Q36: 已核准、尚未動工 | R36: 主清單 | T36: 2022-07-08 | U36: 資料機房未動工，在建的是電池（BESS）。證據：(1) Qld 政府新聞稿 2022-07-08：council 規劃核准與 FIRB 核准已取得，電池工程預計 2023 年中開工。(2) Qld 政府新聞稿 2024-04-11：Stage One 250 MW／2 小時 BESS 財務關閉，Origin Energy 承租全部容量，資料儲存設施留待後續。(3) Quinbrook 官網（2026-10-03 讀取，無日期）：BESS Stage 1-2（520 MW／約 1,858 MWh）運轉中、Stage 3（250 MW／約 1,010 MWh，Stanwell tolling）施工中；Supernode DC 另列為獨立專案，頁面沒有動工、租戶或時程。 | V36: BESS：2024-04-11 財務關閉並宣布開工（Quinbrook 時間軸稱 2024-06 動工）；資料機房：未開始 | W36: BESS Stage 2-3 於 2026 至 2027 完工（Quinbrook）；資料中心無官方時程（Baxtel 聚合器稱 2028 至 2031，僅供線索） | X36: 完工日未公布 | Y36: Quinbrook 官網（BESS，無日期）；Baxtel（資料中心，聚合器，僅線索） | Z36: 可租 | AA36: Qld 政府與 Quinbrook 描述為多租戶（multi-tenant）園區，最多四座 hyperscale 資料中心，並向資料中心營運商行銷（yourneighbourhood 2022-07-13；搜尋摘要稱 CBRE 受委託負責客戶接洽，未開啟來源）。目前沒有任何資料中心租戶，也沒有動工，不可能在近期交付。 | AB36: 資料中心尚無公開租戶。BESS 的承租方為 Origin Energy（Stage 1-2）與 Stanwell Corporation（Stage 3），屬電池 tolling，不是資料機房租戶。 | AC36: Moreton Bay Regional Council 規劃許可（2022 年；DA 編號未查到）+ FIRB 核准（Qld 政府新聞稿 2022-07-08） | AD36: 中 | AE36: (1) 『施工中』標示：Baxtel 標 Planned（預計 Q2 2026，應是 BESS 日期），部分搜尋摘要稱 site is under construction；實際在建的只有 BESS。(2) BESS 規模：2022 報導約 750 至 800 MW／2,000 MWh；現行 Quinbrook 為 780 MW／3,073 MWh，故知悉事實『up to 750 MW』已過時。(3) 資料中心容量：Quinbrook 現稱 potential 500 MW-IT，較舊報導 230 MW-IT。(4) BESS 運轉時間：Quinbrook p=2719 稱 Stage 1 於 2025-10 併網；p=1283 時間軸稱 2026-02 Stage 1 運轉、2026-07 Stage 2 運轉。(5) 狀態判定依據為 2022 年的 council 核准，核准是否仍有效（currency period）與 DA 編號未查證；(1) 投資額 2022 年 A$2.5bn 對 2026 年 Quinbrook 官網 A$3bn 以上（含資料中心後續階段）。(2) Supernode 官網專案網址 /project/metro-dc/ 實際內容是 BESS，/project/sunshine-dc/ 才是資料中心，易混淆。(3) 規劃許可為 2022 年取得，是否仍有效、DA 是否曾變更本次未驗證。(4) 800 MW 是供電容量，不能直接當 IT 容量 地址備註：地址來自 Baxtel（83 Kremzow Rd, Brendale，30 公頃／74 英畝）與 Baxtel 搜尋摘要；官方來源（Qld 政府新聞稿、Quinbrook）只稱 Brendale、South Pine 變電站旁的 30 公頃土地，未列門牌。 | AF36: https://statements.qld.gov.au/statements/95682 https://statements.qld.gov.au/statements/100095 | AG36: https://www.quinbrook.com/?p=1283 https://www.quinbrook.com/?p=2719 https://www.quinbrook.com/?p=1898 https://www.quinbrook.com/portfolio-companies/supernode/ https://supernode.com.au/project/sunshine-dc/ https://supernode.com.au/project/metro-dc/ https://www.quinbrook.com/portfolio/supernode/ | AH36: https://yourneighbourhood.com.au/2-5-billion-data-supernode-brendale-moreton-bay/ https://w.media/as-australian-data-centres-demand-more-power-what-might-be-the-future-role-of-batteries/ https://baxtel.com/data-center/supernode-brendale https://w.media/quinbrook-infrastructure-partners-wins-approval-for-hyperscale-data-centres-in-australia/ https://www.datacenterdynamics.com/en/news/quinbrook-to-build-17-billion-data-center-2gwh-battery-storage-in-queensland-australia/ https://telconews.com.au/story/quinbrook-launches-2-5-billion-supernode-800mw-data-storage-project https://www.theurbandeveloper.com/articles/quinbrook-brendale-brisbane-supernode-data-centre | AI36: https://statements.qld.gov.au/statements/95682 https://statements.qld.gov.au/statements/100095 https://www.quinbrook.com/?p=1283 https://www.quinbrook.com/?p=2719 https://www.quinbrook.com/?p=1898 https://www.quinbrook.com/portfolio-companies/supernode/ https://yourneighbourhood.com.au/2-5-billion-data-supernode-brendale-moreton-bay/ https://w.media/as-australian-data-centres-demand-more-power-what-might-be-the-future-role-of-batteries/ https://baxtel.com/data-center/supernode-brendale https://telconews.com.au/story/quinbrook-launches-2-5-billion-supernode-800mw-data-storage-project https://supernode.com.au/ https://supernode.com.au/project/sunshine-dc/ https://supernode.com.au/project/metro-dc/ https://www.quinbrook.com/portfolio/supernode/ | AJ36: 開啟地圖 | AK36: QLD-A、QLD-B
A37: TAS-002 | B37: 塔斯馬尼亞州 | C37: Firmus Project Southgate — Bell Bay (Long Reach) AI Factory / Long Reach Data Centre | D37: Firmus Technologies（自營 AI 雲／AI factory 業者） | E37: Firmus Technologies（規劃申請代理 Pitt&Sherry；土地所有人未確認：DCD 2026-06-18 稱 Gunns 資產後由 New Forests 取得，DA 文件顯示通行用地為 Crown land） | F37: Lot 1 East Tamar Highway, Long Reach TAS 7253 | G37: Long Reach | H37: 7253 | I37: George Town Council | J37: -41.156064 | K37: 146.92659 | L37: 來源提供 | M37: 288 | N37: 耗電量 | P37: Firmus 官網與 DCD 以約 288 MW『draw』表述，並非 IT 負載；IT 負載未公布。DA 內容：兩棟 data hall、兩層辦公樓、維修棚、變電站、冷卻設備、276 台備用柴油發電機、128 個車位。Firmus 對國會稱塔州三站合計合約容量約 444 MW（平均運轉率約 85%、約 377 MW、年用電約 3.3 TWh）。Baxtel／DatacenterMap 另把此站拆成 GEE01／GEE02 兩棟（聚合器）。Firmus 噪音報告（Project GEE01 Operational Noise Report，2026-05-06，Firmus 網站託管）載明：兩棟 data hall 共 36 個 HyperCube（每棟 18）、148 台冷卻器（每台設計點散熱 2,500 kW，合計約 370 MW 設計散熱能力，含冗餘，不等於 IT 容量）、276 台發電機；典型 IT 負載取標稱值的 75%。IT 標稱 MW 仍未公布。 | Q37: 已核准、尚未動工 | R37: 觀察名單 (出租性待確認) | S37: 出租性待確認：議會規劃報告與 Firmus 提交的 DA 規劃報告（2026-05-08 Rev00，Pitt&Sherry／Firmus 網站託管副本）都稱設施主要目的是提供數位處理與資料傳輸基礎設施給『external users』，但 Firmus 自述自建自有自營、運算硬體自有，對外銷售專屬 AI 運算容量／GPU 雲，未見出租機房空間（colocation／powered shell）的公開要約。此站尚無公開客戶。 | T37: 2026-09-15 | U37: 尚無動工證據。George Town Council 2026-08-25 例會（Minute 101/26）以 6 比 1 核准 DA 2026/29（許可證載明：許可須待 14 天上訴期屆滿，或 TASCAT 上訴被撤回／裁決後才生效；有效期 2 年內須實質動工；條件 3 要求動工前更新 bushfire／emergency 計畫並反映 276 台發電機；條件 18 容許分階段建設但須先核定 staging plan）。ABC 2026-09-15 稱已有 5 件 TASCAT 上訴（社區居民數件，加上 Firmus 於 2026-09-10 針對第 13 條發電機使用限制提出的上訴），依許可證註記，上訴裁決前許可不生效，因此目前不得視為可動工。Firmus 官網稱仍須完成能源供應安排；Hydro Tasmania 對 Firmus 444 MW 請求預計 2026 年底前決定。 | V37: 未動工 | W37: 未公布（Baxtel 稱 2027 年啟用、擴建至 2030，聚合器僅供參考） | X37: 完工日未公布 | Y37: aggregator（Baxtel，僅為線索）；官方無時程 | Z37: 待確認 | AA37: 議會規劃報告與 Firmus 提交的 DA 規劃報告（2026-05-08 Rev00，Pitt&Sherry／Firmus 網站託管副本）都稱設施主要目的是提供數位處理與資料傳輸基礎設施給『external users』，但 Firmus 自述自建自有自營、運算硬體自有，對外銷售專屬 AI 運算容量／GPU 雲，未見出租機房空間（colocation／powered shell）的公開要約。此站尚無公開客戶。 | AB37: 此站無公開客戶。Firmus 全公司客戶：未具名全球科技公司（墨爾本）、OpenAI 與 Meta（東南亞）、Fireworks AI（Firmus AI Cloud）。 | AC37: George Town Council DA 2026/29（報告日 2026-08-17；2026-08-25 核准，Minute 101/26）；TASCAT 上訴中 | AD37: 高 | AE37: (1) 備用發電機數量：Firmus 原申報 128 台，後更正為 276 台（ABC 2026-09-15；許可條件 3 要求更新計畫）。(2) 288 MW 為 draw，並非 IT 負載；Firmus 對國會稱三站合計約 444 MW 合約容量、平均運轉約 377 MW。(3) 時程：Baxtel 稱 2027 年啟用、擴建至 2030，官方（Firmus FAQ）未提供時程。(4) 議程報告載『Application Received 2026-06-22』，但同一報告載公告期自 2026-06-13 起，報告內部日期順序不一致。 地址備註：DA 地址為 Lot 1 East Tamar Highway（CT 152001/1，面積 590.7 ha），位於前 Bell Bay Gunns 紙漿廠整地平台、Williams Creek 與 Dirty Bay 之間、鐵路走廊西側，General Industrial 分區；經共用道路及 CT 136962/1、136962/2、11367/6（Crown land）接 East Tamar Highway，與 Forico 木片廠相鄰。Baxtel 寫 1 E Tamar Hwy, Bell Bay。 | AF37: https://georgetown.tas.gov.au/volumes/documents/Shared/Council-Meetings/2026/08.-August-2026/2026-08-25-Ordinary-Council-Meeting-Confirmed-Minutes-Public-Copy.pdf https://georgetown.tas.gov.au/volumes/documents/Shared/Council-Meetings/2026/08.-August-2026/2026-08-25-Ordinary-Council-Meeting-Agenda.pdf https://www.parliament.tas.gov.au/__data/assets/pdf_file/0010/112231/120.-Firmus-combined.pdf https://www.parliament.tas.gov.au/__data/assets/pdf_file/0012/112260/152.-Hydro-Tasmania-Submission.pdf | AG37: https://firmus.co/bell-bay-industrial-precinct-ai-factory-project https://firmus.co/project-southgate-faqs https://firmus.co/ourcommitments/tasmaniancommunity https://cdn.sanity.io/files/q43wife6/production/78b5aa5a9b063a28510338ea87d12d2e79319892.pdf https://cdn.sanity.io/files/q43wife6/production/f83cc940db9392a3e22304614085d6091ac71bcb.pdf | AH37: https://www.abc.net.au/news/2026-08-30/ai-data-centre-tasmania-firmus-technology-george-town/107089468 https://www.abc.net.au/news/2026-09-15/firmus-technologies-lodge-tascat-appeal-for-generator-use/107144572 https://www.abc.net.au/news/2026-09-04/hydro-tasmania-assess-firmus-450-mw-energy-request/107116852 https://w.media/?p=42806 https://pulsetasmania.com.au/news/george-town-planners-recommend-approval-of-288mw-ai-data-centre/ https://www.theleader.com.au/story/9337393/ai-data-centre-approved-despite-community-concerns/ https://www.datacenterdynamics.com/en/news/firmus-targets-288mw-data-campus-in-tasmania/ https://baxtel.com/data-center/firmus-bell-bay-long-reach https://www.datacentermap.com/australia/launceston/firmus-george-town-campus/ | AI37: https://georgetown.tas.gov.au/volumes/documents/Shared/Council-Meetings/2026/08.-August-2026/2026-08-25-Ordinary-Council-Meeting-Confirmed-Minutes-Public-Copy.pdf https://georgetown.tas.gov.au/volumes/documents/Shared/Council-Meetings/2026/08.-August-2026/2026-08-25-Ordinary-Council-Meeting-Agenda.pdf https://www.parliament.tas.gov.au/__data/assets/pdf_file/0010/112231/120.-Firmus-combined.pdf https://www.parliament.tas.gov.au/__data/assets/pdf_file/0012/112260/152.-Hydro-Tasmania-Submission.pdf https://firmus.co/bell-bay-industrial-precinct-ai-factory-project https://firmus.co/project-southgate-faqs https://firmus.co/ourcommitments/tasmaniancommunity https://cdn.sanity.io/files/q43wife6/production/78b5aa5a9b063a28510338ea87d12d2e79319892.pdf https://cdn.sanity.io/files/q43wife6/production/f83cc940db9392a3e22304614085d6091ac71bcb.pdf https://www.abc.net.au/news/2026-08-30/ai-data-centre-tasmania-firmus-technology-george-town/107089468 https://www.abc.net.au/news/2026-09-15/firmus-technologies-lodge-tascat-appeal-for-generator-use/107144572 https://www.abc.net.au/news/2026-09-04/hydro-tasmania-assess-firmus-450-mw-energy-request/107116852 https://w.media/?p=42806 https://pulsetasmania.com.au/news/george-town-planners-recommend-approval-of-288mw-ai-data-centre/ https://www.theleader.com.au/story/9337393/ai-data-centre-approved-despite-community-concerns/ https://www.datacenterdynamics.com/en/news/firmus-targets-288mw-data-campus-in-tasmania/ https://baxtel.com/data-center/firmus-bell-bay-long-reach https://www.datacentermap.com/australia/launceston/firmus-george-town-campus/ | AJ37: 開啟地圖 | AK37: TAS-A
A38: VIC-015 | B38: 維多利亞州 | C38: PAC1 Leakes Road Data Centre（Truganina；ACS/Coravel 體系） | D38: ACS Group 體系（申請人 Leakes Rd DC Pty Ltd，母公司 ACS；ACS 與 GIP 於 2026-07 推出 Coravel 資料中心平台）——依 DCM wiki 轉述 ASIC 文件推定，未經官方證實 | E38: ACS（Actividades de Construcción y Servicios, S.A.）；GIP（BlackRock）——Coravel 50:50 合資（DCD 2026-07-16，已讀） | F38: 114-146 Leakes Road, Truganina VIC 3029 | G38: Truganina | H38: 3029 | I38: Wyndham City Council | J38: -37.83997 | K38: 144.75841 | L38: 門牌級 | M38: 210 | N38: IT 負載 | P38: WSP 雨水報告（2025-03-14，經 DCM wiki 引述）：up to 210 MW IT capacity（240 MVA），含場內 220 kV 變電站並連至 AusNet Altona Terminal Station。DCD：ACS 簡報曾稱澳洲 220 MW；Coravel 稱 1.7 GW（1.2 GW IT）組合橫跨美、歐、澳。 | Q38: 已核准、尚未動工 | R38: 主清單 | T38: 2026-07-09 | U38: Wyndham 規劃許可 WYP15036/25（2025-03-28 提出、2025-09-25 核准，DCM wiki）；S72 修改 .02 審查中。DTP/DFP 許可 PA2504040（AusNet Transmission Group，2025-10-31 受理、2026-02-17 核發、2026-03-03 更正，許可頁已讀）涵蓋 Altona Terminal Station 至「PAC1 Leakes Road Data Centre」的 220 kV 電纜、客戶變電站及終端站工程；AusNet 專案頁（已讀）稱電網工程 2026 年中開工、預計 2027 完成，2026-07-09 公告 7 月中至 12 月施工（DCM wiki）。資料中心本體施工未見證據。 | V38: 電網工程：2026-07（AusNet）；資料中心本體：未確認 | W38: 2027（僅指電網接入）；本體未公布 | X38: 完工日未公布 | Y38: AusNet 專案頁（公用事業，已讀） | Z38: 大概可租 | AA38: Coravel 定位為面向超大規模客戶的開發/營運平台（DCD 報導其德州案已簽約約 140 MW 客戶）；PAC1 租戶未公布，推測批發出租。 | AB38: 未公布 | AC38: Wyndham WYP15036/25（.02 修改審查中）；DTP PA2504040（電網） | AD38: 中 | AE38: 先前資料稱 PAC1 營運商未識別；本次依 DCM wiki（轉述 ASIC 公司文件：申請人 Leakes Rd DC Pty Ltd，母公司 ACS）推定為 ACS/Coravel，DCD 與 GIP 稿證實 ACS 有澳洲約 220 MW 開發組合，但沒有任何官方文件直接寫出 PAC1=ACS。Baxtel 的 Vantage MEL-C 亦標「Leakes Rd」，無證據與此地相同；先前資料稱 PAC1 營運商未識別：本次依 DCM wiki（ASIC 文件）加 DCD 推定為 ACS／Coravel，沒有官方文件直接寫 PAC1 = ACS。Baxtel 另標 Vantage『MEL-C』在 Truganina，無證據與此地相同。 地址備註：Leakes Road 與 Delivery Drive 東北角，約 13.24 公頃，Lot 11 on PS739073B（WSP 雨水報告，經 DCM wiki 引述）。DTP 許可 PA2504040 的土地同時列 130 Cherry Lane, Laverton North（電纜/終端站側）。 | AF38: https://www.planning.vic.gov.au/planning-approvals/ministerial-permits-register/ministerial-permits/62cc5b40-f5b5-f011-bbd2-7ced8d337ed8 https://www.ausnetservices.com.au/projects-and-innovation/major-projects/laverton-north-transmission-works | AH38: https://www.datacenterdynamics.com/en/news/blackrocks-gip-and-acs-name-data-center-joint-venture-coravel-sign-customer-in-texas/ https://www.global-infra.com/news/acs-is-joined-by-global-infrastructure-partners-to-launch-a-global-data-center-development-platform-with-initial-1-7-gw-portfolio/ https://datacentremoratorium.net/index.php/Resources:ACS_Truganina | AI38: https://www.planning.vic.gov.au/planning-approvals/ministerial-permits-register/ministerial-permits/62cc5b40-f5b5-f011-bbd2-7ced8d337ed8 https://www.ausnetservices.com.au/projects-and-innovation/major-projects/laverton-north-transmission-works https://www.datacenterdynamics.com/en/news/blackrocks-gip-and-acs-name-data-center-joint-venture-coravel-sign-customer-in-texas/ https://www.global-infra.com/news/acs-is-joined-by-global-infrastructure-partners-to-launch-a-global-data-center-development-platform-with-initial-1-7-gw-portfolio/ https://datacentremoratorium.net/index.php/Resources:ACS_Truganina https://datacentremoratorium.net/index.php/Resources:Data_Centres_in_Greater_Melbourne | AJ38: 開啟地圖 | AK38: VIC-A、VIC-B
A39: NSW-014 | B39: 新南威爾斯州 | C39: Goodman Project Apollo — Talavera Road Data Centre, Macquarie Park（SSD-74069708） | D39: Goodman（Goodman Property Services (Aust) Pty Limited） | E39: Goodman Property Services (Aust) Pty Limited（申請人） | F39: 4-10 Talavera Road, Macquarie Park NSW 2113 | G39: Macquarie Park | H39: 2113 | I39: City of Ryde | J39: -33.78128 | K39: 151.13067 | L39: 來源提供 | M39: 135 | N39: 耗電量 | P39: 評估報告：總用電最高 135 MW（IT load 未載明）；八個 data halls、GFA 28,878 m2、高 45 m、66×2.8 MW 發電機。Portal 稱「initial load 約 90 MVA」，W.Media/DCD 稱 135 MW。EDC A$1.365bn；施工 400 人、營運 60 人。 | Q39: 已核准、尚未動工 | R39: 主清單 | T39: 2026-09-03 | U39: 核准 2026-09-02（評估報告 2026-09-03 上傳）；Portal 無後審文件。 | V39: 未見 | W39: 評估報告：施工最長約 24 個月（拆除 3、土方 6、岩石開挖與管線 ≤12、結構與設備 3、內裝調試 12 個月，部分重疊）。 | X39: 完工日未公布 | Y39: DPHI SSD Assessment Report（2026-09-03） | Z39: 大概可租 | AA39: Goodman 稱設施「設計為可容納不同租戶需求」，無已知租戶。同意書要求營運前以「firmed renewable」電力補足全部營運用電（PPA + firming），並在施工後 6 個月內提出 PPA 進度證明——是租戶需分攤的成本。 | AB39: 無（W.Media 2026-09-04） | AC39: SSD-74069708（核准 2026-09-02） | AD39: 高 | AE39: 先前：「約 90 MVA initial load；申請人未顯示」→ 申請人為 Goodman，總用電 135 MW；先前資料寫『proponent not shown、約 90 MVA』；W.Media 確認 proponent 為 Goodman，容量 135 MW（Portal 初始 90 MVA 為分階段負載）；先前資料寫約 90 MVA 初始負載且未載明申請人；核准文件明示申請人為 Goodman、最大耗電 135 MW。與 Lane Cove West 的 Apollo Place（）是兩個不同專案 地址備註：基地 23,190 m2，原兩棟倉庫；位於 Macquarie Park TOD 加速重劃區；M2 另一側約 100 m 為最近住宅。 | AF39: https://www.planningportal.nsw.gov.au/major-projects/projects/project-apollo-data-centre-macquarie-park https://majorprojects.planningportal.nsw.gov.au/prweb/PRRestService/mp/01/getContent?AttachRef=SSD-74069708%2120260903T232908.106+GMT | AH39: https://w.media/goodman-wins-approval-for-135mw-macquarie-park-data-centre/ https://bebeez.eu/2026/09/07/goodman-group-gets-green-light-for-135mw-data-center-in-northern-sydney-australia/ https://www.mingtiandi.com/real-estate/data-centres/goodman-group-wins-government-approval-for-1b-data-centre-in-sydneys-north/ https://baxtel.com/data-center/goodman-project-apollo | AI39: https://www.planningportal.nsw.gov.au/major-projects/projects/project-apollo-data-centre-macquarie-park https://majorprojects.planningportal.nsw.gov.au/prweb/PRRestService/mp/01/getContent?AttachRef=SSD-74069708%2120260903T232908.106+GMT https://w.media/goodman-wins-approval-for-135mw-macquarie-park-data-centre/ | AJ39: 開啟地圖 | AK39: NSW-B、NSW-C、NSW-A
A40: NSW-015 | B40: 新南威爾斯州 | C40: Goodman Project Duke — Kent Road, Mascot（SSD-71368959） | D40: Goodman（Goodman Property Services (Aust) Pty Limited） | E40: Goodman Property Services (Aust) Pty Limited（申請人）；地主 Tallina Pty Ltd as Trustee of Goodman Kent Road Trust（DCD） | F40: 2 Kent Road and 10-22 Kent Road, and 685 Gardeners Road, Mascot NSW 2020 | G40: Mascot | H40: 2020 | I40: Bayside | J40: -33.92085 | K40: 151.18384 | L40: 來源提供 | M40: 85 | N40: IT 負載 | P40: 評估報告：總電力需求約 120 MW、IT load 最高 85 MW；九個 data halls、GFA 26,052 m2、高 40 m、72×2.4 MW 發電機。Portal/DCD 稱 90 MVA/90 MW。EDC A$1,177,672,175；施工 600 人、營運 30 人。 | Q40: 已核准、尚未動工 | R40: 主清單 | T40: 2025-12-22 | U40: 核准 2025-12-22；Portal「後審文件」為空（無 CEMP、無開工通知）。 | V40: 未見 | W40: 評估報告：施工最長 110 週（拆除 3 個月、場整 6 個月、地下管線與結構 12 個月、立面與內裝 3 個月、景觀 1 個月）。Baxtel：2028（聚合站，僅線索）。 | X40: 完工日未公布 | Y40: DPHI SSD Assessment Report（2025-12-22） | Z40: 大概可租 | AA40: Goodman 持有土地並自行開發，未見預租；與 Equinix SY4/SY5 同區，鄰近雪梨機場，是市區內少數已核准的大型標的。 | AB40: 未揭露 | AC40: SSD-71368959（核准 2025-12-22） | AD40: 高 | AE40: 容量：Portal 90 MVA、DCD 90 MW、評估報告 120 MW 總用電/85 MW IT。地址：Portal 寫「2 and 10-22 Kent Road」，評估報告另列 685 Gardeners Road；MW 僅有 MVA 口徑且未在 Notice of Decision 驗證；完工年僅聚合站。 地址備註：前 Eaton 倉庫（Goodman 以約 A$76m 購入，DCD）；三面臨 Gardeners Road、Kent Road、Ricketty Street；基地 22,923 m2，離雪梨機場 600 m。 | AF40: https://www.planningportal.nsw.gov.au/major-projects/projects/project-duke-data-centre https://majorprojects.planningportal.nsw.gov.au/prweb/PRRestService/mp/01/getContent?AttachRef=SSD-71368959%2120251222T223948.276+GMT | AH40: https://www.datacenterdynamics.com/en/news/goodman-files-to-build-90mw-data-center-on-eaton-warehouse-site-in-sydney-australia/ https://baxtel.com/data-center/goodman-project-duke | AI40: https://www.planningportal.nsw.gov.au/major-projects/projects/project-duke-data-centre https://majorprojects.planningportal.nsw.gov.au/prweb/PRRestService/mp/01/getContent?AttachRef=SSD-71368959%2120251222T223948.276+GMT https://baxtel.com/data-center/goodman-project-duke | AJ40: 開啟地圖 | AK40: NSW-B、NSW-A
A41: ACT-002 | B41: 首都領地 | C41: CDC Beard 2 (BE2) 資料中心（CDC Beard 園區第二期） | D41: CDC Data Centres（Canberra Data Centres Pty Ltd） | E41: CDC 自建自營（Infratil 為主要股東之一；其餘股東與持股比例本次未查證） | F41: 23 Tantalum Street, Beard ACT 2620 | G41: Beard | H41: 2620 | I41: ACT（無地方政府；ACT 規劃分區 Jerrabomberra district） | J41: -35.340385 | K41: 149.20917 | L41: 來源提供 | M41: 84 | N41: 口徑不明 | P41: ACT 政府 Environmental Significance Opinion（ESO，2026-05-13）與 ESO 申請表寫：12 個 data hall、總容量 84 MW，緊急發電機合計最多 20 MW（容量基準未說明，可能為 IT/critical）；W.Media（2026-09-30）引用同一數字。3 層、GFA 29,924 m2、建築基底約 10,357 m2；工程總成本 A$203,503,000（DA 申請表）。Stantec 噪音報告列 BE2 有 40 台發電機、66 台冷卻機（BE1 為 12 台、16 台），亦顯示 BE2 規模遠大於 BE1。CDC 官網 Canberra 頁 At a glance 寫 250 MW+ capacity（未說明是否含規劃中），並列已運轉 Hume One 21 MW、Hume Two 51 MW、Fyshwick 45 MW。 | Q41: 已核准、尚未動工 | R41: 主清單 | T41: 2026-09-29 | U41: 尚無開工證據。ACT 規劃局於 2026-09-29 依 Planning Act 2023 s185 有條件核准 DA 202645149（登記冊：Decided / Approval Conditional）。核准條件第 2 項：取得 Icon Water Statement of Acceptance/Endorsement 之前不得動工（僅准拆除、除污、開挖、溝渠、管線與公用設施改遷等早期工程）；並須先送 Design Review（早期工程申請須在 Design Review 開始前提出）。Icon Water 在轉介意見中為 Not Supported（設計未通過其水管網保護審查，屬程序性要求：外部服務設計須先取得 in-principle 接受），規劃局以條件 3 處理，登記冊註記本核准偏離了機構意見。Stage 1 時預留的南側約 9,010 m2 空地已因 Beard 1 施工整平、無植被（Development Outcomes Report）。 | V41: 未開工（截至 2026-10-03） | W41: 未公布 | X41: 完工日未公布 | Y41: 無（CDC 未公布）。類比參考：Beard 1 於 2023-10 取得規劃核准，至 2026-03-26 CDC 投資人簡報已標示為運轉中；僅供類比，不代表 BE2 時程。 | Z41: 大概可租 | AA41: CDC 為出租型（託管/批發）資料中心營運商，BE2 屬其 Canberra 園區擴建，但公開資料未提供預租或可租比例。CDC 發言人（Region，2026-09-09）稱聚焦 the most critical customers across government, national critical infrastructure 及其任務關鍵夥伴；CDC 自稱 sovereign-owned and operated，Canberra 園區持有政府託管框架最高等級認證。公開資料未載明是否接受外資或非政府商業租戶，也未見明文的租戶國籍限制；需直接向 CDC 查詢（不作推測）。W.Media（2026-09-16）引述 Infratil：CDC 已部署 350 MW、合約容量合計 1.1 GW，整體容量多已預簽約。 | AB41: 未公開。（CDC 整體：澳洲國防部 2022-08 與 CDC 簽 10 年、A$91.5m 資料中心服務合約，未指明站點。） | AC41: ACT DA 202645149（Notice of Decision 2026-09-29，delegate Aaron Oshyer；ESO 日期 2026-05-13；Crown lease Vol 3017 Folio 455） | AD41: 高 | AE41: 容量：ESO 與 ESO 申請表寫 BE2 為 12 個 data hall、84 MW；Stantec 噪音報告同一份 DA 內卻寫 Beard 1 & 2 將為兩棟各 20-25 MW、10 個 data hall（與 BE2 的 12 hall 不一致，疑為早期簡報殘留文字）。；Beard 1 容量三種說法：Stantec 交通報告 35 MW；cdc.com/au/canberra 39 MW；噪音報告 20-25 MW。；CDC 官網 Canberra 頁（2026-10 讀取）稱 Beard 園區仍是 Currently under construction；但 DA 文件（2026-08）稱 Stage 1 已建成、已運轉，CDC 2026-03-26 投資人簡報也標示 BE1 運轉中。；狀態：Region（2026-09-09）與 Canberra Times（2026-09-06）寫 DA 公眾意見開放至 9/18、尚待審；ACT 登記冊顯示已於 2026-09-29 有條件核准（W.Media 2026-09-30 已報導核准）。；門牌：Baxtel 將 Beard 1 標為 18 Tantalum St；ESO 申請表為 23 Tantalum Street（同一地塊 Block 25 Section 11）；（1）Canberra Times（更新 2026-09-06）稱 Stage 1「已在興建」；CDC 於本 DA 的開發成果報告（2026，隨 DA 提交）稱 Stage 1 已建成，CDC 2026-03-26 簡報亦把 BE1 標為營運中；CDC 官網仍寫 Beard「目前興建中」（官網資料過時）。（2）投資額 A$200m（Region）對 A$203.5m（DatacenterMap/DCD）。（3）84MW 只見於 ESO，CDC 官網與簡報均無 BE2 數字；Region 報導把 20MW 寫成現場發電機容量，與 ESO 的「合計最高 20MW」一致。 地址備註：地塊為 Block 25 Section 11 Beard（Crown lease Vol 3017 Folio 455，約 47,644 m2，與已運轉的 Beard 1 同一地塊）。門牌 23 Tantalum Street 取自 ACT 政府 ESO 申請表（DA 202645149 附件），W.Media 亦同；ACT DA 登記冊只列街名（Tantalum Street, Copper Crescent, Nickel Street）。基地位於 Tantalum Street 與 Nickel Street 轉角，出入口走 Tantalum Street 與 Copper Close/Copper Crescent。Baxtel 把 Beard 1 標為 18 Tantalum St。Canberra Times 標題中的 Jerrabomberra 是 ACT 的 district 名稱，不是 NSW 的 Jerrabomberra 郊區。地塊南端另預留約 3,830 m2 作未來變電站。 | AF41: https://www.planning.act.gov.au/applications-and-assessments/development-applications/browse-das/development-application-details?da-number=202645149 https://dafinder.blob.core.windows.net/dadocuments/DOCs/NOTICEOFDECISION-202645149-SIGNED.pdf https://dafinder.blob.core.windows.net/dadocuments/DOCs/ENVSIGNIFICANCE-202645149-01.pdf https://dafinder.blob.core.windows.net/dadocuments/DOCs/ESO-202645149-APPLICATION_FORM-01.pdf https://dafinder.blob.core.windows.net/dadocuments/DOCs/DEVOUTCOMEREP-202645149-01.pdf https://dafinder.blob.core.windows.net/dadocuments/DOCs/TRAFFICREPORT-202645149-01.pdf https://dafinder.blob.core.windows.net/dadocuments/DOCs/NOISEREPORT-202645149-01.pdf https://dafinder.blob.core.windows.net/dadocuments/DOCs/APP-202645149-04.pdf https://services1.arcgis.com/E5n4f1VY84i0xSjy/arcgis/rest/services/ACTGOV_DAFINDER_LIST_VIEW/FeatureServer/0/query https://www.cmtedd.act.gov.au/open_government/inform/act_government_media_releases/barr/2026/providing-a-clear-framework-for-data-centres-in-the-act https://www.planning.act.gov.au/applications-and-assessments/development-applications/browse-das/development-application-details?da-number=202645149&amendment-version= https://www.planning.act.gov.au/__data/assets/pdf_file/0015/3063102/ESO202600012-Beard-Proposed-Data-Centre-Development-Beard-2.pdf https://www.parliament.act.gov.au/__data/assets/pdf_file/0011/3110060/QTON-080-Answer-CED-ACT-data-centres-energy-consumption-CLAY.pdf | AG41: https://cdc.com/au/canberra https://cdc.com/resources/news/cdc-welcomes-act-governments-data-centre-framework-development/ https://announcements.asx.com.au/asxpdf/20260326/pdf/06xtcw1cnqqc5p.pdf https://cdc.com/locations/canberra | AH41: https://w.media/cdc-wins-approval-for-au203-5m-beard-2-data-centre-in-canberra/ https://region.com.au/new-200-million-data-centre-proposed-for-beard-fits-territory-standards-on-power-and-water/996833/ https://www.canberratimes.com.au/story/9344073/cdc-data-centres-unveil-jerrabomberra-stage-2-ahead-of-new-rules/ https://w.media/data-center-growth-lifts-infratil-earnings-guidance-for-fy-2027/ https://www.planningalerts.org.au/applications/3548117 https://begadistrictnews.com.au/story/9344073/cdc-data-centres-unveil-jerrabomberra-stage-2-ahead-of-new-rules https://www.datacentermap.com/australia/canberra/cdc-beard-be1/ | AI41: https://www.planning.act.gov.au/applications-and-assessments/development-applications/browse-das/development-application-details?da-number=202645149 https://dafinder.blob.core.windows.net/dadocuments/DOCs/NOTICEOFDECISION-202645149-SIGNED.pdf https://dafinder.blob.core.windows.net/dadocuments/DOCs/ENVSIGNIFICANCE-202645149-01.pdf https://dafinder.blob.core.windows.net/dadocuments/DOCs/ESO-202645149-APPLICATION_FORM-01.pdf https://dafinder.blob.core.windows.net/dadocuments/DOCs/DEVOUTCOMEREP-202645149-01.pdf https://dafinder.blob.core.windows.net/dadocuments/DOCs/TRAFFICREPORT-202645149-01.pdf https://dafinder.blob.core.windows.net/dadocuments/DOCs/NOISEREPORT-202645149-01.pdf https://dafinder.blob.core.windows.net/dadocuments/DOCs/APP-202645149-04.pdf https://services1.arcgis.com/E5n4f1VY84i0xSjy/arcgis/rest/services/ACTGOV_DAFINDER_LIST_VIEW/FeatureServer/0/query https://w.media/cdc-wins-approval-for-au203-5m-beard-2-data-centre-in-canberra/ https://region.com.au/new-200-million-data-centre-proposed-for-beard-fits-territory-standards-on-power-and-water/996833/ https://www.canberratimes.com.au/story/9344073/cdc-data-centres-unveil-jerrabomberra-stage-2-ahead-of-new-rules/ https://cdc.com/au/canberra https://cdc.com/resources/news/cdc-welcomes-act-governments-data-centre-framework-development/ https://announcements.asx.com.au/asxpdf/20260326/pdf/06xtcw1cnqqc5p.pdf https://www.cmtedd.act.gov.au/open_government/inform/act_government_media_releases/barr/2026/providing-a-clear-framework-for-data-centres-in-the-act https://w.media/data-center-growth-lifts-infratil-earnings-guidance-for-fy-2027/ https://w.media/canberra-data-centres-signs-a-new-10-year-deal-with-australian-defence/ https://www.planningalerts.org.au/applications/3548117 https://www.planning.act.gov.au/applications-and-assessments/development-applications/browse-das/development-application-details?da-number=202645149&amendment-version= https://dafinder.blob.core.windows.net/dadocuments/DOCs/SUPP-202645149-LETTER-01.pdf https://www.planning.act.gov.au/__data/assets/pdf_file/0015/3063102/ESO202600012-Beard-Proposed-Data-Centre-Development-Beard-2.pdf https://www.parliament.act.gov.au/__data/assets/pdf_file/0011/3110060/QTON-080-Answer-CED-ACT-data-centres-energy-consumption-CLAY.pdf https://services1.arcgis.com/E5n4f1VY84i0xSjy/arcgis/rest/services/ACTGOV_BLOCKS/FeatureServer/0/query https://begadistrictnews.com.au/story/9344073/cdc-data-centres-unveil-jerrabomberra-stage-2-ahead-of-new-rules https://www.datacentermap.com/australia/canberra/cdc-beard-be1/ https://cdc.com/locations/canberra | AJ41: 開啟地圖 | AK41: ACT-A、ACT-B
A42: VIC-016 | B42: 維多利亞州 | C42: PGIM／GDCF Truganina 資料中心園區（1 Oroya Drive；DFP 許可 PA2504032） | D42: PGIM Real Estate（Global Data Center Fund，build-fill-sell 策略）；實際營運商未指定 | E42: The Trust Company (Australia) Limited as trustee of GDCF Truganina Trust（PGIM／Prudential Financial 的 Global Data Center Fund）；申請顧問 Aurecon | F42: 1 Oroya Drive and 435 Mount Atkinson Road, Truganina VIC 3029 | G42: Truganina | H42: 3029 | I42: Melton City Council（DTP 官員報告 Key Information 欄） | J42: -37.776084 | K42: 144.67773 | L42: 來源提供 | M42: 80 | N42: 口徑不明 | O42: 80 | P42: PGIM（Urban Developer 2026-02-17）：初期 80 MW，Morgan Laughlin 稱可建更多但取決於電力供應；園區分三期、首期投資 A$1.2bn。DTP 官員報告：開發價值 A$422m、單棟 8 層（34 m）、GFA 43,356 m²，含三層辦公樓。DFP 許可僅涵蓋首棟。 | Q42: 已核准、尚未動工 | R42: 主清單 | T42: 2026-09-23 | U42: DFP PA2504032：2025-10-28 受理、2026-05-06 核發（Form 4 與官員報告已讀）。realestatesource 2026-09-23 稱 PGIM 取得首棟最終核准。AusNet 另有 PA2604199（Truganina Terminal Station 至場內 220/33 kV 變電站的專線，預計施工 12–18 個月；依 DCM wiki 引述 AusNet 文件，未獨立開啟）。未見開工通知。 | V42: 未公布 | W42: 未公布 | X42: 完工日未公布 | Y42: — | Z42: 可租 | AA42: Mingtiandi：GDCF 採 build-fill-sell 策略，鎖定低延遲超大規模客群，即建成後招租或出售；營運商尚未指定。 | AB42: 未公布 | AC42: DFP PA2504032（permit 2026-05-06）；AusNet 電網 PA2604199（經 DCM wiki） | AD42: 高 | AE42: realestatesource 2026-07-22 寫『AirTrunk 是 1 Oroya Drive 背後的提案（約 1 GW、成本 A$6.45bn）』，與許可申請人（GDCF Truganina Trust）、PGIM 新聞及該媒體 2026-09-23 自家報導矛盾，視為錯誤。官員報告的 A$422m 為首棟建造價值，A$1.2bn 為首期整體投資；80 MW 僅二手轉述（AFR 原文未讀）；地址 1 Oroya Drive（DTP）vs 另含 435 Mount Atkinson Road（DCM wiki）；許可日期與 A$12 億數字取自 先前 的登記冊與 Urban Developer 紀錄，我方僅開啟 Baxtel 與 DatacenterMap，未自行開啟原始來源 地址備註：Riding Boundary Road 與 Oroya Drive 東南角，土地 20.7 ha（PGIM 以 A$165.6m 購入）；預留變電站位於東南角，不在本許可內。 | AF42: https://www.planning.vic.gov.au/planning-approvals/ministerial-permits-register/ministerial-permits/5615befd-9bb3-f011-bbd2-7ced8d337ed8 https://sftpbspomppprod01.blob.core.windows.net/applicationfiles/5615befd-9bb3-f011-bbd2-7ced8d337ed8_PA2504032-1%20Oroya%20Drive%20Truganina%20-%20DTP%20Planning%20Assessment-Officer%20Report.pdf https://sftpbspomppprod01.blob.core.windows.net/applicationfiles/5615befd-9bb3-f011-bbd2-7ced8d337ed8_PA2504032-1%20Oroya%20Drive%20Truganina%20-%20Form%204.pdf https://www.planning.vic.gov.au/planning-approvals/ministerial-permits-register | AH42: https://www.theurbandeveloper.com/articles/us-fund-manager-pgim-buys-truganina-data-centre-site https://www.mingtiandi.com/real-estate/data-centres/pgim-buys-melbourne-site-for-data-centre-campus-plans-850m-first-phase/ https://www.realestatesource.com.au/green-light-for-data-centre-half-the-size-of-the-rialto/ https://archive.is/20260211071111/https://www.afr.com/property/commercial/new-york-funds-giant-to-pour-1-2b-into-melbourne-data-centre-20260211-p5o1es https://datacentremoratorium.net/index.php/Resources:PGIM_Truganina https://baxtel.com/data-center/pgim-melbourne-campus https://www.datacentermap.com/australia/melbourne/1-oroya-drive/ | AI42: https://www.planning.vic.gov.au/planning-approvals/ministerial-permits-register/ministerial-permits/5615befd-9bb3-f011-bbd2-7ced8d337ed8 https://sftpbspomppprod01.blob.core.windows.net/applicationfiles/5615befd-9bb3-f011-bbd2-7ced8d337ed8_PA2504032-1%20Oroya%20Drive%20Truganina%20-%20DTP%20Planning%20Assessment-Officer%20Report.pdf https://www.theurbandeveloper.com/articles/us-fund-manager-pgim-buys-truganina-data-centre-site https://www.mingtiandi.com/real-estate/data-centres/pgim-buys-melbourne-site-for-data-centre-campus-plans-850m-first-phase/ https://www.realestatesource.com.au/green-light-for-data-centre-half-the-size-of-the-rialto/ https://www.realestatesource.com.au/data-centre-giant-buys-350m-melbourne-site/ https://datacentremoratorium.net/index.php/Resources:PGIM_Truganina https://datacentremoratorium.net/index.php/Resources:Data_Centres_in_Greater_Melbourne https://baxtel.com/data-center/pgim-melbourne-campus https://www.datacentermap.com/australia/melbourne/1-oroya-drive/ | AJ42: 開啟地圖 | AK42: VIC-B、VIC-A、VIC-C
A43: NSW-016 | B43: 新南威爾斯州 | C43: Goodman Project Pluto — 132 McCredie Road Data Centre（SSD-69223466） | D43: Goodman（Goodman Property Services (Aust) Pty Ltd） | E43: Goodman Property Services (Aust) Pty Ltd（申請人） | F43: 132 McCredie Road, Guildford West NSW 2161 | G43: Guildford West | H43: 2161 | I43: Cumberland | J43: -33.85113 | K43: 150.95507 | L43: 來源提供 | M43: 68 | N43: IT 負載 | O43: 34 | P43: 評估報告：總用電 100 MW、IT load 68 MW；九個 data halls、兩層（Portal 稱兩棟三層）、GFA 29,444 m2、高 25.8 m、68 台發電機。第一階段 34 MW（五個 data halls），第二階段再加四個 halls 至 68 MW（W.Media 2026-07-24）。EDC A$1,114,474,328；施工 467 人、營運 60 人。 | Q43: 已核准、尚未動工 | R43: 主清單 | T43: 2026-07-24 | U43: 核准 2026-07-23（評估報告 2026-07-24 上傳）；Portal 無任何後審文件（無 CEMP、無開工通知）。 | V43: 未見 | W43: 評估報告：兩階段，每階段 18 個月（受電力可得性分階段）；未公布起始日。 | X43: 完工日未公布 | Y43: DPHI SSD Assessment Report（2026-07-24） | Z43: 大概可租 | AA43: Goodman 稱設施面向超大規模雲端與資料儲存營運商；W.Media 稱無已揭露租戶。為近期核准、尚無已知預租的中大型標的。 | AB43: 無（W.Media 2026-07-24） | AC43: SSD-69223466（核准 2026-07-23） | AD43: 高 | AE43: Portal 標題「load capacity of 126 MW，兩棟三層」vs 評估報告「100 MW 總用電/68 MW IT，兩層」vs W.Media「68 MW」。先前 的 Baxtel「Goodman」歸屬已由評估報告證實；先前資料寫 126 MW 負載、兩棟三層；核准文件為 100 MW、兩層、9 data halls，以核准文件為準 地址備註：前 Castrol 廠址，可開發面積 71,710 m2；Portal 與 先前 拼為「Maccredie」，評估報告為「McCredie」。 | AF43: https://www.planningportal.nsw.gov.au/major-projects/projects/project-pluto-data-centre https://majorprojects.planningportal.nsw.gov.au/prweb/PRRestService/mp/01/getContent?AttachRef=SSD-69223466%2120260724T063200.298+GMT | AH43: https://w.media/nsw-approves-goodmans-aud-1-1bn-project-pluto-data-centre-in-western-sydney/ https://baxtel.com/data-center/goodman-project-pluto | AI43: https://www.planningportal.nsw.gov.au/major-projects/projects/project-pluto-data-centre https://majorprojects.planningportal.nsw.gov.au/prweb/PRRestService/mp/01/getContent?AttachRef=SSD-69223466%2120260724T063200.298+GMT https://w.media/nsw-approves-goodmans-aud-1-1bn-project-pluto-data-centre-in-western-sydney/ | AJ43: 開啟地圖 | AK43: NSW-B、NSW-A
A44: NSW-017 | B44: 新南威爾斯州 | C44: Apollo Place Data Centre（APDC；AirTrunk Lane Cove West 擴建；SSD-67407231） | D44: AirTrunk（核准函收件人：The Trustee for Airtrunk Lane Cove Trust） | E44: EMKC Cubed Management Pty Ltd（SSD 申請人；評估報告稱其為受資料中心營運商委託的地產開發/資產管理公司） | F44: 1 Apollo Place and part of 1 Sirius Road, Lane Cove West NSW 2066 | G44: Lane Cove West | H44: 2066 | I44: Lane Cove | J44: -33.80853 | K44: 151.14529 | L44: 來源提供 | M44: 45 | N44: 耗電量 | P44: 評估報告：總用電 45 MW、IT load 41 MW；四個 data halls、GFA 9,328 m2、高 32.68 m、29×2 MW 發電機；電池/柴油/消防水依賴既有 SYD2 設施。EDC A$288.4m；施工 380 人、營運 44 人。 | Q44: 已核准、尚未動工 | R44: 主清單 | T44: 2026-08-04 | U44: SSD 核准 2025-10-09。DPHI 於 2026-08-04 核准 CEMP Rev E（條件 C2，含 CNVMP、CTMP、ESCP、Unexpected Finds、Remediation Action Plan），收件人為 AirTrunk Lane Cove Trust 的 Carl Nelson——這是開工前置的最後一類文件，但 portal 尚無開工通知。 | V44: 尚未見開工通知；CEMP 2026-08-04 核准後隨時可開工。 | W44: 評估報告：施工最長 94 週（土方 12–16 週 + 施工與內裝 60–80 週）；若 2026 Q4 開工，約 2028 中完工（推算，非官方日期）。 | X44: 完工日未公布 | Y44: DPHI SSD Assessment Report（2025-10-09）；完工日為本報告推算 | Z44: 大概可租 | AA44: 評估報告：由「已有多處雪梨資產、並營運相鄰 Lane Cove West Data Centre 的資料中心營運商」委託擴建，營運商向雲端/內容提供者或政府租戶出租容量；營運商未在報告中點名，AirTrunk 由 CEMP 核准函收件人認定。 | AB44: 未揭露 | AC44: SSD-67407231（核准 2025-10-09）；同意書 SSD-9741 Mod 4 納入 APDC | AD44: 高 | AE44: 先前：「Proponent 未顯示；Baxtel 列 Goodman Project Apollo — 未驗證」——已更正：Apollo Place ≠ Goodman Project Apollo；申請人 EMKC Cubed Management，營運商為 AirTrunk（Lane Cove Trust）。DCD 搜尋摘要寫「AirTrunk 尚未確認」（2024-02，早期），政府文件已證實；先前資料/Baxtel 把 Goodman 的 Project Apollo 對應到此案；實際申請人是 EMKC Cubed Management，Goodman 的 Project Apollo 在 4-10 Talavera Road（）。營運商名稱未公開 地址備註：SP 80721（1 Apollo Place）與 Lot 1 DP 1271404 的東南部分；開發足跡 5,282 m2，併入 44,842 m2 合併基地，緊貼 AirTrunk SYD2（Lane Cove West Data Centre，SSD-9741，1 Sirius Road）；與 Goodman 的 Project Apollo（Macquarie Park）無關。 | AF44: https://www.planningportal.nsw.gov.au/major-projects/projects/apollo-place-data-centre https://majorprojects.planningportal.nsw.gov.au/prweb/PRRestService/mp/01/getContent?AttachRef=SSD-67407231%2120251009T033248.267+GMT https://majorprojects.planningportal.nsw.gov.au/prweb/PRRestService/mp/01/getContent?AttachRef=SSD-67407231-PA-2%2120260804T071034.216+GMT https://www.planningportal.nsw.gov.au/major-projects/projects/lane-cove-west-data-centre-mod-4-apdc-inclusion | AH44: https://datacenterdynamics.com/en/news/45mw-data-center-proposed-next-to-airtrunk-syd2-site | AI44: https://www.planningportal.nsw.gov.au/major-projects/projects/apollo-place-data-centre https://majorprojects.planningportal.nsw.gov.au/prweb/PRRestService/mp/01/getContent?AttachRef=SSD-67407231%2120251009T033248.267+GMT https://majorprojects.planningportal.nsw.gov.au/prweb/PRRestService/mp/01/getContent?AttachRef=SSD-67407231-PA-2%2120260804T071034.216+GMT | AJ44: 開啟地圖 | AK44: NSW-B、NSW-A
A45: NSW-018 | B45: 新南威爾斯州 | C45: Stockland / EdgeConneX — Road 1 Data Centre（Khartoum Road Data Centre Building H；SSD-80814238） | D45: Stockland–EdgeConneX 50:50 合資（推定；與 NSW-B-12 同申請人） | E45: Stockland Development Pty Ltd（SSD 申請人） | F45: 1-5 Khartoum Road (new Road 1 / Road 23 frontage), Macquarie Park NSW 2113 | G45: Macquarie Park | H45: 2113 | I45: City of Ryde | J45: -33.781 | K45: 151.123 | L45: 來源提供 | M45: 34.3 | N45: IT 負載 | P45: 評估報告（2026-10-02）：最大電力 49 MW（IT load 34.3 MW）；八個 data halls、十層、高 72.8 m（Portal 73.4 m）、GFA 13,307 m2；EDC A$630,439,030；施工 250 人。 | Q45: 已核准、尚未動工 | R45: 主清單 | T45: 2026-10-02 | U45: 核准 2026-10-01（評估報告 2026-10-02 上傳）；無後審文件。 | V45: 未定 | W45: 評估報告：施工 30 個月（場整 3 + 主體與道路 24 + 試運轉 3）。 | X45: 完工日未公布 | Y45: DPHI SSD Assessment Report（2026-10-02） | Z45: 大概可租 | AA45: 與 同為 Stockland/EdgeConneX 合資標的（超大規模 + AI 客戶），無已知租戶。 | AB45: 未揭露 | AC45: SSD-80814238（核准 2026-10-01） | AD45: 高 | AE45: 先前：「Road 1 — 申請人未顯示」→ 評估報告證實為 Stockland Development Pty Ltd（Khartoum Road Building H）。IDA 的 Stockland「Project A（City of Ryde）」可能就是本案（2026-03 時尚未核准），但為推測；先前資料寫 34.3 MW；核准文件為 49 MW 總耗電、34.3 MW 為 IT 負載 地址備註：基地 8,096 m2（原倉庫），位於 正南方；Portal 專案先前名稱「1-5 Khartoum Road Building H Data Centre」（舊網址已 301 轉址到 road-1-data-centre）。Portal 地址只寫「Macquarie Park」。 | AF45: https://www.planningportal.nsw.gov.au/major-projects/projects/road-1-data-centre https://majorprojects.planningportal.nsw.gov.au/prweb/PRRestService/mp/01/getContent?AttachRef=SSD-80814238%2120261002T063830.858+GMT | AI45: https://www.planningportal.nsw.gov.au/major-projects/projects/road-1-data-centre https://majorprojects.planningportal.nsw.gov.au/prweb/PRRestService/mp/01/getContent?AttachRef=SSD-80814238%2120261002T063830.858+GMT | AJ45: 開啟地圖 | AK45: NSW-B、NSW-A
A46: NSW-019 | B46: 新南威爾斯州 | C46: Equinix SY10x xScale（Rosehill） | D46: Equinix | E46: Equinix Hyperscale 2 (SY10) Pty Limited（SSD 申請人）；Equinix 與 PGIM Real Estate 合資（PGIM 80%、Equinix 20%，2022-03 成立，US$575m） | F46: 8 Grand Avenue, Rosehill NSW 2142 | G46: Rosehill | H46: 2142 | I46: City of Parramatta | J46: -33.823588 | K46: 151.03355 | L46: 來源提供 | M46: 31.2 | N46: 口徑不明 | P46: 核准文件（2024-12-16）：data centre building with an operational capacity of 31.2 MW；Equinix 2022-06-14 新聞稿：SY10x 完成後逾 28 MW，與 SY9x 合計逾 55 MW。 | Q46: 已核准、尚未動工 | R46: 觀察名單 (出租性待確認) | S46: 出租性待確認：xScale 是 Equinix 與 PGIM 為超大規模客戶建置的長期租約設施，通常由單一或少數大客戶預租；是否向 5 MW 級第三方開放不明。 | T46: 2024-12-16 | U46: 入口網站 SSD-53338465 只有 EIS、RTS、Agency Advice、核准文件，沒有 Management Plans 或 Notifications（無開工通知、CEMP）。Baxtel 標為 Under Construction、2027，屬聚合站且無日期事件。 | V46: 未證實 | W46: 2027（僅 Baxtel；Equinix 未公布） | X46: 完工日未公布 | Y46: Baxtel（聚合站） | Z46: 待確認 | AA46: xScale 是 Equinix 與 PGIM 為超大規模客戶建置的長期租約設施，通常由單一或少數大客戶預租；是否向 5 MW 級第三方開放不明。 | AB46: 未公布 | AC46: SSD-53338465（2024-12-16 核准） | AD46: 中 | AE46: 施工狀態：Baxtel 稱在建（2027），入口網站無任何開工文件；地址：Baxtel 10 Grand Ave，核准文件 8 Grand Avenue；先前：「Equinix xScale SY9x/SY10x 在 Rosehill — mapping unverified」→ 評估報告證實申請人為 Equinix Hyperscale 2 (SY10) Pty Limited，即 SY10x。 地址備註：已解決：核准文件地址 8 Grand Avenue, Rosehill（Lot 10 DP 1275083）。相鄰的 SY9x 為 10 Grand Avenue（Planning Panel PPSSCC-64，DA 2020-07-31 核准，三層）；DataCenterMap 列 SY9x 為 8A Grand Avenue，Baxtel 把 SY10x 列為 10 Grand Ave，與政府文件不符，不採用。 | AF46: https://www.planningportal.nsw.gov.au/major-projects/projects/grand-avenue-data-centre-expansion-rosehill https://www.planningportal.nsw.gov.au/planning-panel/data-centre-4 https://majorprojects.planningportal.nsw.gov.au/prweb/PRRestService/mp/01/getContent?AttachRef=SSD-53338465%2120241216T034941.727+GMT | AG46: https://newsroom.equinix.com/2022-06-14-Equinix-and-PGIM-Real-Estate-Open-First-xScale-TM-Data-Centre-in-Sydney-for-Hyperscalers | AH46: https://baxtel.com/data-center/equinix-sy10x | AI46: https://www.planningportal.nsw.gov.au/major-projects/projects/grand-avenue-data-centre-expansion-rosehill https://www.planningportal.nsw.gov.au/planning-panel/data-centre-4 https://newsroom.equinix.com/2022-06-14-Equinix-and-PGIM-Real-Estate-Open-First-xScale-TM-Data-Centre-in-Sydney-for-Hyperscalers https://baxtel.com/data-center/equinix-sy10x https://majorprojects.planningportal.nsw.gov.au/prweb/PRRestService/mp/01/getContent?AttachRef=SSD-53338465%2120241216T034941.727+GMT | AJ46: 開啟地圖 | AK46: NSW-A、NSW-B
A47: NSW-020 | B47: 新南威爾斯州 | C47: DCI CBR01 — DCI Poplars Data Centre Project（Poplars Innovation Precinct, Jerrabomberra） | D47: DCI Data Centers（The Trustee for NineZero DC Sub Trust I, trading as DCI Data Centers） | E47: DCI Data Centers；用地位於 Poplars Innovation Precinct Stage 1（地主未於文件具名） | F47: 2 Wolseley Place, Jerrabomberra NSW 2620 | G47: Jerrabomberra | H47: 2620 | I47: Queanbeyan-Palerang Regional | J47: -35.3814 | K47: 149.1935 | L47: 來源提供 | M47: 20 | N47: IT 負載 | O47: 8 | P47: 核准報告：五個資料廳，分三階段 8 MW（兩廳）+ 4 MW（一廳）+ 8 MW（兩廳）IT，共 20 MW IT；最大電力容量（power capacity）25.4 MW；GFA 5,826 m2；16 台 2 MW 柴油備用發電機；投資額 A$2.78 億；施工職缺 125。2022 年新聞稱 CBR01 為 20 MW、Tier III、走獨立 132 kV Essential Energy 電網。 | Q47: 已核准、尚未動工 | R47: 主清單 | T47: 2025-11-06 | U47: Planning Portal（2026-10-03 讀取）：已核准，Determination Date 2025-11-06（Director），Instrument of Consent 上傳 2025-12-08；『Approved Documents』欄顯示『There are no post approval documents available』— 無 CEMP／開工通知，無施工證據。 | V47: 未見 | W47: 未公布 | X47: 完工日未公布 | Y47: — | Z47: 可租 | AA47: 核准報告：『The Applicant will lease space within the data halls to its tenant/s』，租戶自行裝修；2022 年新聞定位為服務聯邦政府／公有雲工作負載的 Canberra 邊緣雲資料中心。 | AB47: 無公開租戶 | AC47: SSD-64287712（2025-11-06 核准） | AD47: 高 | AE47: Portal 將本案開發類型歸為『Warehouse or distribution centres』，因此不在 先前 以 Data Storage 篩選得到的 50 筆清單內（先前資料 未收錄）。容量三種口徑：IT 20 MW（分階段 8+4+8）、最大電力 25.4 MW、2022 新聞 20 MW；此案不在先前資料的 50 筆 Data Storage 清單內（入口網站歸類為 Warehouse or distribution centres），為新發現；營運商為推定 地址備註：Lot 6 DP 1288362，4.05 ha，B7 Business Park 用地；北接 Tompsitt Drive、東接 Environa Drive、Wolseley Place 為基地邊界道路；鄰近 Canberra 機場與 ACT 邊界（核准報告稱 ACT 邊界在 Poplars Grassland Reserve 以西）。 | AF47: https://www.planningportal.nsw.gov.au/major-projects/projects/dci-poplars-data-centre-project-0 | AH47: https://w.media/dci-to-build-20-mw-cloud-edge-data-centre-in-canberra/ | AI47: https://www.planningportal.nsw.gov.au/major-projects/projects/dci-poplars-data-centre-project-0 https://w.media/dci-to-build-20-mw-cloud-edge-data-centre-in-canberra/ | AJ47: 開啟地圖 | AK47: NSW-C、NSW-A
A48: SA-003 | B48: 南澳州 | C48: DCI Adelaide 03（ADL03）— Technology Park, Mawson Lakes | D48: DCI Data Centers（DCI 澳紐業務） | E48: DCI Data Centers；官網（2026-10-03 讀取）仍稱為 Brookfield Asset Management 基礎建設事業的 portfolio company | F48: Technology Park, Mawson Lakes SA 5095 | G48: Mawson Lakes | H48: 5095 | I48: City of Salisbury（依郊區推定，未由規劃文件確認） | J48: -34.81048 | K48: 138.61118 | L48: 郊區級（近似） | M48: 8 | N48: IT 負載 | Q48: 已核准、尚未動工 | R48: 觀察名單 (出租性待確認) | S48: 2021 年取得 DA 後無任何更新，MW 僅有二手來源，信心低。 | T48: 2021-08 | U48: 無動工證據。2021-08-30/31 DCI 宣布購得土地並取得 Development Approval，稱 further announcements over the coming months；之後未見 2022 至 2026 的動工、竣工或規格更新。DCI 官網 locations 頁（2026-10-03 讀取）仍把 ADL03 列在 Under Development（We are developing ADL03 data centre），連結回 2021-08 新聞稿。南澳 DA 通常有失效期限，本案核准已五年，是否仍有效、是否展延或已實質開工均未能查證。 | V48: 未知（未見任何公告） | W48: 未公布 | X48: 完工日未公布 | Y48: 無。DCI 2021-08 新聞稿未提時程；其後無更新。Baxtel 仍標 Planned | Z48: 大概可租 | AA48: DCI 以 Tier-Ready / Tier III 的 secure cloud edge colocation 面向國防、政府與高科技客戶（ADL01/ADL02 為同模式），ADL03 定位相同；但無預租或租戶公告。 | AB48: 未揭露 | AC48: City of Salisbury 2021 年 DA（案號未取得） | AD48: 低 | AE48: (1) MW：8 MW 只來自 Data Centre Magazine 搜尋摘要，DCI 官網未列。(2) 擁有權：主管備忘稱 DCI 為印尼持有，但 DCI 官網 2026-10-03 仍寫 Brookfield portfolio company，W.Media 2025-03-31 訪談也提到 Brookfield 延攬其 CEO，疑似與 PT DCI Indonesia 混淆，未能證實是否另有 2026 年出售。(3) 核准時效：2021 年的 DA 是否仍有效未知；(1) 所有權：DCD 2021 稱 Brookfield 旗下，主管備忘稱印尼持有。(2) 聚合器對 DCI 其他設施的 MW 不一（ADL02：DCI 官方 4 MW IT，Baxtel 6 MW，RenewMap 10 MW），顯示聚合器 MW 不可靠。(3) 2021 年 DA 的有效性與進度無第一手資料。 地址備註：只知道在 Mawson Lakes 的 Technology Park（DCI 官網稱 Mawson Lakes site, Adelaide's defence precinct）。未找到 lot、街名或街號；DA 文件在 PlanSA（被 Cloudflare 擋下）。DCI 於 2021-08 宣布已購地並取得 Development Approval。 | AG48: https://dcidatacenters.com/locations/ https://dcidatacenters.com/news/adelaide-new-digital-infrastructure/ https://www.dcidatacenters.com/locations/ https://www.dcidatacenters.com/news/adelaide-new-digital-infrastructure/ | AH48: https://baxtel.com/news/1051 https://baxtel.com/data-center/dci-adelaide-adl03 https://datacentremagazine.com/data-centres/dci-commits-8-mw-high-security-data-centre-adelaide https://www.indailysa.com.au/news/archive/2021/08/30/new-data-centres-to-boost-sas-it-capacity https://itwire.com/business-it-news/data-centres/dci-data-centre-constructs-new-centre-in-south-australia https://thetechcapital.com/brookfields-dci-invests-in-further-australian-data-centre-expansions/ https://w.media/dci-data-centers-to-build-10mw-data-centre-in-darwin-australia/ https://www.datacenterdynamics.com/en/news/dci-acquires-land-for-third-adelaide-data-center/ https://www.datacenters.com/dci-adelaide-03 https://baxtel.com/sites/dci-adelaide-adl03 | AI48: https://dcidatacenters.com/locations/ https://dcidatacenters.com/news/adelaide-new-digital-infrastructure/ https://dcidatacenters.com/ https://baxtel.com/news/1051 https://baxtel.com/data-center/dci-adelaide-adl03 https://baxtel.com/data-center/dci-adelaide/news https://www.indailysa.com.au/news/archive/2021/08/30/new-data-centres-to-boost-sas-it-capacity https://itwire.com/business-it-news/data-centres/dci-data-centre-constructs-new-centre-in-south-australia https://www.techpartner.news/news/dci-reveals-new-data-centre-plans-for-sa-569291 https://thetechcapital.com/brookfields-dci-invests-in-further-australian-data-centre-expansions/ https://w.media/dci-data-centers-to-build-10mw-data-centre-in-darwin-australia/ https://w.media/the-impact-of-ai-on-digital-infrastructure-sumit-mukhija-chief-executive-officer-dci-data-centers/ https://w.media/dcis-sumit-mukhija-why-certainty-matters-more-than-megawatts/ https://www.dcidatacenters.com/locations/ https://www.dcidatacenters.com/news/adelaide-new-digital-infrastructure/ https://www.dcidatacenters.com/news/adl02-launch/ https://www.datacenterdynamics.com/en/news/dci-acquires-land-for-third-adelaide-data-center/ https://www.datacenters.com/dci-adelaide-03 https://renewalsa.sa.gov.au/projects/technology-park-adelaide | AJ48: 開啟地圖 | AK48: SA-A、SA-B
A49: NSW-021 | B49: 新南威爾斯州 | C49: Southern Highlands Data Campus (SHDC) — Data Building Two (DB2) | D49: Cloud Carrier (Cloud Carrier Operations Pty Ltd) | E49: Nakar Property Pty Ltd | F49: 30 Douglas Road, Moss Vale NSW 2577 | G49: Moss Vale | H49: 2577 | I49: Wingecarribee Shire | J49: -34.515334 | K49: 150.36982 | L49: 門牌級 | M49: 未公布 | N49: 口徑不明 | P49: DB2 容量未公布；為三層樓資料儲存建築及戶外設備（DA 25/2158）。DB1 為 28 MW 可作參考但不可直接推定；官網標示 DB2『coming soon』。列入是因園區規模明顯 >5 MW（園區規劃至 300 MW）。 | Q49: 已核准、尚未動工 | R49: 主清單 | T49: 2025-09-22 | U49: 無施工證據。範疇界定報告：DA 25/2158 於 2025-04-14 遞交，『approved to proceed on 22 September 2025』（措辭含糊，我方未能在 Wingecarribee 議會 DA 登記冊核實）。 | V49: 未見 | W49: 未公布（官網：coming soon） | X49: 完工日未公布 | Y49: Cloud Carrier 官網 DB2 (coming soon) | Z49: 可租 | AA49: 與 DB1 相同的 powered shell／colocation 模式。 | AB49: 未公開 | AC49: Wingecarribee Council DA 25/2158（報告稱 2025-09-22 核准） | AD49: 中 | AE49: 核准字樣只出現在申請人自撰的範疇界定報告，未經議會登記冊核實。 地址備註：與 DB1 同一園區地址（Lot 40 DP 1288692）。 | AF49: https://www.planningportal.nsw.gov.au/major-projects/projects/southern-highlands-data-campus-power-station https://majorprojects.planningportal.nsw.gov.au/prweb/PRRestService/mp/01/getContent?AttachRef=PDA-95012491%2120250926T033914.129+GMT | AG49: https://cloudcarrier.com/campus/ https://cloudcarrier.com/ | AH49: https://w.media/cloud-carrier-launches-australias-first-liquid-cooled-data-campus-in-the-southern-highlands/ | AI49: https://www.planningportal.nsw.gov.au/major-projects/projects/southern-highlands-data-campus-power-station https://majorprojects.planningportal.nsw.gov.au/prweb/PRRestService/mp/01/getContent?AttachRef=PDA-95012491%2120250926T033914.129+GMT https://cloudcarrier.com/ | AJ49: 開啟地圖 | AK49: NSW-C
A50: VIC-017 | B50: 維多利亞州 | C50: MAB Haystone 工業園區內的資料中心地塊（Westmeadows；DFP 許可 PA2302143） | D50: 未指定（用地開發商 MAB；申請人 MAB） | E50: MAB Corporation | F50: 140-204 Western Avenue, Westmeadows VIC 3049 | G50: Westmeadows | H50: 3049 | I50: Hume City Council | J50: -37.681718 | K50: 144.87397 | L50: 街道級 | M50: 未公布 | N50: 口徑不明 | P50: 無任何 MW 或營運商資料。許可（Form 9，依 Watson Young 2022-06 圖面 TP01–TP15）准許公用設施（資料中心）用途與建築工程。規模無法判斷是否達 5 MW，列為低信心線索。 | Q50: 已核准、尚未動工 | R50: 觀察名單 (出租性待確認) | S50: 出租性待確認：僅有用途許可；是否由 MAB 出售地塊予營運商或自建招租皆未知。 | T50: 2024-07-12 | U50: Hume 規劃修訂 C269hume 與組合許可（s96I）：2023-03-29 受理，Form 9 簽發 2023-12-08，登記冊決定日 2023-12-21。MAB 2024-07 起銷售 Haystone 地塊。未見任何資料中心開工證據。 | V50: 未公布 | W50: 未公布 | X50: 完工日未公布 | Y50: — | Z50: 待確認 | AA50: 僅有用途許可；是否由 MAB 出售地塊予營運商或自建招租皆未知。 | AB50: 未公布 | AC50: DFP PA2302143（Hume C269hume；Form 9 2023-12-08；登記冊決定 2023-12-21） | AD50: 低 | AE50: 地址備註：Lot 1 & 2 TP512682；前 Cleanaway 有毒廢棄物掩埋場緩衝地，Haystone 工業園區約 38–41 ha，鄰 Melbourne Airport；資料中心為園區內一宗約 3 ha 的大地塊（realestatesource）。 | AF50: https://www.planning.vic.gov.au/planning-approvals/ministerial-permits-register/ministerial-permits/6bac05e8-144c-404a-b7b2-b9e5445cb849 https://sftpbspomppprod01.blob.core.windows.net/applicationfiles/6bac05e8-144c-404a-b7b2-b9e5445cb849_C269hume%20-PA2302143%20-%20140-204%20Western%20Avenue%20Westmeadows%20-%20Data%20Centre%20-%20Form%209%20-%20APPROVAL%20FINAL%20.pdf | AH50: https://www.realestatesource.com.au/mab-wins-long-battle-to-develop-tip-buffer-site/ https://www.mab.com.au/projects/business-parks/haystone/ https://datacentremoratorium.net/index.php/Resources:MAB_Westmeadows | AI50: https://www.planning.vic.gov.au/planning-approvals/ministerial-permits-register/ministerial-permits/6bac05e8-144c-404a-b7b2-b9e5445cb849 https://sftpbspomppprod01.blob.core.windows.net/applicationfiles/6bac05e8-144c-404a-b7b2-b9e5445cb849_C269hume%20-PA2302143%20-%20140-204%20Western%20Avenue%20Westmeadows%20-%20Data%20Centre%20-%20Form%209%20-%20APPROVAL%20FINAL%20.pdf https://www.realestatesource.com.au/mab-wins-long-battle-to-develop-tip-buffer-site/ https://datacentremoratorium.net/index.php/Resources:MAB_Westmeadows | AJ50: 開啟地圖 | AK50: VIC-B、VIC-A
A51: VIC-018 | B51: 維多利亞州 | C51: Perri Melbourne Data Centre（PMDC，West Footscray；DFP 許可 PA2403320） | D51: 未指定（開發商 Perri Projects；未見營運商或租戶） | E51: Central Godown Pty Ltd（董事 David Scalzo，Perri Projects）與 Albert Kennedy Pty Ltd 共有土地；申請顧問 Contour Consultants Aust Pty Ltd；建築師 Greenbox Architects | F51: 63 Sunshine Road and 1 McArthur Street, West Footscray VIC 3012 | G51: West Footscray | H51: 3012 | I51: Maribyrnong City Council | J51: -37.801296 | K51: 144.8698 | L51: 門牌級 | M51: 未公布 | N51: 口徑不明 | P51: 官方文件無 MW。DTP 官員報告：4 層（17.6–19.6 m）、GFA 約 28,698 m²、三個資料廳（地面、1 樓、2 樓各一）、地下室柴油儲存約 510 kL、營運人員 150 FTE；Urban Developer：開發成本 A$800m、完工價值 A$1bn。柴油量與樓板規模顯示遠超 5 MW，但無法換算 MW。 | Q51: 已核准、尚未動工 | R51: 觀察名單 (出租性待確認) | S51: 出租性待確認：規模與 DFP 路徑顯示為商業資料中心，但未見營運商、租戶或出租模式。 | T51: 2025-12-17 | U51: DFP PA2403320：2024-11-02 受理（公告 2025-01-08 至 22）；WorkSafe 於 2024-12-18 先反對、2025-03-04 附條件同意；2025-04-04 核發；PA2403320-1（建築高度增加 1.92 m）2025-12-17 核准。ABC 2026-06-09 與 realestate.com.au 2026-09-24 均稱已核准；未見開工證據。 | V51: 未公布 | W51: 未公布 | X51: 完工日未公布 | Y51: — | Z51: 待確認 | AA51: 規模與 DFP 路徑顯示為商業資料中心，但未見營運商、租戶或出租模式。 | AB51: 未公布 | AC51: DFP PA2403320（-1 修訂 2025-12-17）；Maribyrnong 分割許可（編號未取得）；TP331/2022(1)（前案進出道路） | AD51: 高 | AE51: 先前資料 將 PA2403320 標為 NEXTDC M3（申請人 Contour Consultants）：錯誤。申請人為 Central Godown Pty Ltd（Perri Projects），官員報告明載鄰近的 Next DC Melbourne data centre 位於 Indwe Street 與 Cala Street 轉角，NEXTDC M3 擴建另為 PA2604231；先前資料 將 PA2403320 歸為 NEXTDC M3（申請人 Contour Consultants）——本次無法證實：申請人是規劃顧問，許可與官員報告未提 NEXTDC；NEXTDC M3 的 DFP 申請是 PA2604231。 地址備註：Goldsbrough Mort 羊毛倉庫（遺產登錄）後方空地，Sunshine Road／McArthur Street／Indwe Street 之間，約 2.72 ha；距 Tottenham 站約 600 m。與 NEXTDC M3（Indwe Street 與 Cala Street 轉角）相隔約一個街區，不是同一專案。 | AF51: https://www.planning.vic.gov.au/planning-approvals/ministerial-permits-register/ministerial-permits/fcb0d877-0b98-ef11-8a68-002248938a9c https://sftpbspomppprod01.blob.core.windows.net/applicationfiles/fcb0d877-0b98-ef11-8a68-002248938a9c_DTP%20Planning%20Assessment-Officer%20Report%20-%20PA2403320%20-%2063%20Sunshine%20Road%20West%20Footscray.pdf%20-%20Redacted.pdf https://sftpbspomppprod01.blob.core.windows.net/applicationfiles/fcb0d877-0b98-ef11-8a68-002248938a9c_Planning%20Permit%20-%20PA2403320%20-%2063%20Sunshine%20Road%20West%20Footscray.pdf | AH51: https://www.theurbandeveloper.com/articles/data-centre-perri-projects-victoria-west-footscray https://www.datacenterdynamics.com/en/news/data-center-planned-for-former-woolstore-in-west-melbourne-australia/ https://www.abc.net.au/news/2026-06-09/firefighter-concern-over-data-centres-in-melbourne-west/106762858 https://www.realestate.com.au/news/west-footscray-data-centre-deters-homebuyers/ https://datacentremoratorium.net/index.php/Resources:Perri_Melbourne_Data_Centre_(PMDC) | AI51: https://www.planning.vic.gov.au/planning-approvals/ministerial-permits-register/ministerial-permits/fcb0d877-0b98-ef11-8a68-002248938a9c https://sftpbspomppprod01.blob.core.windows.net/applicationfiles/fcb0d877-0b98-ef11-8a68-002248938a9c_DTP%20Planning%20Assessment-Officer%20Report%20-%20PA2403320%20-%2063%20Sunshine%20Road%20West%20Footscray.pdf%20-%20Redacted.pdf https://sftpbspomppprod01.blob.core.windows.net/applicationfiles/fcb0d877-0b98-ef11-8a68-002248938a9c_Planning%20Permit%20-%20PA2403320%20-%2063%20Sunshine%20Road%20West%20Footscray.pdf https://www.theurbandeveloper.com/articles/data-centre-perri-projects-victoria-west-footscray https://www.datacenterdynamics.com/en/news/data-center-planned-for-former-woolstore-in-west-melbourne-australia/ https://www.abc.net.au/news/2026-06-09/firefighter-concern-over-data-centres-in-melbourne-west/106762858 https://www.realestate.com.au/news/west-footscray-data-centre-deters-homebuyers/ https://datacentremoratorium.net/index.php/Resources:Perri_Melbourne_Data_Centre_(PMDC) | AJ51: 開啟地圖 | AK51: VIC-B、VIC-A
A52: VIC-019 | B52: 維多利亞州 | C52: STACK MEL03（Tarneit，1005 Boundary Road；STACK 身分為推定；Wyndham 許可 WYP15464/25） | D52: STACK Infrastructure（推定，尚未正式宣布） | E52: 未知（申請顧問 Tract Consultants，亦為 MEL02 的顧問） | F52: 1005 Boundary Road, Tarneit VIC 3029 | G52: Tarneit | H52: 3029 | I52: Wyndham City Council | J52: -37.802318 | K52: 144.67166 | L52: 街道級 | M52: 未公布 | N52: 口徑不明 | P52: MW 未公布。DCM wiki 引述雨水計畫（ACOR）：4 棟、各 3 層（約 32.5 m）、4 座變電站、280 kW 太陽能；規模遠超 5 MW 門檻。 | Q52: 已核准、尚未動工 | R52: 觀察名單 (出租性待確認) | S52: 出租性待確認：營運商身分未證實。 | T52: 2026-06-19 | U52: Wyndham WYP15464/25：2025-12-19 提出（用途為公用設施（資料中心）），2026-06-19 核准（依 DCM wiki 整理 Wyndham 入口網站；入口網站需登入，未能獨立開啟）。尚無開工證據。 | V52: 未公布 | W52: 未公布 | X52: 完工日未公布 | Y52: — | Z52: 待確認 | AA52: 營運商身分未證實。 | AB52: 未公布 | AC52: Wyndham WYP15464/25；分割 WYP15630/26（經 DCM wiki） | AD52: 低 | AE52: STACK 身分僅憑申請顧問推定；DCM wiki 自述 STACK 尚未正式宣布 MEL03；STACK 身分只憑申請代理人 Tract Consultants（亦為 MEL02 的代理人）推定；DCM wiki 自述 STACK 尚未正式宣布 MEL03。 地址備註：DCM wiki 引 Wyndham 申請 WYP15464/25 與 ACOR 雨水管理計畫；位於 Tarneit Logistics Hub 東側待細分地塊（細分案 WYP15630/26）。 | AF52: https://www.planning.vic.gov.au/planning-approvals/ministerial-permits-register/ministerial-permits/3445e501-ef0a-f111-8406-7ced8da0d89a | AH52: https://datacentremoratorium.net/index.php/Resources:STACK_MEL03_Campus https://www.charterhall.com.au/tarneit | AI52: https://www.planning.vic.gov.au/planning-approvals/ministerial-permits-register/ministerial-permits/3445e501-ef0a-f111-8406-7ced8da0d89a https://datacentremoratorium.net/index.php/Resources:STACK_MEL03_Campus | AJ52: 開啟地圖 | AK52: VIC-B、VIC-A
